Workbook

Sheet RAW_DATA
A1: Job_ID | B1: Date_Collected | C1: Source_Portal | D1: Job_Title | E1: Company | F1: City | G1: Experience_Min(years) | H1: Experience_Max(years) | I1: Salary_Min(LPA) | J1: Salary_Max(LPA) | K1: Raw_Skills_Text | L1: Good_To_Have_Skills | M1: Remote_Option | N1: Company_Size | O1: SQL | P1: Python | Q1: PowerBI | R1: Tableau | S1: Excel | T1: Statistics | U1: AWS | V1: GCP | W1: NoSQL | X1: Data Modeling | Y1: Pandas | Z1: Numpy | AA1: Pyspark | AB1: Hadoop | AC1: ETL | AD1: Azure | AE1: Databricks | AF1: A/B Testing | AG1: Snowflake | AH1: Agile | AI1: Jira | AJ1: Git & Github | AK1: MIS Reporting | AL1: CI/CD | AM1: Python_pref | AN1: SQL_pref | AO1: Airflow_pref | AP1: Kafka_pref | AQ1: ML_pref | AR1: API_pref | AS1: Docker_pref | AT1: dbt_pref | AU1: AWS_pref | AV1: GCP_pref | AW1: Azure_pref | AX1: Tableau_pref | AY1: PowerBI_pref | AZ1: Employment_Type
A2: 1 | B2: 46178 | C2: LinkedIn | D2: Data Analyst | E2: Acko | F2: Bengaluru | G2: 4 | H2: 6 | I2: ND | J2: ND | K2: Amplitude, Mixpanel, Tableau, A/B Testing, SQL, Python, pandas, NumPy, Data Modelling, Star Schema, Snowflake Schema, Excel, Product Analytics, Funnel Analysis, Behavioral Segmentation | L2: ML Concepts | M2: ND | N2: Startup | O2: =IF(ISBLANK(K2),0,IF(ISNUMBER(SEARCH("sql",K2)),1,0)) -> 1 | P2: =IF(ISBLANK(K2),0,IF(ISNUMBER(SEARCH("Python",K2)),1,0)) -> 1 | Q2: =IF(ISBLANK(K2),0,IF(ISNUMBER(SEARCH("PowerBI",K2)),1,0)) -> 0 | R2: =IF(ISBLANK(K2),0,IF(ISNUMBER(SEARCH("Tableau",K2)),1,0)) -> 1 | S2: =IF(ISBLANK(K2),0,IF(ISNUMBER(SEARCH("Excel",K2)),1,0)) -> 1 | T2: =IF(ISBLANK(K2),0,IF(ISNUMBER(SEARCH("Statistics",K2)),1,0)) -> 0 | U2: =IF(ISBLANK(K2),0,IF(ISNUMBER(SEARCH("AWS",K2)),1,0)) -> 0 | V2: =IF(ISBLANK(K2),0,IF(ISNUMBER(SEARCH("GCP",K2)),1,0)) -> 0 | W2: =IF(ISBLANK(K2),0,IF(ISNUMBER(SEARCH("NoSQL",K2)),1,0)) -> 0 | X2: =IF(ISBLANK(K2),0,IF(ISNUMBER(SEARCH("Data Modeling",K2)),1,0)) -> 0 | Y2: =IF(ISBLANK(K2),0,IF(ISNUMBER(SEARCH("Pandas",K2)),1,0)) -> 1 | Z2: =IF(ISBLANK(K2),0,IF(ISNUMBER(SEARCH("Numpy",K2)),1,0)) -> 1 | AA2: =IF(ISBLANK(K2),0,IF(ISNUMBER(SEARCH("Pyspark",K2)),1,0)) -> 0 | AB2: =IF(ISBLANK(K2),0,IF(ISNUMBER(SEARCH("Hadoop",K2)),1,0)) -> 0 | AC2: =IF(ISBLANK(K2),0,IF(ISNUMBER(SEARCH("ETL",K2)),1,0)) -> 0 | AD2: =IF(ISBLANK(K2),0,IF(ISNUMBER(SEARCH("Azure",K2)),1,0)) -> 0 | AE2: =IF(ISBLANK(K2),0,IF(ISNUMBER(SEARCH("Databricks",K2)),1,0)) -> 0 | AF2: =IF(ISBLANK(K2),0,IF(ISNUMBER(SEARCH("A/B Testing",K2)),1,0)) -> 1 | AG2: =IF(ISBLANK(K2),0,IF(ISNUMBER(SEARCH("Snowflake",K2)),1,0)) -> 1 | AH2: =IF(ISBLANK(K2),0,IF(ISNUMBER(SEARCH("Agile",K2)),1,0)) -> 0 | AI2: =IF(ISBLANK(K2),0,IF(ISNUMBER(SEARCH("Jira",K2)),1,0)) -> 0 | AJ2: =IF(ISBLANK(K2),0,IF(ISNUMBER(SEARCH("Git",K2)),1,0)) -> 0 | AK2: =IF(ISBLANK(K2),0,IF(ISNUMBER(SEARCH("Reporting",K2)),1,0)) -> 0 | AL2: =AM2 -> 0 | AM2: =AN5 -> 0 | AN2: =IF(ISBLANK(L2),0,IF(ISNUMBER(SEARCH("SQL",L2)),1,0)) -> 0 | AO2: =IF(ISBLANK(L2),0,IF(ISNUMBER(SEARCH("Airflow",L2)),1,0)) -> 0 | AP2: =IF(ISBLANK(L2),0,IF(ISNUMBER(SEARCH("Kafka",L2)),1,0)) -> 0 | AQ2: =AR3 -> 0 | AR2: =IF(ISBLANK(L4),0,IF(ISNUMBER(SEARCH("API",L4)),1,0)) -> 0 | AS2: =IF(ISBLANK(L4),0,IF(ISNUMBER(SEARCH("Docker",L4)),1,0)) -> 0 | AT2: =IF(ISBLANK(L4),0,IF(ISNUMBER(SEARCH("dbt",L4)),1,0)) -> 0 | AU2: =IF(ISBLANK(L4),0,IF(ISNUMBER(SEARCH("AWS",L4)),1,0)) -> 0 | AV2: =IF(ISBLANK(L4),0,IF(ISNUMBER(SEARCH("GCP",L4)),1,0)) -> 0 | AW2: =IF(ISBLANK(L4),0,IF(ISNUMBER(SEARCH("Azure",L4)),1,0)) -> 0 | AX2: =IF(ISBLANK(M4),0,IF(ISNUMBER(SEARCH("Tableau",L4)),1,0)) -> 0 | AY2: =IF(ISBLANK(N4),0,IF(ISNUMBER(SEARCH("PowerBI",L4)),1,0)) -> 0 | AZ2: Fulltime
A3: 2 | B3: 46178 | C3: LinkedIn | D3: Data Analyst | E3: Dassault Systemes | F3: Bengaluru | G3: 3 | H3: 5 | I3: ND | J3: ND | K3: Python , Java, Oracle SQL, Adavnced Excel , BI & dashboards , Data Visulaization & KPI reporting | L3: None | M3: ND | N3: Small | O3: =IF(ISBLANK(K3),0,IF(ISNUMBER(SEARCH("sql",K3)),1,0)) -> 1 | P3: =IF(ISBLANK(K3),0,IF(ISNUMBER(SEARCH("Python",K3)),1,0)) -> 1 | Q3: =IF(ISBLANK(K3),0,IF(ISNUMBER(SEARCH("PowerBI",K3)),1,0)) -> 0 | R3: =IF(ISBLANK(K3),0,IF(ISNUMBER(SEARCH("Tableau",K3)),1,0)) -> 0 | S3: =IF(ISBLANK(K3),0,IF(ISNUMBER(SEARCH("Excel",K3)),1,0)) -> 1 | T3: =IF(ISBLANK(K3),0,IF(ISNUMBER(SEARCH("Statistics",K3)),1,0)) -> 0 | U3: =IF(ISBLANK(K3),0,IF(ISNUMBER(SEARCH("AWS",K3)),1,0)) -> 0 | V3: =IF(ISBLANK(K3),0,IF(ISNUMBER(SEARCH("GCP",K3)),1,0)) -> 0 | W3: =IF(ISBLANK(K3),0,IF(ISNUMBER(SEARCH("NoSQL",K3)),1,0)) -> 0 | X3: =IF(ISBLANK(K3),0,IF(ISNUMBER(SEARCH("Data Modeling",K3)),1,0)) -> 0 | Y3: =IF(ISBLANK(K3),0,IF(ISNUMBER(SEARCH("Pandas",K3)),1,0)) -> 0 | Z3: =IF(ISBLANK(K3),0,IF(ISNUMBER(SEARCH("Numpy",K3)),1,0)) -> 0 | AA3: =IF(ISBLANK(K3),0,IF(ISNUMBER(SEARCH("Pyspark",K3)),1,0)) -> 0 | AB3: =IF(ISBLANK(K3),0,IF(ISNUMBER(SEARCH("Hadoop",K3)),1,0)) -> 0 | AC3: =IF(ISBLANK(K3),0,IF(ISNUMBER(SEARCH("ETL",K3)),1,0)) -> 0 | AD3: =IF(ISBLANK(K3),0,IF(ISNUMBER(SEARCH("Azure",K3)),1,0)) -> 0 | AE3: =IF(ISBLANK(K3),0,IF(ISNUMBER(SEARCH("Databricks",K3)),1,0)) -> 0 | AF3: =IF(ISBLANK(K3),0,IF(ISNUMBER(SEARCH("A/B Testing",K3)),1,0)) -> 0 | AG3: =IF(ISBLANK(K3),0,IF(ISNUMBER(SEARCH("Snowflake",K3)),1,0)) -> 0 | AH3: =IF(ISBLANK(K3),0,IF(ISNUMBER(SEARCH("Agile",K3)),1,0)) -> 0 | AI3: =IF(ISBLANK(K3),0,IF(ISNUMBER(SEARCH("Jira",K3)),1,0)) -> 0 | AJ3: =IF(ISBLANK(K3),0,IF(ISNUMBER(SEARCH("Git",K3)),1,0)) -> 0 | AK3: =IF(ISBLANK(K3),0,IF(ISNUMBER(SEARCH("Reporting",K3)),1,0)) -> 1 | AL3: =IF(ISBLANK(K3),0,IF(ISNUMBER(SEARCH("CI/CD",K3)),1,0)) -> 0 | AM3: =IF(ISBLANK(L3),0,IF(ISNUMBER(SEARCH("Python",L3)),1,0)) -> 0 | AN3: =IF(ISBLANK(L3),0,IF(ISNUMBER(SEARCH("SQL",L3)),1,0)) -> 0 | AO3: =IF(ISBLANK(L3),0,IF(ISNUMBER(SEARCH("Airflow",L3)),1,0)) -> 0 | AP3: =IF(ISBLANK(L3),0,IF(ISNUMBER(SEARCH("Kafka",L3)),1,0)) -> 0 | AQ3: =IF(ISBLANK(L3),0,IF(ISNUMBER(SEARCH("ML",L3)),1,0)) -> 0 | AR3: =IF(ISBLANK(L4),0,IF(ISNUMBER(SEARCH("ML",L4)),1,0)) -> 0 | AS3: =IF(ISBLANK(L5),0,IF(ISNUMBER(SEARCH("Docker",L5)),1,0)) -> 0 | AT3: =IF(ISBLANK(L5),0,IF(ISNUMBER(SEARCH("dbt",L5)),1,0)) -> 0 | AU3: =IF(ISBLANK(L5),0,IF(ISNUMBER(SEARCH("AWS",L5)),1,0)) -> 0 | AV3: =IF(ISBLANK(L5),0,IF(ISNUMBER(SEARCH("GCP",L5)),1,0)) -> 0 | AW3: =IF(ISBLANK(L5),0,IF(ISNUMBER(SEARCH("Azure",L5)),1,0)) -> 0 | AX3: =IF(ISBLANK(M5),0,IF(ISNUMBER(SEARCH("Tableau",L5)),1,0)) -> 0 | AY3: =IF(ISBLANK(N5),0,IF(ISNUMBER(SEARCH("PowerBI",L5)),1,0)) -> 0 | AZ3: Fulltime
A4: 3 | B4: 46178 | C4: LinkedIn | D4: MIS Analyst | E4: Teamware Solutions | F4: Mumbai | G4: 3 | H4: 5 | I4: ND | J4: ND | K4: Excel, MIS Analysis and Reporting , PowerBI , MIS and SOP dovumentation | L4: None | M4: ND | N4: Small | O4: =IF(ISBLANK(K4),0,IF(ISNUMBER(SEARCH("sql",K4)),1,0)) -> 0 | P4: =IF(ISBLANK(K4),0,IF(ISNUMBER(SEARCH("Python",K4)),1,0)) -> 0 | Q4: =IF(ISBLANK(K4),0,IF(ISNUMBER(SEARCH("PowerBI",K4)),1,0)) -> 1 | R4: =IF(ISBLANK(K4),0,IF(ISNUMBER(SEARCH("Tableau",K4)),1,0)) -> 0 | S4: =IF(ISBLANK(K4),0,IF(ISNUMBER(SEARCH("Excel",K4)),1,0)) -> 1 | T4: =IF(ISBLANK(K4),0,IF(ISNUMBER(SEARCH("Statistics",K4)),1,0)) -> 0 | U4: =IF(ISBLANK(K4),0,IF(ISNUMBER(SEARCH("AWS",K4)),1,0)) -> 0 | V4: =IF(ISBLANK(K4),0,IF(ISNUMBER(SEARCH("GCP",K4)),1,0)) -> 0 | W4: =IF(ISBLANK(K4),0,IF(ISNUMBER(SEARCH("NoSQL",K4)),1,0)) -> 0 | X4: =IF(ISBLANK(K4),0,IF(ISNUMBER(SEARCH("Data Modeling",K4)),1,0)) -> 0 | Y4: =IF(ISBLANK(K4),0,IF(ISNUMBER(SEARCH("Pandas",K4)),1,0)) -> 0 | Z4: =IF(ISBLANK(K4),0,IF(ISNUMBER(SEARCH("Numpy",K4)),1,0)) -> 0 | AA4: =IF(ISBLANK(K4),0,IF(ISNUMBER(SEARCH("Pyspark",K4)),1,0)) -> 0 | AB4: =IF(ISBLANK(K4),0,IF(ISNUMBER(SEARCH("Hadoop",K4)),1,0)) -> 0 | AC4: =IF(ISBLANK(K4),0,IF(ISNUMBER(SEARCH("ETL",K4)),1,0)) -> 0 | AD4: =IF(ISBLANK(K4),0,IF(ISNUMBER(SEARCH("Azure",K4)),1,0)) -> 0 | AE4: =IF(ISBLANK(K4),0,IF(ISNUMBER(SEARCH("Databricks",K4)),1,0)) -> 0 | AF4: =IF(ISBLANK(K4),0,IF(ISNUMBER(SEARCH("A/B Testing",K4)),1,0)) -> 0 | AG4: =IF(ISBLANK(K4),0,IF(ISNUMBER(SEARCH("Snowflake",K4)),1,0)) -> 0 | AH4: =IF(ISBLANK(K4),0,IF(ISNUMBER(SEARCH("Agile",K4)),1,0)) -> 0 | AI4: =IF(ISBLANK(K4),0,IF(ISNUMBER(SEARCH("Jira",K4)),1,0)) -> 0 | AJ4: =IF(ISBLANK(K4),0,IF(ISNUMBER(SEARCH("Git",K4)),1,0)) -> 0 | AK4: =IF(ISBLANK(K4),0,IF(ISNUMBER(SEARCH("Reporting",K4)),1,0)) -> 1 | AL4: =IF(ISBLANK(K4),0,IF(ISNUMBER(SEARCH("CI/CD",K4)),1,0)) -> 0 | AM4: =IF(ISBLANK(L4),0,IF(ISNUMBER(SEARCH("Python",L4)),1,0)) -> 0 | AN4: =IF(ISBLANK(L4),0,IF(ISNUMBER(SEARCH("SQL",L4)),1,0)) -> 0 | AO4: =IF(ISBLANK(L4),0,IF(ISNUMBER(SEARCH("Airflow",L4)),1,0)) -> 0 | AP4: =IF(ISBLANK(L4),0,IF(ISNUMBER(SEARCH("Kafka",L4)),1,0)) -> 0 | AQ4: =IF(ISBLANK(L4),0,IF(ISNUMBER(SEARCH("ML",L4)),1,0)) -> 0 | AR4: =IF(ISBLANK(L5),0,IF(ISNUMBER(SEARCH("ML",L5)),1,0)) -> 0 | AS4: =IF(ISBLANK(L6),0,IF(ISNUMBER(SEARCH("Docker",L6)),1,0)) -> 0 | AT4: =IF(ISBLANK(L6),0,IF(ISNUMBER(SEARCH("dbt",L6)),1,0)) -> 0 | AU4: =IF(ISBLANK(L6),0,IF(ISNUMBER(SEARCH("AWS",L6)),1,0)) -> 0 | AV4: =IF(ISBLANK(L6),0,IF(ISNUMBER(SEARCH("GCP",L6)),1,0)) -> 0 | AW4: =IF(ISBLANK(L6),0,IF(ISNUMBER(SEARCH("Azure",L6)),1,0)) -> 0 | AX4: =IF(ISBLANK(M6),0,IF(ISNUMBER(SEARCH("Tableau",L6)),1,0)) -> 0 | AY4: =IF(ISBLANK(N6),0,IF(ISNUMBER(SEARCH("PowerBI",L6)),1,0)) -> 0 | AZ4: Fulltime
A5: 4 | B5: 46178 | C5: LinkedIn | D5: Data Engineer | E5: OptimHire | F5: Hyderabad | G5: 6 | H5: 10 | I5: ND | J5: ND | K5: Python , PySpark , Scala, Big Data processing, ETL development, Data pipelines,AWS | L5: None | M5: ND | N5: Medium | O5: =IF(ISBLANK(K5),0,IF(ISNUMBER(SEARCH("sql",K5)),1,0)) -> 0 | P5: =IF(ISBLANK(K5),0,IF(ISNUMBER(SEARCH("Python",K5)),1,0)) -> 1 | Q5: =IF(ISBLANK(K5),0,IF(ISNUMBER(SEARCH("PowerBI",K5)),1,0)) -> 0 | R5: =IF(ISBLANK(K5),0,IF(ISNUMBER(SEARCH("Tableau",K5)),1,0)) -> 0 | S5: =IF(ISBLANK(K5),0,IF(ISNUMBER(SEARCH("Excel",K5)),1,0)) -> 0 | T5: =IF(ISBLANK(K5),0,IF(ISNUMBER(SEARCH("Statistics",K5)),1,0)) -> 0 | U5: =IF(ISBLANK(K5),0,IF(ISNUMBER(SEARCH("AWS",K5)),1,0)) -> 1 | V5: =IF(ISBLANK(K5),0,IF(ISNUMBER(SEARCH("GCP",K5)),1,0)) -> 0 | W5: =IF(ISBLANK(K5),0,IF(ISNUMBER(SEARCH("NoSQL",K5)),1,0)) -> 0 | X5: =IF(ISBLANK(K5),0,IF(ISNUMBER(SEARCH("Data Modeling",K5)),1,0)) -> 0 | Y5: =IF(ISBLANK(K5),0,IF(ISNUMBER(SEARCH("Pandas",K5)),1,0)) -> 0 | Z5: =IF(ISBLANK(K5),0,IF(ISNUMBER(SEARCH("Numpy",K5)),1,0)) -> 0 | AA5: =IF(ISBLANK(K5),0,IF(ISNUMBER(SEARCH("Pyspark",K5)),1,0)) -> 1 | AB5: =IF(ISBLANK(K5),0,IF(ISNUMBER(SEARCH("Hadoop",K5)),1,0)) -> 0 | AC5: =IF(ISBLANK(K5),0,IF(ISNUMBER(SEARCH("ETL",K5)),1,0)) -> 1 | AD5: =IF(ISBLANK(K5),0,IF(ISNUMBER(SEARCH("Azure",K5)),1,0)) -> 0 | AE5: =IF(ISBLANK(K5),0,IF(ISNUMBER(SEARCH("Databricks",K5)),1,0)) -> 0 | AF5: =IF(ISBLANK(K5),0,IF(ISNUMBER(SEARCH("A/B Testing",K5)),1,0)) -> 0 | AG5: =IF(ISBLANK(K5),0,IF(ISNUMBER(SEARCH("Snowflake",K5)),1,0)) -> 0 | AH5: =IF(ISBLANK(K5),0,IF(ISNUMBER(SEARCH("Agile",K5)),1,0)) -> 0 | AI5: =IF(ISBLANK(K5),0,IF(ISNUMBER(SEARCH("Jira",K5)),1,0)) -> 0 | AJ5: =IF(ISBLANK(K5),0,IF(ISNUMBER(SEARCH("Git",K5)),1,0)) -> 0 | AK5: =IF(ISBLANK(K5),0,IF(ISNUMBER(SEARCH("Reporting",K5)),1,0)) -> 0 | AL5: =IF(ISBLANK(K5),0,IF(ISNUMBER(SEARCH("CI/CD",K5)),1,0)) -> 0 | AM5: =IF(ISBLANK(L5),0,IF(ISNUMBER(SEARCH("Python",L5)),1,0)) -> 0 | AN5: =IF(ISBLANK(L5),0,IF(ISNUMBER(SEARCH("SQL",L5)),1,0)) -> 0 | AO5: =IF(ISBLANK(L5),0,IF(ISNUMBER(SEARCH("Airflow",L5)),1,0)) -> 0 | AP5: =IF(ISBLANK(L5),0,IF(ISNUMBER(SEARCH("Kafka",L5)),1,0)) -> 0 | AQ5: =IF(ISBLANK(L5),0,IF(ISNUMBER(SEARCH("ML",L5)),1,0)) -> 0 | AR5: =IF(ISBLANK(L6),0,IF(ISNUMBER(SEARCH("ML",L6)),1,0)) -> 0 | AS5: =IF(ISBLANK(L7),0,IF(ISNUMBER(SEARCH("Docker",L7)),1,0)) -> 0 | AT5: =IF(ISBLANK(L7),0,IF(ISNUMBER(SEARCH("dbt",L7)),1,0)) -> 0 | AU5: =IF(ISBLANK(L7),0,IF(ISNUMBER(SEARCH("AWS",L7)),1,0)) -> 0 | AV5: =IF(ISBLANK(L7),0,IF(ISNUMBER(SEARCH("GCP",L7)),1,0)) -> 0 | AW5: =IF(ISBLANK(L7),0,IF(ISNUMBER(SEARCH("Azure",L7)),1,0)) -> 0 | AX5: =IF(ISBLANK(M7),0,IF(ISNUMBER(SEARCH("Tableau",L7)),1,0)) -> 0 | AY5: =IF(ISBLANK(N7),0,IF(ISNUMBER(SEARCH("PowerBI",L7)),1,0)) -> 0 | AZ5: Fulltime
A6: 5 | B6: 46178 | C6: LinkedIn | D6: BI Developer | E6: Qpact Solutions | F6: Hyderabad | G6: 5 | H6: 10 | I6: ND | J6: ND | K6: PowerBI , DAX, Python , Automation,SQl , Database management,ETL, Data visualization | L6: None | M6: Hybrid | N6: Medium | O6: =IF(ISBLANK(K6),0,IF(ISNUMBER(SEARCH("sql",K6)),1,0)) -> 1 | P6: =IF(ISBLANK(K6),0,IF(ISNUMBER(SEARCH("Python",K6)),1,0)) -> 1 | Q6: =IF(ISBLANK(K6),0,IF(ISNUMBER(SEARCH("PowerBI",K6)),1,0)) -> 1 | R6: =IF(ISBLANK(K6),0,IF(ISNUMBER(SEARCH("Tableau",K6)),1,0)) -> 0 | S6: =IF(ISBLANK(K6),0,IF(ISNUMBER(SEARCH("Excel",K6)),1,0)) -> 0 | T6: =IF(ISBLANK(K6),0,IF(ISNUMBER(SEARCH("Statistics",K6)),1,0)) -> 0 | U6: =IF(ISBLANK(K6),0,IF(ISNUMBER(SEARCH("AWS",K6)),1,0)) -> 0 | V6: =IF(ISBLANK(K6),0,IF(ISNUMBER(SEARCH("GCP",K6)),1,0)) -> 0 | W6: =IF(ISBLANK(K6),0,IF(ISNUMBER(SEARCH("NoSQL",K6)),1,0)) -> 0 | X6: =IF(ISBLANK(K6),0,IF(ISNUMBER(SEARCH("Data Modeling",K6)),1,0)) -> 0 | Y6: =IF(ISBLANK(K6),0,IF(ISNUMBER(SEARCH("Pandas",K6)),1,0)) -> 0 | Z6: =IF(ISBLANK(K6),0,IF(ISNUMBER(SEARCH("Numpy",K6)),1,0)) -> 0 | AA6: =IF(ISBLANK(K6),0,IF(ISNUMBER(SEARCH("Pyspark",K6)),1,0)) -> 0 | AB6: =IF(ISBLANK(K6),0,IF(ISNUMBER(SEARCH("Hadoop",K6)),1,0)) -> 0 | AC6: =IF(ISBLANK(K6),0,IF(ISNUMBER(SEARCH("ETL",K6)),1,0)) -> 1 | AD6: =IF(ISBLANK(K6),0,IF(ISNUMBER(SEARCH("Azure",K6)),1,0)) -> 0 | AE6: =IF(ISBLANK(K6),0,IF(ISNUMBER(SEARCH("Databricks",K6)),1,0)) -> 0 | AF6: =IF(ISBLANK(K6),0,IF(ISNUMBER(SEARCH("A/B Testing",K6)),1,0)) -> 0 | AG6: =IF(ISBLANK(K6),0,IF(ISNUMBER(SEARCH("Snowflake",K6)),1,0)) -> 0 | AH6: =IF(ISBLANK(K6),0,IF(ISNUMBER(SEARCH("Agile",K6)),1,0)) -> 0 | AI6: =IF(ISBLANK(K6),0,IF(ISNUMBER(SEARCH("Jira",K6)),1,0)) -> 0 | AJ6: =IF(ISBLANK(K6),0,IF(ISNUMBER(SEARCH("Git",K6)),1,0)) -> 0 | AK6: =IF(ISBLANK(K6),0,IF(ISNUMBER(SEARCH("Reporting",K6)),1,0)) -> 0 | AL6: =IF(ISBLANK(K6),0,IF(ISNUMBER(SEARCH("CI/CD",K6)),1,0)) -> 0 | AM6: =IF(ISBLANK(L6),0,IF(ISNUMBER(SEARCH("Python",L6)),1,0)) -> 0 | AN6: =IF(ISBLANK(L6),0,IF(ISNUMBER(SEARCH("SQL",L6)),1,0)) -> 0 | AO6: =IF(ISBLANK(L6),0,IF(ISNUMBER(SEARCH("Airflow",L6)),1,0)) -> 0 | AP6: =IF(ISBLANK(L6),0,IF(ISNUMBER(SEARCH("Kafka",L6)),1,0)) -> 0 | AQ6: =IF(ISBLANK(L6),0,IF(ISNUMBER(SEARCH("ML",L6)),1,0)) -> 0 | AR6: =IF(ISBLANK(L7),0,IF(ISNUMBER(SEARCH("ML",L7)),1,0)) -> 0 | AS6: =IF(ISBLANK(L8),0,IF(ISNUMBER(SEARCH("Docker",L8)),1,0)) -> 0 | AT6: =IF(ISBLANK(L8),0,IF(ISNUMBER(SEARCH("dbt",L8)),1,0)) -> 0 | AU6: =IF(ISBLANK(L8),0,IF(ISNUMBER(SEARCH("AWS",L8)),1,0)) -> 0 | AV6: =IF(ISBLANK(L8),0,IF(ISNUMBER(SEARCH("GCP",L8)),1,0)) -> 0 | AW6: =IF(ISBLANK(L8),0,IF(ISNUMBER(SEARCH("Azure",L8)),1,0)) -> 0 | AX6: =IF(ISBLANK(M8),0,IF(ISNUMBER(SEARCH("Tableau",L8)),1,0)) -> 0 | AY6: =IF(ISBLANK(N8),0,IF(ISNUMBER(SEARCH("PowerBI",L8)),1,0)) -> 0 | AZ6: Fulltime
A7: 6 | B7: 46178 | C7: LinkedIn | D7: Data Analyst | E7: GreedyGame | F7: Bengaluru | G7: 2 | H7: 4 | I7: ND | J7: ND | K7: Python , R , Numpy , Pandas, SQL , PowerBI , Looker Studio, BigQuery, Web and App analytics | L7: Kafka(exposure),A/B testing , Tensorflow or HuggingFace(familiarity) | M7: On-site | N7: Startup | O7: =IF(ISBLANK(K7),0,IF(ISNUMBER(SEARCH("sql",K7)),1,0)) -> 1 | P7: =IF(ISBLANK(K7),0,IF(ISNUMBER(SEARCH("Python",K7)),1,0)) -> 1 | Q7: =IF(ISBLANK(K7),0,IF(ISNUMBER(SEARCH("PowerBI",K7)),1,0)) -> 1 | R7: =IF(ISBLANK(K7),0,IF(ISNUMBER(SEARCH("Tableau",K7)),1,0)) -> 0 | S7: =IF(ISBLANK(K7),0,IF(ISNUMBER(SEARCH("Excel",K7)),1,0)) -> 0 | T7: =IF(ISBLANK(K7),0,IF(ISNUMBER(SEARCH("Statistics",K7)),1,0)) -> 0 | U7: =IF(ISBLANK(K7),0,IF(ISNUMBER(SEARCH("AWS",K7)),1,0)) -> 0 | V7: =IF(ISBLANK(K7),0,IF(ISNUMBER(SEARCH("GCP",K7)),1,0)) -> 0 | W7: =IF(ISBLANK(K7),0,IF(ISNUMBER(SEARCH("NoSQL",K7)),1,0)) -> 0 | X7: =IF(ISBLANK(K7),0,IF(ISNUMBER(SEARCH("Data Modeling",K7)),1,0)) -> 0 | Y7: =IF(ISBLANK(K7),0,IF(ISNUMBER(SEARCH("Pandas",K7)),1,0)) -> 1 | Z7: =IF(ISBLANK(K7),0,IF(ISNUMBER(SEARCH("Numpy",K7)),1,0)) -> 1 | AA7: =IF(ISBLANK(K7),0,IF(ISNUMBER(SEARCH("Pyspark",K7)),1,0)) -> 0 | AB7: =IF(ISBLANK(K7),0,IF(ISNUMBER(SEARCH("Hadoop",K7)),1,0)) -> 0 | AC7: =IF(ISBLANK(K7),0,IF(ISNUMBER(SEARCH("ETL",K7)),1,0)) -> 0 | AD7: =IF(ISBLANK(K7),0,IF(ISNUMBER(SEARCH("Azure",K7)),1,0)) -> 0 | AE7: =IF(ISBLANK(K7),0,IF(ISNUMBER(SEARCH("Databricks",K7)),1,0)) -> 0 | AF7: =IF(ISBLANK(K7),0,IF(ISNUMBER(SEARCH("A/B Testing",K7)),1,0)) -> 0 | AG7: =IF(ISBLANK(K7),0,IF(ISNUMBER(SEARCH("Snowflake",K7)),1,0)) -> 0 | AH7: =IF(ISBLANK(K7),0,IF(ISNUMBER(SEARCH("Agile",K7)),1,0)) -> 0 | AI7: =IF(ISBLANK(K7),0,IF(ISNUMBER(SEARCH("Jira",K7)),1,0)) -> 0 | AJ7: =IF(ISBLANK(K7),0,IF(ISNUMBER(SEARCH("Git",K7)),1,0)) -> 0 | AK7: =IF(ISBLANK(K7),0,IF(ISNUMBER(SEARCH("Reporting",K7)),1,0)) -> 0 | AL7: =IF(ISBLANK(K7),0,IF(ISNUMBER(SEARCH("CI/CD",K7)),1,0)) -> 0 | AM7: =IF(ISBLANK(L7),0,IF(ISNUMBER(SEARCH("Python",L7)),1,0)) -> 0 | AN7: =IF(ISBLANK(L7),0,IF(ISNUMBER(SEARCH("SQL",L7)),1,0)) -> 0 | AO7: =IF(ISBLANK(L7),0,IF(ISNUMBER(SEARCH("Airflow",L7)),1,0)) -> 0 | AP7: =IF(ISBLANK(L7),0,IF(ISNUMBER(SEARCH("Kafka",L7)),1,0)) -> 1 | AQ7: =IF(ISBLANK(L7),0,IF(ISNUMBER(SEARCH("ML",L7)),1,0)) -> 0 | AR7: =IF(ISBLANK(L8),0,IF(ISNUMBER(SEARCH("ML",L8)),1,0)) -> 0 | AS7: =IF(ISBLANK(L9),0,IF(ISNUMBER(SEARCH("Docker",L9)),1,0)) -> 0 | AT7: =IF(ISBLANK(L9),0,IF(ISNUMBER(SEARCH("dbt",L9)),1,0)) -> 0 | AU7: =IF(ISBLANK(L9),0,IF(ISNUMBER(SEARCH("AWS",L9)),1,0)) -> 0 | AV7: =IF(ISBLANK(L9),0,IF(ISNUMBER(SEARCH("GCP",L9)),1,0)) -> 0 | AW7: =IF(ISBLANK(L9),0,IF(ISNUMBER(SEARCH("Azure",L9)),1,0)) -> 0 | AX7: =IF(ISBLANK(M9),0,IF(ISNUMBER(SEARCH("Tableau",L9)),1,0)) -> 0 | AY7: =IF(ISBLANK(N9),0,IF(ISNUMBER(SEARCH("PowerBI",L9)),1,0)) -> 0 | AZ7: Fulltime
A8: 7 | B8: 46178 | C8: LinkedIn | D8: MIS Analyst | E8: Kapiva | F8: Bengaluru | G8: ND | H8: ND | I8: ND | J8: ND | K8: Excel , SQL | L8: None | M8: On-site | N8: Startup | O8: =IF(ISBLANK(K8),0,IF(ISNUMBER(SEARCH("sql",K8)),1,0)) -> 1 | P8: =IF(ISBLANK(K8),0,IF(ISNUMBER(SEARCH("Python",K8)),1,0)) -> 0 | Q8: =IF(ISBLANK(K8),0,IF(ISNUMBER(SEARCH("PowerBI",K8)),1,0)) -> 0 | R8: =IF(ISBLANK(K8),0,IF(ISNUMBER(SEARCH("Tableau",K8)),1,0)) -> 0 | S8: =IF(ISBLANK(K8),0,IF(ISNUMBER(SEARCH("Excel",K8)),1,0)) -> 1 | T8: =IF(ISBLANK(K8),0,IF(ISNUMBER(SEARCH("Statistics",K8)),1,0)) -> 0 | U8: =IF(ISBLANK(K8),0,IF(ISNUMBER(SEARCH("AWS",K8)),1,0)) -> 0 | V8: =IF(ISBLANK(K8),0,IF(ISNUMBER(SEARCH("GCP",K8)),1,0)) -> 0 | W8: =IF(ISBLANK(K8),0,IF(ISNUMBER(SEARCH("NoSQL",K8)),1,0)) -> 0 | X8: =IF(ISBLANK(K8),0,IF(ISNUMBER(SEARCH("Data Modeling",K8)),1,0)) -> 0 | Y8: =IF(ISBLANK(K8),0,IF(ISNUMBER(SEARCH("Pandas",K8)),1,0)) -> 0 | Z8: =IF(ISBLANK(K8),0,IF(ISNUMBER(SEARCH("Numpy",K8)),1,0)) -> 0 | AA8: =IF(ISBLANK(K8),0,IF(ISNUMBER(SEARCH("Pyspark",K8)),1,0)) -> 0 | AB8: =IF(ISBLANK(K8),0,IF(ISNUMBER(SEARCH("Hadoop",K8)),1,0)) -> 0 | AC8: =IF(ISBLANK(K8),0,IF(ISNUMBER(SEARCH("ETL",K8)),1,0)) -> 0 | AD8: =IF(ISBLANK(K8),0,IF(ISNUMBER(SEARCH("Azure",K8)),1,0)) -> 0 | AE8: =IF(ISBLANK(K8),0,IF(ISNUMBER(SEARCH("Databricks",K8)),1,0)) -> 0 | AF8: =IF(ISBLANK(K8),0,IF(ISNUMBER(SEARCH("A/B Testing",K8)),1,0)) -> 0 | AG8: =IF(ISBLANK(K8),0,IF(ISNUMBER(SEARCH("Snowflake",K8)),1,0)) -> 0 | AH8: =IF(ISBLANK(K8),0,IF(ISNUMBER(SEARCH("Agile",K8)),1,0)) -> 0 | AI8: =IF(ISBLANK(K8),0,IF(ISNUMBER(SEARCH("Jira",K8)),1,0)) -> 0 | AJ8: =IF(ISBLANK(K8),0,IF(ISNUMBER(SEARCH("Git",K8)),1,0)) -> 0 | AK8: =IF(ISBLANK(K8),0,IF(ISNUMBER(SEARCH("Reporting",K8)),1,0)) -> 0 | AL8: =IF(ISBLANK(K8),0,IF(ISNUMBER(SEARCH("CI/CD",K8)),1,0)) -> 0 | AM8: =IF(ISBLANK(L8),0,IF(ISNUMBER(SEARCH("Python",L8)),1,0)) -> 0 | AN8: =IF(ISBLANK(L8),0,IF(ISNUMBER(SEARCH("SQL",L8)),1,0)) -> 0 | AO8: =IF(ISBLANK(L8),0,IF(ISNUMBER(SEARCH("Airflow",L8)),1,0)) -> 0 | AP8: =IF(ISBLANK(L8),0,IF(ISNUMBER(SEARCH("Kafka",L8)),1,0)) -> 0 | AQ8: =IF(ISBLANK(L8),0,IF(ISNUMBER(SEARCH("ML",L8)),1,0)) -> 0 | AR8: =IF(ISBLANK(L9),0,IF(ISNUMBER(SEARCH("ML",L9)),1,0)) -> 0 | AS8: =IF(ISBLANK(L10),0,IF(ISNUMBER(SEARCH("Docker",L10)),1,0)) -> 0 | AT8: =IF(ISBLANK(L10),0,IF(ISNUMBER(SEARCH("dbt",L10)),1,0)) -> 0 | AU8: =IF(ISBLANK(L10),0,IF(ISNUMBER(SEARCH("AWS",L10)),1,0)) -> 0 | AV8: =IF(ISBLANK(L10),0,IF(ISNUMBER(SEARCH("GCP",L10)),1,0)) -> 0 | AW8: =IF(ISBLANK(L10),0,IF(ISNUMBER(SEARCH("Azure",L10)),1,0)) -> 0 | AX8: =IF(ISBLANK(M10),0,IF(ISNUMBER(SEARCH("Tableau",L10)),1,0)) -> 0 | AY8: =IF(ISBLANK(N10),0,IF(ISNUMBER(SEARCH("PowerBI",L10)),1,0)) -> 0 | AZ8: Fulltime
A9: 8 | B9: 46178 | C9: LinkedIn | D9: Data Analyst | E9: Optum India | F9: Noida | G9: 3 | H9: None | I9: ND | J9: ND | K9: Python , PySpark , Hive, SQL , Cloud Platforms, Analytics Pipelines | L9: CMS datasets such as MMR/MOR/EDPS , Medicare risk adjustment | M9: On-site | N9: Large | O9: =IF(ISBLANK(K9),0,IF(ISNUMBER(SEARCH("sql",K9)),1,0)) -> 1 | P9: =IF(ISBLANK(K9),0,IF(ISNUMBER(SEARCH("Python",K9)),1,0)) -> 1 | Q9: =IF(ISBLANK(K9),0,IF(ISNUMBER(SEARCH("PowerBI",K9)),1,0)) -> 0 | R9: =IF(ISBLANK(K9),0,IF(ISNUMBER(SEARCH("Tableau",K9)),1,0)) -> 0 | S9: =IF(ISBLANK(K9),0,IF(ISNUMBER(SEARCH("Excel",K9)),1,0)) -> 0 | T9: =IF(ISBLANK(K9),0,IF(ISNUMBER(SEARCH("Statistics",K9)),1,0)) -> 0 | U9: =IF(ISBLANK(K9),0,IF(ISNUMBER(SEARCH("AWS",K9)),1,0)) -> 0 | V9: =IF(ISBLANK(K9),0,IF(ISNUMBER(SEARCH("GCP",K9)),1,0)) -> 0 | W9: =IF(ISBLANK(K9),0,IF(ISNUMBER(SEARCH("NoSQL",K9)),1,0)) -> 0 | X9: =IF(ISBLANK(K9),0,IF(ISNUMBER(SEARCH("Data Modeling",K9)),1,0)) -> 0 | Y9: =IF(ISBLANK(K9),0,IF(ISNUMBER(SEARCH("Pandas",K9)),1,0)) -> 0 | Z9: =IF(ISBLANK(K9),0,IF(ISNUMBER(SEARCH("Numpy",K9)),1,0)) -> 0 | AA9: =IF(ISBLANK(K9),0,IF(ISNUMBER(SEARCH("Pyspark",K9)),1,0)) -> 1 | AB9: =IF(ISBLANK(K9),0,IF(ISNUMBER(SEARCH("Hadoop",K9)),1,0)) -> 0 | AC9: =IF(ISBLANK(K9),0,IF(ISNUMBER(SEARCH("ETL",K9)),1,0)) -> 0 | AD9: =IF(ISBLANK(K9),0,IF(ISNUMBER(SEARCH("Azure",K9)),1,0)) -> 0 | AE9: =IF(ISBLANK(K9),0,IF(ISNUMBER(SEARCH("Databricks",K9)),1,0)) -> 0 | AF9: =IF(ISBLANK(K9),0,IF(ISNUMBER(SEARCH("A/B Testing",K9)),1,0)) -> 0 | AG9: =IF(ISBLANK(K9),0,IF(ISNUMBER(SEARCH("Snowflake",K9)),1,0)) -> 0 | AH9: =IF(ISBLANK(K9),0,IF(ISNUMBER(SEARCH("Agile",K9)),1,0)) -> 0 | AI9: =IF(ISBLANK(K9),0,IF(ISNUMBER(SEARCH("Jira",K9)),1,0)) -> 0 | AJ9: =IF(ISBLANK(K9),0,IF(ISNUMBER(SEARCH("Git",K9)),1,0)) -> 0 | AK9: =IF(ISBLANK(K9),0,IF(ISNUMBER(SEARCH("Reporting",K9)),1,0)) -> 0 | AL9: =IF(ISBLANK(K9),0,IF(ISNUMBER(SEARCH("CI/CD",K9)),1,0)) -> 0 | AM9: =IF(ISBLANK(L9),0,IF(ISNUMBER(SEARCH("Python",L9)),1,0)) -> 0 | AN9: =IF(ISBLANK(L9),0,IF(ISNUMBER(SEARCH("SQL",L9)),1,0)) -> 0 | AO9: =IF(ISBLANK(L9),0,IF(ISNUMBER(SEARCH("Airflow",L9)),1,0)) -> 0 | AP9: =IF(ISBLANK(L9),0,IF(ISNUMBER(SEARCH("Kafka",L9)),1,0)) -> 0 | AQ9: =IF(ISBLANK(L9),0,IF(ISNUMBER(SEARCH("ML",L9)),1,0)) -> 0 | AR9: =IF(ISBLANK(L10),0,IF(ISNUMBER(SEARCH("ML",L10)),1,0)) -> 0 | AS9: =IF(ISBLANK(L11),0,IF(ISNUMBER(SEARCH("Docker",L11)),1,0)) -> 0 | AT9: =IF(ISBLANK(L11),0,IF(ISNUMBER(SEARCH("dbt",L11)),1,0)) -> 0 | AU9: =IF(ISBLANK(L11),0,IF(ISNUMBER(SEARCH("AWS",L11)),1,0)) -> 0 | AV9: =IF(ISBLANK(L11),0,IF(ISNUMBER(SEARCH("GCP",L11)),1,0)) -> 0 | AW9: =IF(ISBLANK(L11),0,IF(ISNUMBER(SEARCH("Azure",L11)),1,0)) -> 0 | AX9: =IF(ISBLANK(M11),0,IF(ISNUMBER(SEARCH("Tableau",L11)),1,0)) -> 0 | AY9: =IF(ISBLANK(N11),0,IF(ISNUMBER(SEARCH("PowerBI",L11)),1,0)) -> 0 | AZ9: Fulltime
A10: 9 | B10: 46178 | C10: LinkedIn | D10: Data Analyst | E10: Everbridge | F10: Bengaluru | G10: 2 | H10: 5 | I10: ND | J10: ND | K10: SQL , Snowflake, BigQuery, Redshift , Azure Synapse, Tableau , PowerBI, dbt, AWS Quicksight | L10: ETL Pipelines , Python, APIs,Git, AI analytics Tools, Sharepoint | M10: On-site | N10: Large | O10: =IF(ISBLANK(K10),0,IF(ISNUMBER(SEARCH("sql",K10)),1,0)) -> 1 | P10: =IF(ISBLANK(K10),0,IF(ISNUMBER(SEARCH("Python",K10)),1,0)) -> 0 | Q10: =IF(ISBLANK(K10),0,IF(ISNUMBER(SEARCH("PowerBI",K10)),1,0)) -> 1 | R10: =IF(ISBLANK(K10),0,IF(ISNUMBER(SEARCH("Tableau",K10)),1,0)) -> 1 | S10: =IF(ISBLANK(K10),0,IF(ISNUMBER(SEARCH("Excel",K10)),1,0)) -> 0 | T10: =IF(ISBLANK(K10),0,IF(ISNUMBER(SEARCH("Statistics",K10)),1,0)) -> 0 | U10: =IF(ISBLANK(K10),0,IF(ISNUMBER(SEARCH("AWS",K10)),1,0)) -> 1 | V10: =IF(ISBLANK(K10),0,IF(ISNUMBER(SEARCH("GCP",K10)),1,0)) -> 0 | W10: =IF(ISBLANK(K10),0,IF(ISNUMBER(SEARCH("NoSQL",K10)),1,0)) -> 0 | X10: =IF(ISBLANK(K10),0,IF(ISNUMBER(SEARCH("Data Modeling",K10)),1,0)) -> 0 | Y10: =IF(ISBLANK(K10),0,IF(ISNUMBER(SEARCH("Pandas",K10)),1,0)) -> 0 | Z10: =IF(ISBLANK(K10),0,IF(ISNUMBER(SEARCH("Numpy",K10)),1,0)) -> 0 | AA10: =IF(ISBLANK(K10),0,IF(ISNUMBER(SEARCH("Pyspark",K10)),1,0)) -> 0 | AB10: =IF(ISBLANK(K10),0,IF(ISNUMBER(SEARCH("Hadoop",K10)),1,0)) -> 0 | AC10: =IF(ISBLANK(K10),0,IF(ISNUMBER(SEARCH("ETL",K10)),1,0)) -> 0 | AD10: =IF(ISBLANK(K10),0,IF(ISNUMBER(SEARCH("Azure",K10)),1,0)) -> 1 | AE10: =IF(ISBLANK(K10),0,IF(ISNUMBER(SEARCH("Databricks",K10)),1,0)) -> 0 | AF10: =IF(ISBLANK(K10),0,IF(ISNUMBER(SEARCH("A/B Testing",K10)),1,0)) -> 0 | AG10: =IF(ISBLANK(K10),0,IF(ISNUMBER(SEARCH("Snowflake",K10)),1,0)) -> 1 | AH10: =IF(ISBLANK(K10),0,IF(ISNUMBER(SEARCH("Agile",K10)),1,0)) -> 0 | AI10: =IF(ISBLANK(K10),0,IF(ISNUMBER(SEARCH("Jira",K10)),1,0)) -> 0 | AJ10: =IF(ISBLANK(K10),0,IF(ISNUMBER(SEARCH("Git",K10)),1,0)) -> 0 | AK10: =IF(ISBLANK(K10),0,IF(ISNUMBER(SEARCH("Reporting",K10)),1,0)) -> 0 | AL10: =IF(ISBLANK(K10),0,IF(ISNUMBER(SEARCH("CI/CD",K10)),1,0)) -> 0 | AM10: =IF(ISBLANK(L10),0,IF(ISNUMBER(SEARCH("Python",L10)),1,0)) -> 1 | AN10: =IF(ISBLANK(L10),0,IF(ISNUMBER(SEARCH("SQL",L10)),1,0)) -> 0 | AO10: =IF(ISBLANK(L10),0,IF(ISNUMBER(SEARCH("Airflow",L10)),1,0)) -> 0 | AP10: =IF(ISBLANK(L10),0,IF(ISNUMBER(SEARCH("Kafka",L10)),1,0)) -> 0 | AQ10: =IF(ISBLANK(L10),0,IF(ISNUMBER(SEARCH("ML",L10)),1,0)) -> 0 | AR10: =IF(ISBLANK(L11),0,IF(ISNUMBER(SEARCH("ML",L11)),1,0)) -> 0 | AS10: =IF(ISBLANK(L12),0,IF(ISNUMBER(SEARCH("Docker",L12)),1,0)) -> 0 | AT10: =IF(ISBLANK(L12),0,IF(ISNUMBER(SEARCH("dbt",L12)),1,0)) -> 0 | AU10: =IF(ISBLANK(L12),0,IF(ISNUMBER(SEARCH("AWS",L12)),1,0)) -> 0 | AV10: =IF(ISBLANK(L12),0,IF(ISNUMBER(SEARCH("GCP",L12)),1,0)) -> 0 | AW10: =IF(ISBLANK(L12),0,IF(ISNUMBER(SEARCH("Azure",L12)),1,0)) -> 0 | AX10: =IF(ISBLANK(M12),0,IF(ISNUMBER(SEARCH("Tableau",L12)),1,0)) -> 0 | AY10: =IF(ISBLANK(N12),0,IF(ISNUMBER(SEARCH("PowerBI",L12)),1,0)) -> 0 | AZ10: Fulltime
A11: 10 | B11: 46178 | C11: LinkedIn | D11: Business Analyst | E11: Aditya Birla Capital | F11: Mumbai | G11: ND | H11: ND | I11: ND | J11: ND | K11: PowerBI , DAX , Excel , R,Python , Databricks | L11: None | M11: On-site | N11: Large | O11: =IF(ISBLANK(K11),0,IF(ISNUMBER(SEARCH("sql",K11)),1,0)) -> 0 | P11: =IF(ISBLANK(K11),0,IF(ISNUMBER(SEARCH("Python",K11)),1,0)) -> 1 | Q11: =IF(ISBLANK(K11),0,IF(ISNUMBER(SEARCH("PowerBI",K11)),1,0)) -> 1 | R11: =IF(ISBLANK(K11),0,IF(ISNUMBER(SEARCH("Tableau",K11)),1,0)) -> 0 | S11: =IF(ISBLANK(K11),0,IF(ISNUMBER(SEARCH("Excel",K11)),1,0)) -> 1 | T11: =IF(ISBLANK(K11),0,IF(ISNUMBER(SEARCH("Statistics",K11)),1,0)) -> 0 | U11: =IF(ISBLANK(K11),0,IF(ISNUMBER(SEARCH("AWS",K11)),1,0)) -> 0 | V11: =IF(ISBLANK(K11),0,IF(ISNUMBER(SEARCH("GCP",K11)),1,0)) -> 0 | W11: =IF(ISBLANK(K11),0,IF(ISNUMBER(SEARCH("NoSQL",K11)),1,0)) -> 0 | X11: =IF(ISBLANK(K11),0,IF(ISNUMBER(SEARCH("Data Modeling",K11)),1,0)) -> 0 | Y11: =IF(ISBLANK(K11),0,IF(ISNUMBER(SEARCH("Pandas",K11)),1,0)) -> 0 | Z11: =IF(ISBLANK(K11),0,IF(ISNUMBER(SEARCH("Numpy",K11)),1,0)) -> 0 | AA11: =IF(ISBLANK(K11),0,IF(ISNUMBER(SEARCH("Pyspark",K11)),1,0)) -> 0 | AB11: =IF(ISBLANK(K11),0,IF(ISNUMBER(SEARCH("Hadoop",K11)),1,0)) -> 0 | AC11: =IF(ISBLANK(K11),0,IF(ISNUMBER(SEARCH("ETL",K11)),1,0)) -> 0 | AD11: =IF(ISBLANK(K11),0,IF(ISNUMBER(SEARCH("Azure",K11)),1,0)) -> 0 | AE11: =IF(ISBLANK(K11),0,IF(ISNUMBER(SEARCH("Databricks",K11)),1,0)) -> 1 | AF11: =IF(ISBLANK(K11),0,IF(ISNUMBER(SEARCH("A/B Testing",K11)),1,0)) -> 0 | AG11: =IF(ISBLANK(K11),0,IF(ISNUMBER(SEARCH("Snowflake",K11)),1,0)) -> 0 | AH11: =IF(ISBLANK(K11),0,IF(ISNUMBER(SEARCH("Agile",K11)),1,0)) -> 0 | AI11: =IF(ISBLANK(K11),0,IF(ISNUMBER(SEARCH("Jira",K11)),1,0)) -> 0 | AJ11: =IF(ISBLANK(K11),0,IF(ISNUMBER(SEARCH("Git",K11)),1,0)) -> 0 | AK11: =IF(ISBLANK(K11),0,IF(ISNUMBER(SEARCH("Reporting",K11)),1,0)) -> 0 | AL11: =IF(ISBLANK(K11),0,IF(ISNUMBER(SEARCH("CI/CD",K11)),1,0)) -> 0 | AM11: =IF(ISBLANK(L11),0,IF(ISNUMBER(SEARCH("Python",L11)),1,0)) -> 0 | AN11: =IF(ISBLANK(L11),0,IF(ISNUMBER(SEARCH("SQL",L11)),1,0)) -> 0 | AO11: =IF(ISBLANK(L11),0,IF(ISNUMBER(SEARCH("Airflow",L11)),1,0)) -> 0 | AP11: =IF(ISBLANK(L11),0,IF(ISNUMBER(SEARCH("Kafka",L11)),1,0)) -> 0 | AQ11: =IF(ISBLANK(L11),0,IF(ISNUMBER(SEARCH("ML",L11)),1,0)) -> 0 | AR11: =IF(ISBLANK(L12),0,IF(ISNUMBER(SEARCH("ML",L12)),1,0)) -> 0 | AS11: =IF(ISBLANK(L13),0,IF(ISNUMBER(SEARCH("Docker",L13)),1,0)) -> 0 | AT11: =IF(ISBLANK(L13),0,IF(ISNUMBER(SEARCH("dbt",L13)),1,0)) -> 0 | AU11: =IF(ISBLANK(L13),0,IF(ISNUMBER(SEARCH("AWS",L13)),1,0)) -> 0 | AV11: =IF(ISBLANK(L13),0,IF(ISNUMBER(SEARCH("GCP",L13)),1,0)) -> 0 | AW11: =IF(ISBLANK(L13),0,IF(ISNUMBER(SEARCH("Azure",L13)),1,0)) -> 0 | AX11: =IF(ISBLANK(M13),0,IF(ISNUMBER(SEARCH("Tableau",L13)),1,0)) -> 0 | AY11: =IF(ISBLANK(N13),0,IF(ISNUMBER(SEARCH("PowerBI",L13)),1,0)) -> 0 | AZ11: Fulltime
A12: 11 | B12: 46178 | C12: LinkedIn | D12: Data Analyst | E12: Google | F12: Hyderabad | G12: 2 | H12: ND | I12: ND | J12: ND | K12: SQL, Python, R | L12: C++, Machine Learning(familarity), Risk Analysis | M12: On-site | N12: Large | O12: =IF(ISBLANK(K12),0,IF(ISNUMBER(SEARCH("sql",K12)),1,0)) -> 1 | P12: =IF(ISBLANK(K12),0,IF(ISNUMBER(SEARCH("Python",K12)),1,0)) -> 1 | Q12: =IF(ISBLANK(K12),0,IF(ISNUMBER(SEARCH("PowerBI",K12)),1,0)) -> 0 | R12: =IF(ISBLANK(K12),0,IF(ISNUMBER(SEARCH("Tableau",K12)),1,0)) -> 0 | S12: =IF(ISBLANK(K12),0,IF(ISNUMBER(SEARCH("Excel",K12)),1,0)) -> 0 | T12: =IF(ISBLANK(K12),0,IF(ISNUMBER(SEARCH("Statistics",K12)),1,0)) -> 0 | U12: =IF(ISBLANK(K12),0,IF(ISNUMBER(SEARCH("AWS",K12)),1,0)) -> 0 | V12: =IF(ISBLANK(K12),0,IF(ISNUMBER(SEARCH("GCP",K12)),1,0)) -> 0 | W12: =IF(ISBLANK(K12),0,IF(ISNUMBER(SEARCH("NoSQL",K12)),1,0)) -> 0 | X12: =IF(ISBLANK(K12),0,IF(ISNUMBER(SEARCH("Data Modeling",K12)),1,0)) -> 0 | Y12: =IF(ISBLANK(K12),0,IF(ISNUMBER(SEARCH("Pandas",K12)),1,0)) -> 0 | Z12: =IF(ISBLANK(K12),0,IF(ISNUMBER(SEARCH("Numpy",K12)),1,0)) -> 0 | AA12: =IF(ISBLANK(K12),0,IF(ISNUMBER(SEARCH("Pyspark",K12)),1,0)) -> 0 | AB12: =IF(ISBLANK(K12),0,IF(ISNUMBER(SEARCH("Hadoop",K12)),1,0)) -> 0 | AC12: =IF(ISBLANK(K12),0,IF(ISNUMBER(SEARCH("ETL",K12)),1,0)) -> 0 | AD12: =IF(ISBLANK(K12),0,IF(ISNUMBER(SEARCH("Azure",K12)),1,0)) -> 0 | AE12: =IF(ISBLANK(K12),0,IF(ISNUMBER(SEARCH("Databricks",K12)),1,0)) -> 0 | AF12: =IF(ISBLANK(K12),0,IF(ISNUMBER(SEARCH("A/B Testing",K12)),1,0)) -> 0 | AG12: =IF(ISBLANK(K12),0,IF(ISNUMBER(SEARCH("Snowflake",K12)),1,0)) -> 0 | AH12: =IF(ISBLANK(K12),0,IF(ISNUMBER(SEARCH("Agile",K12)),1,0)) -> 0 | AI12: =IF(ISBLANK(K12),0,IF(ISNUMBER(SEARCH("Jira",K12)),1,0)) -> 0 | AJ12: =IF(ISBLANK(K12),0,IF(ISNUMBER(SEARCH("Git",K12)),1,0)) -> 0 | AK12: =IF(ISBLANK(K12),0,IF(ISNUMBER(SEARCH("Reporting",K12)),1,0)) -> 0 | AL12: =IF(ISBLANK(K12),0,IF(ISNUMBER(SEARCH("CI/CD",K12)),1,0)) -> 0 | AM12: =IF(ISBLANK(L12),0,IF(ISNUMBER(SEARCH("Python",L12)),1,0)) -> 0 | AN12: =IF(ISBLANK(L12),0,IF(ISNUMBER(SEARCH("SQL",L12)),1,0)) -> 0 | AO12: =IF(ISBLANK(L12),0,IF(ISNUMBER(SEARCH("Airflow",L12)),1,0)) -> 0 | AP12: =IF(ISBLANK(L12),0,IF(ISNUMBER(SEARCH("Kafka",L12)),1,0)) -> 0 | AQ12: =IF(ISBLANK(L12),0,IF(ISNUMBER(SEARCH("ML",L12)),1,0)) -> 0 | AR12: =IF(ISBLANK(L13),0,IF(ISNUMBER(SEARCH("ML",L13)),1,0)) -> 0 | AS12: =IF(ISBLANK(L14),0,IF(ISNUMBER(SEARCH("Docker",L14)),1,0)) -> 0 | AT12: =IF(ISBLANK(L14),0,IF(ISNUMBER(SEARCH("dbt",L14)),1,0)) -> 0 | AU12: =IF(ISBLANK(L14),0,IF(ISNUMBER(SEARCH("AWS",L14)),1,0)) -> 0 | AV12: =IF(ISBLANK(L14),0,IF(ISNUMBER(SEARCH("GCP",L14)),1,0)) -> 0 | AW12: =IF(ISBLANK(L14),0,IF(ISNUMBER(SEARCH("Azure",L14)),1,0)) -> 1 | AX12: =IF(ISBLANK(M14),0,IF(ISNUMBER(SEARCH("Tableau",L14)),1,0)) -> 0 | AY12: =IF(ISBLANK(N14),0,IF(ISNUMBER(SEARCH("PowerBI",L14)),1,0)) -> 0 | AZ12: Fulltime
A13: 12 | B13: 46178 | C13: LinkedIn | D13: Data Analyst | E13: Persistent Systems | F13: Pune | G13: 5 | H13: 8 | I13: ND | J13: ND | K13: SQL,ETL , Data Transformation | L13: Python & Cloud exposure | M13: On-site | N13: Large | O13: =IF(ISBLANK(K13),0,IF(ISNUMBER(SEARCH("sql",K13)),1,0)) -> 1 | P13: =IF(ISBLANK(K13),0,IF(ISNUMBER(SEARCH("Python",K13)),1,0)) -> 0 | Q13: =IF(ISBLANK(K13),0,IF(ISNUMBER(SEARCH("PowerBI",K13)),1,0)) -> 0 | R13: =IF(ISBLANK(K13),0,IF(ISNUMBER(SEARCH("Tableau",K13)),1,0)) -> 0 | S13: =IF(ISBLANK(K13),0,IF(ISNUMBER(SEARCH("Excel",K13)),1,0)) -> 0 | T13: =IF(ISBLANK(K13),0,IF(ISNUMBER(SEARCH("Statistics",K13)),1,0)) -> 0 | U13: =IF(ISBLANK(K13),0,IF(ISNUMBER(SEARCH("AWS",K13)),1,0)) -> 0 | V13: =IF(ISBLANK(K13),0,IF(ISNUMBER(SEARCH("GCP",K13)),1,0)) -> 0 | W13: =IF(ISBLANK(K13),0,IF(ISNUMBER(SEARCH("NoSQL",K13)),1,0)) -> 0 | X13: =IF(ISBLANK(K13),0,IF(ISNUMBER(SEARCH("Data Modeling",K13)),1,0)) -> 0 | Y13: =IF(ISBLANK(K13),0,IF(ISNUMBER(SEARCH("Pandas",K13)),1,0)) -> 0 | Z13: =IF(ISBLANK(K13),0,IF(ISNUMBER(SEARCH("Numpy",K13)),1,0)) -> 0 | AA13: =IF(ISBLANK(K13),0,IF(ISNUMBER(SEARCH("Pyspark",K13)),1,0)) -> 0 | AB13: =IF(ISBLANK(K13),0,IF(ISNUMBER(SEARCH("Hadoop",K13)),1,0)) -> 0 | AC13: =IF(ISBLANK(K13),0,IF(ISNUMBER(SEARCH("ETL",K13)),1,0)) -> 1 | AD13: =IF(ISBLANK(K13),0,IF(ISNUMBER(SEARCH("Azure",K13)),1,0)) -> 0 | AE13: =IF(ISBLANK(K13),0,IF(ISNUMBER(SEARCH("Databricks",K13)),1,0)) -> 0 | AF13: =IF(ISBLANK(K13),0,IF(ISNUMBER(SEARCH("A/B Testing",K13)),1,0)) -> 0 | AG13: =IF(ISBLANK(K13),0,IF(ISNUMBER(SEARCH("Snowflake",K13)),1,0)) -> 0 | AH13: =IF(ISBLANK(K13),0,IF(ISNUMBER(SEARCH("Agile",K13)),1,0)) -> 0 | AI13: =IF(ISBLANK(K13),0,IF(ISNUMBER(SEARCH("Jira",K13)),1,0)) -> 0 | AJ13: =IF(ISBLANK(K13),0,IF(ISNUMBER(SEARCH("Git",K13)),1,0)) -> 0 | AK13: =IF(ISBLANK(K13),0,IF(ISNUMBER(SEARCH("Reporting",K13)),1,0)) -> 0 | AL13: =IF(ISBLANK(K13),0,IF(ISNUMBER(SEARCH("CI/CD",K13)),1,0)) -> 0 | AM13: =IF(ISBLANK(L13),0,IF(ISNUMBER(SEARCH("Python",L13)),1,0)) -> 1 | AN13: =IF(ISBLANK(L13),0,IF(ISNUMBER(SEARCH("SQL",L13)),1,0)) -> 0 | AO13: =IF(ISBLANK(L13),0,IF(ISNUMBER(SEARCH("Airflow",L13)),1,0)) -> 0 | AP13: =IF(ISBLANK(L13),0,IF(ISNUMBER(SEARCH("Kafka",L13)),1,0)) -> 0 | AQ13: =IF(ISBLANK(L13),0,IF(ISNUMBER(SEARCH("ML",L13)),1,0)) -> 0 | AR13: =IF(ISBLANK(L14),0,IF(ISNUMBER(SEARCH("ML",L14)),1,0)) -> 0 | AS13: =IF(ISBLANK(L15),0,IF(ISNUMBER(SEARCH("Docker",L15)),1,0)) -> 0 | AT13: =IF(ISBLANK(L15),0,IF(ISNUMBER(SEARCH("dbt",L15)),1,0)) -> 0 | AU13: =IF(ISBLANK(L15),0,IF(ISNUMBER(SEARCH("AWS",L15)),1,0)) -> 0 | AV13: =IF(ISBLANK(L15),0,IF(ISNUMBER(SEARCH("GCP",L15)),1,0)) -> 0 | AW13: =IF(ISBLANK(L15),0,IF(ISNUMBER(SEARCH("Azure",L15)),1,0)) -> 0 | AX13: =IF(ISBLANK(M15),0,IF(ISNUMBER(SEARCH("Tableau",L15)),1,0)) -> 0 | AY13: =IF(ISBLANK(N15),0,IF(ISNUMBER(SEARCH("PowerBI",L15)),1,0)) -> 0 | AZ13: Fulltime
A14: 13 | B14: 46178 | C14: LinkedIn | D14: Data Analyst | E14: CoffeeBeans | F14: Bengaluru | G14: 7 | H14: 10 | I14: ND | J14: ND | K14: Advanced SQL , PowerBI , Github | L14: Azure data systems, ETL pipelines, Agile/Scrum | M14: On-site | N14: Medium | O14: =IF(ISBLANK(K14),0,IF(ISNUMBER(SEARCH("sql",K14)),1,0)) -> 1 | P14: =IF(ISBLANK(K14),0,IF(ISNUMBER(SEARCH("Python",K14)),1,0)) -> 0 | Q14: =IF(ISBLANK(K14),0,IF(ISNUMBER(SEARCH("PowerBI",K14)),1,0)) -> 1 | R14: =IF(ISBLANK(K14),0,IF(ISNUMBER(SEARCH("Tableau",K14)),1,0)) -> 0 | S14: =IF(ISBLANK(K14),0,IF(ISNUMBER(SEARCH("Excel",K14)),1,0)) -> 0 | T14: =IF(ISBLANK(K14),0,IF(ISNUMBER(SEARCH("Statistics",K14)),1,0)) -> 0 | U14: =IF(ISBLANK(K14),0,IF(ISNUMBER(SEARCH("AWS",K14)),1,0)) -> 0 | V14: =IF(ISBLANK(K14),0,IF(ISNUMBER(SEARCH("GCP",K14)),1,0)) -> 0 | W14: =IF(ISBLANK(K14),0,IF(ISNUMBER(SEARCH("NoSQL",K14)),1,0)) -> 0 | X14: =IF(ISBLANK(K14),0,IF(ISNUMBER(SEARCH("Data Modeling",K14)),1,0)) -> 0 | Y14: =IF(ISBLANK(K14),0,IF(ISNUMBER(SEARCH("Pandas",K14)),1,0)) -> 0 | Z14: =IF(ISBLANK(K14),0,IF(ISNUMBER(SEARCH("Numpy",K14)),1,0)) -> 0 | AA14: =IF(ISBLANK(K14),0,IF(ISNUMBER(SEARCH("Pyspark",K14)),1,0)) -> 0 | AB14: =IF(ISBLANK(K14),0,IF(ISNUMBER(SEARCH("Hadoop",K14)),1,0)) -> 0 | AC14: =IF(ISBLANK(K14),0,IF(ISNUMBER(SEARCH("ETL",K14)),1,0)) -> 0 | AD14: =IF(ISBLANK(K14),0,IF(ISNUMBER(SEARCH("Azure",K14)),1,0)) -> 0 | AE14: =IF(ISBLANK(K14),0,IF(ISNUMBER(SEARCH("Databricks",K14)),1,0)) -> 0 | AF14: =IF(ISBLANK(K14),0,IF(ISNUMBER(SEARCH("A/B Testing",K14)),1,0)) -> 0 | AG14: =IF(ISBLANK(K14),0,IF(ISNUMBER(SEARCH("Snowflake",K14)),1,0)) -> 0 | AH14: =IF(ISBLANK(K14),0,IF(ISNUMBER(SEARCH("Agile",K14)),1,0)) -> 0 | AI14: =IF(ISBLANK(K14),0,IF(ISNUMBER(SEARCH("Jira",K14)),1,0)) -> 0 | AJ14: =IF(ISBLANK(K14),0,IF(ISNUMBER(SEARCH("Git",K14)),1,0)) -> 1 | AK14: =IF(ISBLANK(K14),0,IF(ISNUMBER(SEARCH("Reporting",K14)),1,0)) -> 0 | AL14: =IF(ISBLANK(K14),0,IF(ISNUMBER(SEARCH("CI/CD",K14)),1,0)) -> 0 | AM14: =IF(ISBLANK(L14),0,IF(ISNUMBER(SEARCH("Python",L14)),1,0)) -> 0 | AN14: =IF(ISBLANK(L14),0,IF(ISNUMBER(SEARCH("SQL",L14)),1,0)) -> 0 | AO14: =IF(ISBLANK(L14),0,IF(ISNUMBER(SEARCH("Airflow",L14)),1,0)) -> 0 | AP14: =IF(ISBLANK(L14),0,IF(ISNUMBER(SEARCH("Kafka",L14)),1,0)) -> 0 | AQ14: =IF(ISBLANK(L14),0,IF(ISNUMBER(SEARCH("ML",L14)),1,0)) -> 0 | AR14: =IF(ISBLANK(L15),0,IF(ISNUMBER(SEARCH("ML",L15)),1,0)) -> 0 | AS14: =IF(ISBLANK(L16),0,IF(ISNUMBER(SEARCH("Docker",L16)),1,0)) -> 0 | AT14: =IF(ISBLANK(L16),0,IF(ISNUMBER(SEARCH("dbt",L16)),1,0)) -> 0 | AU14: =IF(ISBLANK(L16),0,IF(ISNUMBER(SEARCH("AWS",L16)),1,0)) -> 0 | AV14: =IF(ISBLANK(L16),0,IF(ISNUMBER(SEARCH("GCP",L16)),1,0)) -> 0 | AW14: =IF(ISBLANK(L16),0,IF(ISNUMBER(SEARCH("Azure",L16)),1,0)) -> 0 | AX14: =IF(ISBLANK(M16),0,IF(ISNUMBER(SEARCH("Tableau",L16)),1,0)) -> 0 | AY14: =IF(ISBLANK(N16),0,IF(ISNUMBER(SEARCH("PowerBI",L16)),1,0)) -> 0 | AZ14: Fulltime
A15: 14 | B15: 46178 | C15: LinkedIn | D15: Data Analyst | E15: Skeps | F15: Gurgaon | G15: 2 | H15: ND | I15: ND | J15: ND | K15: Excel , SQL, Python , Dashboarding Tools(Tableau, Metabase etc), Statistics,Pandas, Numpy , Scikit learn,Seaborn | L15: None | M15: On-site | N15: Startup | O15: =IF(ISBLANK(K15),0,IF(ISNUMBER(SEARCH("sql",K15)),1,0)) -> 1 | P15: =IF(ISBLANK(K15),0,IF(ISNUMBER(SEARCH("Python",K15)),1,0)) -> 1 | Q15: =IF(ISBLANK(K15),0,IF(ISNUMBER(SEARCH("PowerBI",K15)),1,0)) -> 0 | R15: =IF(ISBLANK(K15),0,IF(ISNUMBER(SEARCH("Tableau",K15)),1,0)) -> 1 | S15: =IF(ISBLANK(K15),0,IF(ISNUMBER(SEARCH("Excel",K15)),1,0)) -> 1 | T15: =IF(ISBLANK(K15),0,IF(ISNUMBER(SEARCH("Statistics",K15)),1,0)) -> 1 | U15: =IF(ISBLANK(K15),0,IF(ISNUMBER(SEARCH("AWS",K15)),1,0)) -> 0 | V15: =IF(ISBLANK(K15),0,IF(ISNUMBER(SEARCH("GCP",K15)),1,0)) -> 0 | W15: =IF(ISBLANK(K15),0,IF(ISNUMBER(SEARCH("NoSQL",K15)),1,0)) -> 0 | X15: =IF(ISBLANK(K15),0,IF(ISNUMBER(SEARCH("Data Modeling",K15)),1,0)) -> 0 | Y15: =IF(ISBLANK(K15),0,IF(ISNUMBER(SEARCH("Pandas",K15)),1,0)) -> 1 | Z15: =IF(ISBLANK(K15),0,IF(ISNUMBER(SEARCH("Numpy",K15)),1,0)) -> 1 | AA15: =IF(ISBLANK(K15),0,IF(ISNUMBER(SEARCH("Pyspark",K15)),1,0)) -> 0 | AB15: =IF(ISBLANK(K15),0,IF(ISNUMBER(SEARCH("Hadoop",K15)),1,0)) -> 0 | AC15: =IF(ISBLANK(K15),0,IF(ISNUMBER(SEARCH("ETL",K15)),1,0)) -> 0 | AD15: =IF(ISBLANK(K15),0,IF(ISNUMBER(SEARCH("Azure",K15)),1,0)) -> 0 | AE15: =IF(ISBLANK(K15),0,IF(ISNUMBER(SEARCH("Databricks",K15)),1,0)) -> 0 | AF15: =IF(ISBLANK(K15),0,IF(ISNUMBER(SEARCH("A/B Testing",K15)),1,0)) -> 0 | AG15: =IF(ISBLANK(K15),0,IF(ISNUMBER(SEARCH("Snowflake",K15)),1,0)) -> 0 | AH15: =IF(ISBLANK(K15),0,IF(ISNUMBER(SEARCH("Agile",K15)),1,0)) -> 0 | AI15: =IF(ISBLANK(K15),0,IF(ISNUMBER(SEARCH("Jira",K15)),1,0)) -> 0 | AJ15: =IF(ISBLANK(K15),0,IF(ISNUMBER(SEARCH("Git",K15)),1,0)) -> 0 | AK15: =IF(ISBLANK(K15),0,IF(ISNUMBER(SEARCH("Reporting",K15)),1,0)) -> 0 | AL15: =IF(ISBLANK(K15),0,IF(ISNUMBER(SEARCH("CI/CD",K15)),1,0)) -> 0 | AM15: =IF(ISBLANK(L15),0,IF(ISNUMBER(SEARCH("Python",L15)),1,0)) -> 0 | AN15: =IF(ISBLANK(L15),0,IF(ISNUMBER(SEARCH("SQL",L15)),1,0)) -> 0 | AO15: =IF(ISBLANK(L15),0,IF(ISNUMBER(SEARCH("Airflow",L15)),1,0)) -> 0 | AP15: =IF(ISBLANK(L15),0,IF(ISNUMBER(SEARCH("Kafka",L15)),1,0)) -> 0 | AQ15: =IF(ISBLANK(L15),0,IF(ISNUMBER(SEARCH("ML",L15)),1,0)) -> 0 | AR15: =IF(ISBLANK(L16),0,IF(ISNUMBER(SEARCH("ML",L16)),1,0)) -> 0 | AS15: =IF(ISBLANK(L17),0,IF(ISNUMBER(SEARCH("Docker",L17)),1,0)) -> 0 | AT15: =IF(ISBLANK(L17),0,IF(ISNUMBER(SEARCH("dbt",L17)),1,0)) -> 0 | AU15: =IF(ISBLANK(L17),0,IF(ISNUMBER(SEARCH("AWS",L17)),1,0)) -> 1 | AV15: =IF(ISBLANK(L17),0,IF(ISNUMBER(SEARCH("GCP",L17)),1,0)) -> 1 | AW15: =IF(ISBLANK(L17),0,IF(ISNUMBER(SEARCH("Azure",L17)),1,0)) -> 1 | AX15: =IF(ISBLANK(M17),0,IF(ISNUMBER(SEARCH("Tableau",L17)),1,0)) -> 0 | AY15: =IF(ISBLANK(N17),0,IF(ISNUMBER(SEARCH("PowerBI",L17)),1,0)) -> 0 | AZ15: Fulltime
A16: 15 | B16: 46178 | C16: LinkedIn | D16: Data Analyst | E16: Prudent Technologies and Consulting Inc | F16: Hyderabad | G16: 2 | H16: 5 | I16: ND | J16: ND | K16: MySQL , DAX , PowerBI, Data Analysis | L16: None | M16: On-site | N16: Large | O16: =IF(ISBLANK(K16),0,IF(ISNUMBER(SEARCH("sql",K16)),1,0)) -> 1 | P16: =IF(ISBLANK(K16),0,IF(ISNUMBER(SEARCH("Python",K16)),1,0)) -> 0 | Q16: =IF(ISBLANK(K16),0,IF(ISNUMBER(SEARCH("PowerBI",K16)),1,0)) -> 1 | R16: =IF(ISBLANK(K16),0,IF(ISNUMBER(SEARCH("Tableau",K16)),1,0)) -> 0 | S16: =IF(ISBLANK(K16),0,IF(ISNUMBER(SEARCH("Excel",K16)),1,0)) -> 0 | T16: =IF(ISBLANK(K16),0,IF(ISNUMBER(SEARCH("Statistics",K16)),1,0)) -> 0 | U16: =IF(ISBLANK(K16),0,IF(ISNUMBER(SEARCH("AWS",K16)),1,0)) -> 0 | V16: =IF(ISBLANK(K16),0,IF(ISNUMBER(SEARCH("GCP",K16)),1,0)) -> 0 | W16: =IF(ISBLANK(K16),0,IF(ISNUMBER(SEARCH("NoSQL",K16)),1,0)) -> 0 | X16: =IF(ISBLANK(K16),0,IF(ISNUMBER(SEARCH("Data Modeling",K16)),1,0)) -> 0 | Y16: =IF(ISBLANK(K16),0,IF(ISNUMBER(SEARCH("Pandas",K16)),1,0)) -> 0 | Z16: =IF(ISBLANK(K16),0,IF(ISNUMBER(SEARCH("Numpy",K16)),1,0)) -> 0 | AA16: =IF(ISBLANK(K16),0,IF(ISNUMBER(SEARCH("Pyspark",K16)),1,0)) -> 0 | AB16: =IF(ISBLANK(K16),0,IF(ISNUMBER(SEARCH("Hadoop",K16)),1,0)) -> 0 | AC16: =IF(ISBLANK(K16),0,IF(ISNUMBER(SEARCH("ETL",K16)),1,0)) -> 0 | AD16: =IF(ISBLANK(K16),0,IF(ISNUMBER(SEARCH("Azure",K16)),1,0)) -> 0 | AE16: =IF(ISBLANK(K16),0,IF(ISNUMBER(SEARCH("Databricks",K16)),1,0)) -> 0 | AF16: =IF(ISBLANK(K16),0,IF(ISNUMBER(SEARCH("A/B Testing",K16)),1,0)) -> 0 | AG16: =IF(ISBLANK(K16),0,IF(ISNUMBER(SEARCH("Snowflake",K16)),1,0)) -> 0 | AH16: =IF(ISBLANK(K16),0,IF(ISNUMBER(SEARCH("Agile",K16)),1,0)) -> 0 | AI16: =IF(ISBLANK(K16),0,IF(ISNUMBER(SEARCH("Jira",K16)),1,0)) -> 0 | AJ16: =IF(ISBLANK(K16),0,IF(ISNUMBER(SEARCH("Git",K16)),1,0)) -> 0 | AK16: =IF(ISBLANK(K16),0,IF(ISNUMBER(SEARCH("Reporting",K16)),1,0)) -> 0 | AL16: =IF(ISBLANK(K16),0,IF(ISNUMBER(SEARCH("CI/CD",K16)),1,0)) -> 0 | AM16: =IF(ISBLANK(L16),0,IF(ISNUMBER(SEARCH("Python",L16)),1,0)) -> 0 | AN16: =IF(ISBLANK(L16),0,IF(ISNUMBER(SEARCH("SQL",L16)),1,0)) -> 0 | AO16: =IF(ISBLANK(L16),0,IF(ISNUMBER(SEARCH("Airflow",L16)),1,0)) -> 0 | AP16: =IF(ISBLANK(L16),0,IF(ISNUMBER(SEARCH("Kafka",L16)),1,0)) -> 0 | AQ16: =IF(ISBLANK(L16),0,IF(ISNUMBER(SEARCH("ML",L16)),1,0)) -> 0 | AR16: =IF(ISBLANK(L17),0,IF(ISNUMBER(SEARCH("ML",L17)),1,0)) -> 0 | AS16: =IF(ISBLANK(L18),0,IF(ISNUMBER(SEARCH("Docker",L18)),1,0)) -> 0 | AT16: =IF(ISBLANK(L18),0,IF(ISNUMBER(SEARCH("dbt",L18)),1,0)) -> 0 | AU16: =IF(ISBLANK(L18),0,IF(ISNUMBER(SEARCH("AWS",L18)),1,0)) -> 0 | AV16: =IF(ISBLANK(L18),0,IF(ISNUMBER(SEARCH("GCP",L18)),1,0)) -> 0 | AW16: =IF(ISBLANK(L18),0,IF(ISNUMBER(SEARCH("Azure",L18)),1,0)) -> 0 | AX16: =IF(ISBLANK(M18),0,IF(ISNUMBER(SEARCH("Tableau",L18)),1,0)) -> 0 | AY16: =IF(ISBLANK(N18),0,IF(ISNUMBER(SEARCH("PowerBI",L18)),1,0)) -> 0 | AZ16: Fulltime
A17: 16 | B17: 46178 | C17: LinkedIn | D17: Data Analyst | E17: Call Quest Solutions | F17: Pune | G17: ND | H17: ND | I17: ND | J17: ND | K17: SQL , Excel , Python /R, Data visualization tools | L17: AWS/Azure/GCP, Predictive analytics, Data warehouse concepts | M17: On-site | N17: Medium | O17: =IF(ISBLANK(K17),0,IF(ISNUMBER(SEARCH("sql",K17)),1,0)) -> 1 | P17: =IF(ISBLANK(K17),0,IF(ISNUMBER(SEARCH("Python",K17)),1,0)) -> 1 | Q17: =IF(ISBLANK(K17),0,IF(ISNUMBER(SEARCH("PowerBI",K17)),1,0)) -> 0 | R17: =IF(ISBLANK(K17),0,IF(ISNUMBER(SEARCH("Tableau",K17)),1,0)) -> 0 | S17: =IF(ISBLANK(K17),0,IF(ISNUMBER(SEARCH("Excel",K17)),1,0)) -> 1 | T17: =IF(ISBLANK(K17),0,IF(ISNUMBER(SEARCH("Statistics",K17)),1,0)) -> 0 | U17: =IF(ISBLANK(K17),0,IF(ISNUMBER(SEARCH("AWS",K17)),1,0)) -> 0 | V17: =IF(ISBLANK(K17),0,IF(ISNUMBER(SEARCH("GCP",K17)),1,0)) -> 0 | W17: =IF(ISBLANK(K17),0,IF(ISNUMBER(SEARCH("NoSQL",K17)),1,0)) -> 0 | X17: =IF(ISBLANK(K17),0,IF(ISNUMBER(SEARCH("Data Modeling",K17)),1,0)) -> 0 | Y17: =IF(ISBLANK(K17),0,IF(ISNUMBER(SEARCH("Pandas",K17)),1,0)) -> 0 | Z17: =IF(ISBLANK(K17),0,IF(ISNUMBER(SEARCH("Numpy",K17)),1,0)) -> 0 | AA17: =IF(ISBLANK(K17),0,IF(ISNUMBER(SEARCH("Pyspark",K17)),1,0)) -> 0 | AB17: =IF(ISBLANK(K17),0,IF(ISNUMBER(SEARCH("Hadoop",K17)),1,0)) -> 0 | AC17: =IF(ISBLANK(K17),0,IF(ISNUMBER(SEARCH("ETL",K17)),1,0)) -> 0 | AD17: =IF(ISBLANK(K17),0,IF(ISNUMBER(SEARCH("Azure",K17)),1,0)) -> 0 | AE17: =IF(ISBLANK(K17),0,IF(ISNUMBER(SEARCH("Databricks",K17)),1,0)) -> 0 | AF17: =IF(ISBLANK(K17),0,IF(ISNUMBER(SEARCH("A/B Testing",K17)),1,0)) -> 0 | AG17: =IF(ISBLANK(K17),0,IF(ISNUMBER(SEARCH("Snowflake",K17)),1,0)) -> 0 | AH17: =IF(ISBLANK(K17),0,IF(ISNUMBER(SEARCH("Agile",K17)),1,0)) -> 0 | AI17: =IF(ISBLANK(K17),0,IF(ISNUMBER(SEARCH("Jira",K17)),1,0)) -> 0 | AJ17: =IF(ISBLANK(K17),0,IF(ISNUMBER(SEARCH("Git",K17)),1,0)) -> 0 | AK17: =IF(ISBLANK(K17),0,IF(ISNUMBER(SEARCH("Reporting",K17)),1,0)) -> 0 | AL17: =IF(ISBLANK(K17),0,IF(ISNUMBER(SEARCH("CI/CD",K17)),1,0)) -> 0 | AM17: =IF(ISBLANK(L17),0,IF(ISNUMBER(SEARCH("Python",L17)),1,0)) -> 0 | AN17: =IF(ISBLANK(L17),0,IF(ISNUMBER(SEARCH("SQL",L17)),1,0)) -> 0 | AO17: =IF(ISBLANK(L17),0,IF(ISNUMBER(SEARCH("Airflow",L17)),1,0)) -> 0 | AP17: =IF(ISBLANK(L17),0,IF(ISNUMBER(SEARCH("Kafka",L17)),1,0)) -> 0 | AQ17: =IF(ISBLANK(L17),0,IF(ISNUMBER(SEARCH("ML",L17)),1,0)) -> 0 | AR17: =IF(ISBLANK(L18),0,IF(ISNUMBER(SEARCH("ML",L18)),1,0)) -> 0 | AS17: =IF(ISBLANK(L19),0,IF(ISNUMBER(SEARCH("Docker",L19)),1,0)) -> 0 | AT17: =IF(ISBLANK(L19),0,IF(ISNUMBER(SEARCH("dbt",L19)),1,0)) -> 0 | AU17: =IF(ISBLANK(L19),0,IF(ISNUMBER(SEARCH("AWS",L19)),1,0)) -> 0 | AV17: =IF(ISBLANK(L19),0,IF(ISNUMBER(SEARCH("GCP",L19)),1,0)) -> 0 | AW17: =IF(ISBLANK(L19),0,IF(ISNUMBER(SEARCH("Azure",L19)),1,0)) -> 0 | AX17: =IF(ISBLANK(M19),0,IF(ISNUMBER(SEARCH("Tableau",L19)),1,0)) -> 0 | AY17: =IF(ISBLANK(N19),0,IF(ISNUMBER(SEARCH("PowerBI",L19)),1,0)) -> 0 | AZ17: Fulltime
A18: 17 | B18: 46178 | C18: LinkedIn | D18: Data Analyst | E18: Infovision | F18: Bengaluru | G18: ND | H18: ND | I18: ND | J18: ND | K18: Python,SQL, Git, Statistics, Advanced Excel, Data visualization tools | L18: None | M18: On-site | N18: Medium | O18: =IF(ISBLANK(K18),0,IF(ISNUMBER(SEARCH("sql",K18)),1,0)) -> 1 | P18: =IF(ISBLANK(K18),0,IF(ISNUMBER(SEARCH("Python",K18)),1,0)) -> 1 | Q18: =IF(ISBLANK(K18),0,IF(ISNUMBER(SEARCH("PowerBI",K18)),1,0)) -> 0 | R18: =IF(ISBLANK(K18),0,IF(ISNUMBER(SEARCH("Tableau",K18)),1,0)) -> 0 | S18: =IF(ISBLANK(K18),0,IF(ISNUMBER(SEARCH("Excel",K18)),1,0)) -> 1 | T18: =IF(ISBLANK(K18),0,IF(ISNUMBER(SEARCH("Statistics",K18)),1,0)) -> 1 | U18: =IF(ISBLANK(K18),0,IF(ISNUMBER(SEARCH("AWS",K18)),1,0)) -> 0 | V18: =IF(ISBLANK(K18),0,IF(ISNUMBER(SEARCH("GCP",K18)),1,0)) -> 0 | W18: =IF(ISBLANK(K18),0,IF(ISNUMBER(SEARCH("NoSQL",K18)),1,0)) -> 0 | X18: =IF(ISBLANK(K18),0,IF(ISNUMBER(SEARCH("Data Modeling",K18)),1,0)) -> 0 | Y18: =IF(ISBLANK(K18),0,IF(ISNUMBER(SEARCH("Pandas",K18)),1,0)) -> 0 | Z18: =IF(ISBLANK(K18),0,IF(ISNUMBER(SEARCH("Numpy",K18)),1,0)) -> 0 | AA18: =IF(ISBLANK(K18),0,IF(ISNUMBER(SEARCH("Pyspark",K18)),1,0)) -> 0 | AB18: =IF(ISBLANK(K18),0,IF(ISNUMBER(SEARCH("Hadoop",K18)),1,0)) -> 0 | AC18: =IF(ISBLANK(K18),0,IF(ISNUMBER(SEARCH("ETL",K18)),1,0)) -> 0 | AD18: =IF(ISBLANK(K18),0,IF(ISNUMBER(SEARCH("Azure",K18)),1,0)) -> 0 | AE18: =IF(ISBLANK(K18),0,IF(ISNUMBER(SEARCH("Databricks",K18)),1,0)) -> 0 | AF18: =IF(ISBLANK(K18),0,IF(ISNUMBER(SEARCH("A/B Testing",K18)),1,0)) -> 0 | AG18: =IF(ISBLANK(K18),0,IF(ISNUMBER(SEARCH("Snowflake",K18)),1,0)) -> 0 | AH18: =IF(ISBLANK(K18),0,IF(ISNUMBER(SEARCH("Agile",K18)),1,0)) -> 0 | AI18: =IF(ISBLANK(K18),0,IF(ISNUMBER(SEARCH("Jira",K18)),1,0)) -> 0 | AJ18: =IF(ISBLANK(K18),0,IF(ISNUMBER(SEARCH("Git",K18)),1,0)) -> 1 | AK18: =IF(ISBLANK(K18),0,IF(ISNUMBER(SEARCH("Reporting",K18)),1,0)) -> 0 | AL18: =IF(ISBLANK(K18),0,IF(ISNUMBER(SEARCH("CI/CD",K18)),1,0)) -> 0 | AM18: =IF(ISBLANK(L18),0,IF(ISNUMBER(SEARCH("Python",L18)),1,0)) -> 0 | AN18: =IF(ISBLANK(L18),0,IF(ISNUMBER(SEARCH("SQL",L18)),1,0)) -> 0 | AO18: =IF(ISBLANK(L18),0,IF(ISNUMBER(SEARCH("Airflow",L18)),1,0)) -> 0 | AP18: =IF(ISBLANK(L18),0,IF(ISNUMBER(SEARCH("Kafka",L18)),1,0)) -> 0 | AQ18: =IF(ISBLANK(L18),0,IF(ISNUMBER(SEARCH("ML",L18)),1,0)) -> 0 | AR18: =IF(ISBLANK(L19),0,IF(ISNUMBER(SEARCH("ML",L19)),1,0)) -> 0 | AS18: =IF(ISBLANK(L20),0,IF(ISNUMBER(SEARCH("Docker",L20)),1,0)) -> 0 | AT18: =IF(ISBLANK(L20),0,IF(ISNUMBER(SEARCH("dbt",L20)),1,0)) -> 0 | AU18: =IF(ISBLANK(L20),0,IF(ISNUMBER(SEARCH("AWS",L20)),1,0)) -> 0 | AV18: =IF(ISBLANK(L20),0,IF(ISNUMBER(SEARCH("GCP",L20)),1,0)) -> 1 | AW18: =IF(ISBLANK(L20),0,IF(ISNUMBER(SEARCH("Azure",L20)),1,0)) -> 0 | AX18: =IF(ISBLANK(M20),0,IF(ISNUMBER(SEARCH("Tableau",L20)),1,0)) -> 0 | AY18: =IF(ISBLANK(N20),0,IF(ISNUMBER(SEARCH("PowerBI",L20)),1,0)) -> 0 | AZ18: Fulltime
A19: 18 | B19: 46178 | C19: LinkedIn | D19: Data Engineer | E19: Qualcomm | F19: Bengaluru | G19: 3 | H19: 5 | I19: ND | J19: ND | K19: Data Modeling, Data Analysis, Python , Advanced SQL , NpSQL , DB Unix Shell scripts | L19: None | M19: On-site | N19: Large | O19: =IF(ISBLANK(K19),0,IF(ISNUMBER(SEARCH("sql",K19)),1,0)) -> 1 | P19: =IF(ISBLANK(K19),0,IF(ISNUMBER(SEARCH("Python",K19)),1,0)) -> 1 | Q19: =IF(ISBLANK(K19),0,IF(ISNUMBER(SEARCH("PowerBI",K19)),1,0)) -> 0 | R19: =IF(ISBLANK(K19),0,IF(ISNUMBER(SEARCH("Tableau",K19)),1,0)) -> 0 | S19: =IF(ISBLANK(K19),0,IF(ISNUMBER(SEARCH("Excel",K19)),1,0)) -> 0 | T19: =IF(ISBLANK(K19),0,IF(ISNUMBER(SEARCH("Statistics",K19)),1,0)) -> 0 | U19: =IF(ISBLANK(K19),0,IF(ISNUMBER(SEARCH("AWS",K19)),1,0)) -> 0 | V19: =IF(ISBLANK(K19),0,IF(ISNUMBER(SEARCH("GCP",K19)),1,0)) -> 0 | W19: =IF(ISBLANK(K19),0,IF(ISNUMBER(SEARCH("NoSQL",K19)),1,0)) -> 0 | X19: =IF(ISBLANK(K19),0,IF(ISNUMBER(SEARCH("Data Modeling",K19)),1,0)) -> 1 | Y19: =IF(ISBLANK(K19),0,IF(ISNUMBER(SEARCH("Pandas",K19)),1,0)) -> 0 | Z19: =IF(ISBLANK(K19),0,IF(ISNUMBER(SEARCH("Numpy",K19)),1,0)) -> 0 | AA19: =IF(ISBLANK(K19),0,IF(ISNUMBER(SEARCH("Pyspark",K19)),1,0)) -> 0 | AB19: =IF(ISBLANK(K19),0,IF(ISNUMBER(SEARCH("Hadoop",K19)),1,0)) -> 0 | AC19: =IF(ISBLANK(K19),0,IF(ISNUMBER(SEARCH("ETL",K19)),1,0)) -> 0 | AD19: =IF(ISBLANK(K19),0,IF(ISNUMBER(SEARCH("Azure",K19)),1,0)) -> 0 | AE19: =IF(ISBLANK(K19),0,IF(ISNUMBER(SEARCH("Databricks",K19)),1,0)) -> 0 | AF19: =IF(ISBLANK(K19),0,IF(ISNUMBER(SEARCH("A/B Testing",K19)),1,0)) -> 0 | AG19: =IF(ISBLANK(K19),0,IF(ISNUMBER(SEARCH("Snowflake",K19)),1,0)) -> 0 | AH19: =IF(ISBLANK(K19),0,IF(ISNUMBER(SEARCH("Agile",K19)),1,0)) -> 0 | AI19: =IF(ISBLANK(K19),0,IF(ISNUMBER(SEARCH("Jira",K19)),1,0)) -> 0 | AJ19: =IF(ISBLANK(K19),0,IF(ISNUMBER(SEARCH("Git",K19)),1,0)) -> 0 | AK19: =IF(ISBLANK(K19),0,IF(ISNUMBER(SEARCH("Reporting",K19)),1,0)) -> 0 | AL19: =IF(ISBLANK(K19),0,IF(ISNUMBER(SEARCH("CI/CD",K19)),1,0)) -> 0 | AM19: =IF(ISBLANK(L19),0,IF(ISNUMBER(SEARCH("Python",L19)),1,0)) -> 0 | AN19: =IF(ISBLANK(L19),0,IF(ISNUMBER(SEARCH("SQL",L19)),1,0)) -> 0 | AO19: =IF(ISBLANK(L19),0,IF(ISNUMBER(SEARCH("Airflow",L19)),1,0)) -> 0 | AP19: =IF(ISBLANK(L19),0,IF(ISNUMBER(SEARCH("Kafka",L19)),1,0)) -> 0 | AQ19: =IF(ISBLANK(L19),0,IF(ISNUMBER(SEARCH("ML",L19)),1,0)) -> 0 | AR19: =IF(ISBLANK(L20),0,IF(ISNUMBER(SEARCH("ML",L20)),1,0)) -> 0 | AS19: =IF(ISBLANK(L21),0,IF(ISNUMBER(SEARCH("Docker",L21)),1,0)) -> 0 | AT19: =IF(ISBLANK(L21),0,IF(ISNUMBER(SEARCH("dbt",L21)),1,0)) -> 0 | AU19: =IF(ISBLANK(L21),0,IF(ISNUMBER(SEARCH("AWS",L21)),1,0)) -> 1 | AV19: =IF(ISBLANK(L21),0,IF(ISNUMBER(SEARCH("GCP",L21)),1,0)) -> 1 | AW19: =IF(ISBLANK(L21),0,IF(ISNUMBER(SEARCH("Azure",L21)),1,0)) -> 0 | AX19: =IF(ISBLANK(M21),0,IF(ISNUMBER(SEARCH("Tableau",L21)),1,0)) -> 0 | AY19: =IF(ISBLANK(N21),0,IF(ISNUMBER(SEARCH("PowerBI",L21)),1,0)) -> 0 | AZ19: Fulltime
A20: 19 | B20: 46178 | C20: LinkedIn | D20: Data Engineer | E20: Impetus | F20: Gurgaon | G20: 4 | H20: 6 | I20: ND | J20: ND | K20: PySpark, Hadoop, Hive, Python , Bash, SQL, Data warehousing | L20: GCP sevices such as bigquery, dataflow etc, Airflow | M20: On-site | N20: Medium | O20: =IF(ISBLANK(K20),0,IF(ISNUMBER(SEARCH("sql",K20)),1,0)) -> 1 | P20: =IF(ISBLANK(K20),0,IF(ISNUMBER(SEARCH("Python",K20)),1,0)) -> 1 | Q20: =IF(ISBLANK(K20),0,IF(ISNUMBER(SEARCH("PowerBI",K20)),1,0)) -> 0 | R20: =IF(ISBLANK(K20),0,IF(ISNUMBER(SEARCH("Tableau",K20)),1,0)) -> 0 | S20: =IF(ISBLANK(K20),0,IF(ISNUMBER(SEARCH("Excel",K20)),1,0)) -> 0 | T20: =IF(ISBLANK(K20),0,IF(ISNUMBER(SEARCH("Statistics",K20)),1,0)) -> 0 | U20: =IF(ISBLANK(K20),0,IF(ISNUMBER(SEARCH("AWS",K20)),1,0)) -> 0 | V20: =IF(ISBLANK(K20),0,IF(ISNUMBER(SEARCH("GCP",K20)),1,0)) -> 0 | W20: =IF(ISBLANK(K20),0,IF(ISNUMBER(SEARCH("NoSQL",K20)),1,0)) -> 0 | X20: =IF(ISBLANK(K20),0,IF(ISNUMBER(SEARCH("Data Modeling",K20)),1,0)) -> 0 | Y20: =IF(ISBLANK(K20),0,IF(ISNUMBER(SEARCH("Pandas",K20)),1,0)) -> 0 | Z20: =IF(ISBLANK(K20),0,IF(ISNUMBER(SEARCH("Numpy",K20)),1,0)) -> 0 | AA20: =IF(ISBLANK(K20),0,IF(ISNUMBER(SEARCH("Pyspark",K20)),1,0)) -> 1 | AB20: =IF(ISBLANK(K20),0,IF(ISNUMBER(SEARCH("Hadoop",K20)),1,0)) -> 1 | AC20: =IF(ISBLANK(K20),0,IF(ISNUMBER(SEARCH("ETL",K20)),1,0)) -> 0 | AD20: =IF(ISBLANK(K20),0,IF(ISNUMBER(SEARCH("Azure",K20)),1,0)) -> 0 | AE20: =IF(ISBLANK(K20),0,IF(ISNUMBER(SEARCH("Databricks",K20)),1,0)) -> 0 | AF20: =IF(ISBLANK(K20),0,IF(ISNUMBER(SEARCH("A/B Testing",K20)),1,0)) -> 0 | AG20: =IF(ISBLANK(K20),0,IF(ISNUMBER(SEARCH("Snowflake",K20)),1,0)) -> 0 | AH20: =IF(ISBLANK(K20),0,IF(ISNUMBER(SEARCH("Agile",K20)),1,0)) -> 0 | AI20: =IF(ISBLANK(K20),0,IF(ISNUMBER(SEARCH("Jira",K20)),1,0)) -> 0 | AJ20: =IF(ISBLANK(K20),0,IF(ISNUMBER(SEARCH("Git",K20)),1,0)) -> 0 | AK20: =IF(ISBLANK(K20),0,IF(ISNUMBER(SEARCH("Reporting",K20)),1,0)) -> 0 | AL20: =IF(ISBLANK(K20),0,IF(ISNUMBER(SEARCH("CI/CD",K20)),1,0)) -> 0 | AM20: =IF(ISBLANK(L20),0,IF(ISNUMBER(SEARCH("Python",L20)),1,0)) -> 0 | AN20: =IF(ISBLANK(L20),0,IF(ISNUMBER(SEARCH("SQL",L20)),1,0)) -> 0 | AO20: =IF(ISBLANK(L20),0,IF(ISNUMBER(SEARCH("Airflow",L20)),1,0)) -> 1 | AP20: =IF(ISBLANK(L20),0,IF(ISNUMBER(SEARCH("Kafka",L20)),1,0)) -> 0 | AQ20: =IF(ISBLANK(L20),0,IF(ISNUMBER(SEARCH("ML",L20)),1,0)) -> 0 | AR20: =IF(ISBLANK(L21),0,IF(ISNUMBER(SEARCH("ML",L21)),1,0)) -> 0 | AS20: =IF(ISBLANK(L22),0,IF(ISNUMBER(SEARCH("Docker",L22)),1,0)) -> 0 | AT20: =IF(ISBLANK(L22),0,IF(ISNUMBER(SEARCH("dbt",L22)),1,0)) -> 0 | AU20: =IF(ISBLANK(L22),0,IF(ISNUMBER(SEARCH("AWS",L22)),1,0)) -> 0 | AV20: =IF(ISBLANK(L22),0,IF(ISNUMBER(SEARCH("GCP",L22)),1,0)) -> 0 | AW20: =IF(ISBLANK(L22),0,IF(ISNUMBER(SEARCH("Azure",L22)),1,0)) -> 0 | AX20: =IF(ISBLANK(M22),0,IF(ISNUMBER(SEARCH("Tableau",L22)),1,0)) -> 0 | AY20: =IF(ISBLANK(N22),0,IF(ISNUMBER(SEARCH("PowerBI",L22)),1,0)) -> 0 | AZ20: Fulltime
A21: 20 | B21: 46178 | C21: LinkedIn | D21: Data Engineer | E21: Bachatt | F21: Gurgaon | G21: 2 | H21: 4 | I21: ND | J21: ND | K21: SQL , PySpark , Java(or another similar language), Airflow | L21: AWS/GCP | M21: On-site | N21: Startup | O21: =IF(ISBLANK(K21),0,IF(ISNUMBER(SEARCH("sql",K21)),1,0)) -> 1 | P21: =IF(ISBLANK(K21),0,IF(ISNUMBER(SEARCH("Python",K21)),1,0)) -> 0 | Q21: =IF(ISBLANK(K21),0,IF(ISNUMBER(SEARCH("PowerBI",K21)),1,0)) -> 0 | R21: =IF(ISBLANK(K21),0,IF(ISNUMBER(SEARCH("Tableau",K21)),1,0)) -> 0 | S21: =IF(ISBLANK(K21),0,IF(ISNUMBER(SEARCH("Excel",K21)),1,0)) -> 0 | T21: =IF(ISBLANK(K21),0,IF(ISNUMBER(SEARCH("Statistics",K21)),1,0)) -> 0 | U21: =IF(ISBLANK(K21),0,IF(ISNUMBER(SEARCH("AWS",K21)),1,0)) -> 0 | V21: =IF(ISBLANK(K21),0,IF(ISNUMBER(SEARCH("GCP",K21)),1,0)) -> 0 | W21: =IF(ISBLANK(K21),0,IF(ISNUMBER(SEARCH("NoSQL",K21)),1,0)) -> 0 | X21: =IF(ISBLANK(K21),0,IF(ISNUMBER(SEARCH("Data Modeling",K21)),1,0)) -> 0 | Y21: =IF(ISBLANK(K21),0,IF(ISNUMBER(SEARCH("Pandas",K21)),1,0)) -> 0 | Z21: =IF(ISBLANK(K21),0,IF(ISNUMBER(SEARCH("Numpy",K21)),1,0)) -> 0 | AA21: =IF(ISBLANK(K21),0,IF(ISNUMBER(SEARCH("Pyspark",K21)),1,0)) -> 1 | AB21: =IF(ISBLANK(K21),0,IF(ISNUMBER(SEARCH("Hadoop",K21)),1,0)) -> 0 | AC21: =IF(ISBLANK(K21),0,IF(ISNUMBER(SEARCH("ETL",K21)),1,0)) -> 0 | AD21: =IF(ISBLANK(K21),0,IF(ISNUMBER(SEARCH("Azure",K21)),1,0)) -> 0 | AE21: =IF(ISBLANK(K21),0,IF(ISNUMBER(SEARCH("Databricks",K21)),1,0)) -> 0 | AF21: =IF(ISBLANK(K21),0,IF(ISNUMBER(SEARCH("A/B Testing",K21)),1,0)) -> 0 | AG21: =IF(ISBLANK(K21),0,IF(ISNUMBER(SEARCH("Snowflake",K21)),1,0)) -> 0 | AH21: =IF(ISBLANK(K21),0,IF(ISNUMBER(SEARCH("Agile",K21)),1,0)) -> 0 | AI21: =IF(ISBLANK(K21),0,IF(ISNUMBER(SEARCH("Jira",K21)),1,0)) -> 0 | AJ21: =IF(ISBLANK(K21),0,IF(ISNUMBER(SEARCH("Git",K21)),1,0)) -> 0 | AK21: =IF(ISBLANK(K21),0,IF(ISNUMBER(SEARCH("Reporting",K21)),1,0)) -> 0 | AL21: =IF(ISBLANK(K21),0,IF(ISNUMBER(SEARCH("CI/CD",K21)),1,0)) -> 0 | AM21: =IF(ISBLANK(L21),0,IF(ISNUMBER(SEARCH("Python",L21)),1,0)) -> 0 | AN21: =IF(ISBLANK(L21),0,IF(ISNUMBER(SEARCH("SQL",L21)),1,0)) -> 0 | AO21: =IF(ISBLANK(L21),0,IF(ISNUMBER(SEARCH("Airflow",L21)),1,0)) -> 0 | AP21: =IF(ISBLANK(L21),0,IF(ISNUMBER(SEARCH("Kafka",L21)),1,0)) -> 0 | AQ21: =IF(ISBLANK(L21),0,IF(ISNUMBER(SEARCH("ML",L21)),1,0)) -> 0 | AR21: =IF(ISBLANK(L22),0,IF(ISNUMBER(SEARCH("ML",L22)),1,0)) -> 0 | AS21: =IF(ISBLANK(L23),0,IF(ISNUMBER(SEARCH("Docker",L23)),1,0)) -> 0 | AT21: =IF(ISBLANK(L23),0,IF(ISNUMBER(SEARCH("dbt",L23)),1,0)) -> 0 | AU21: =IF(ISBLANK(L23),0,IF(ISNUMBER(SEARCH("AWS",L23)),1,0)) -> 0 | AV21: =IF(ISBLANK(L23),0,IF(ISNUMBER(SEARCH("GCP",L23)),1,0)) -> 0 | AW21: =IF(ISBLANK(L23),0,IF(ISNUMBER(SEARCH("Azure",L23)),1,0)) -> 0 | AX21: =IF(ISBLANK(M23),0,IF(ISNUMBER(SEARCH("Tableau",L23)),1,0)) -> 0 | AY21: =IF(ISBLANK(N23),0,IF(ISNUMBER(SEARCH("PowerBI",L23)),1,0)) -> 0 | AZ21: Fulltime
A22: 21 | B22: 46178 | C22: LinkedIn | D22: Data Engineer | E22: TCS | F22: Pune | G22: 6 | H22: 10 | I22: ND | J22: ND | K22: AWS, Python , SQL, Databricks, Automation | L22: None | M22: On-site | N22: Large | O22: =IF(ISBLANK(K22),0,IF(ISNUMBER(SEARCH("sql",K22)),1,0)) -> 1 | P22: =IF(ISBLANK(K22),0,IF(ISNUMBER(SEARCH("Python",K22)),1,0)) -> 1 | Q22: =IF(ISBLANK(K22),0,IF(ISNUMBER(SEARCH("PowerBI",K22)),1,0)) -> 0 | R22: =IF(ISBLANK(K22),0,IF(ISNUMBER(SEARCH("Tableau",K22)),1,0)) -> 0 | S22: =IF(ISBLANK(K22),0,IF(ISNUMBER(SEARCH("Excel",K22)),1,0)) -> 0 | T22: =IF(ISBLANK(K22),0,IF(ISNUMBER(SEARCH("Statistics",K22)),1,0)) -> 0 | U22: =IF(ISBLANK(K22),0,IF(ISNUMBER(SEARCH("AWS",K22)),1,0)) -> 1 | V22: =IF(ISBLANK(K22),0,IF(ISNUMBER(SEARCH("GCP",K22)),1,0)) -> 0 | W22: =IF(ISBLANK(K22),0,IF(ISNUMBER(SEARCH("NoSQL",K22)),1,0)) -> 0 | X22: =IF(ISBLANK(K22),0,IF(ISNUMBER(SEARCH("Data Modeling",K22)),1,0)) -> 0 | Y22: =IF(ISBLANK(K22),0,IF(ISNUMBER(SEARCH("Pandas",K22)),1,0)) -> 0 | Z22: =IF(ISBLANK(K22),0,IF(ISNUMBER(SEARCH("Numpy",K22)),1,0)) -> 0 | AA22: =IF(ISBLANK(K22),0,IF(ISNUMBER(SEARCH("Pyspark",K22)),1,0)) -> 0 | AB22: =IF(ISBLANK(K22),0,IF(ISNUMBER(SEARCH("Hadoop",K22)),1,0)) -> 0 | AC22: =IF(ISBLANK(K22),0,IF(ISNUMBER(SEARCH("ETL",K22)),1,0)) -> 0 | AD22: =IF(ISBLANK(K22),0,IF(ISNUMBER(SEARCH("Azure",K22)),1,0)) -> 0 | AE22: =IF(ISBLANK(K22),0,IF(ISNUMBER(SEARCH("Databricks",K22)),1,0)) -> 1 | AF22: =IF(ISBLANK(K22),0,IF(ISNUMBER(SEARCH("A/B Testing",K22)),1,0)) -> 0 | AG22: =IF(ISBLANK(K22),0,IF(ISNUMBER(SEARCH("Snowflake",K22)),1,0)) -> 0 | AH22: =IF(ISBLANK(K22),0,IF(ISNUMBER(SEARCH("Agile",K22)),1,0)) -> 0 | AI22: =IF(ISBLANK(K22),0,IF(ISNUMBER(SEARCH("Jira",K22)),1,0)) -> 0 | AJ22: =IF(ISBLANK(K22),0,IF(ISNUMBER(SEARCH("Git",K22)),1,0)) -> 0 | AK22: =IF(ISBLANK(K22),0,IF(ISNUMBER(SEARCH("Reporting",K22)),1,0)) -> 0 | AL22: =IF(ISBLANK(K22),0,IF(ISNUMBER(SEARCH("CI/CD",K22)),1,0)) -> 0 | AM22: =IF(ISBLANK(L22),0,IF(ISNUMBER(SEARCH("Python",L22)),1,0)) -> 0 | AN22: =IF(ISBLANK(L22),0,IF(ISNUMBER(SEARCH("SQL",L22)),1,0)) -> 0 | AO22: =IF(ISBLANK(L22),0,IF(ISNUMBER(SEARCH("Airflow",L22)),1,0)) -> 0 | AP22: =IF(ISBLANK(L22),0,IF(ISNUMBER(SEARCH("Kafka",L22)),1,0)) -> 0 | AQ22: =IF(ISBLANK(L22),0,IF(ISNUMBER(SEARCH("ML",L22)),1,0)) -> 0 | AR22: =IF(ISBLANK(L23),0,IF(ISNUMBER(SEARCH("ML",L23)),1,0)) -> 0 | AS22: =IF(ISBLANK(L24),0,IF(ISNUMBER(SEARCH("Docker",L24)),1,0)) -> 0 | AT22: =IF(ISBLANK(L24),0,IF(ISNUMBER(SEARCH("dbt",L24)),1,0)) -> 0 | AU22: =IF(ISBLANK(L24),0,IF(ISNUMBER(SEARCH("AWS",L24)),1,0)) -> 0 | AV22: =IF(ISBLANK(L24),0,IF(ISNUMBER(SEARCH("GCP",L24)),1,0)) -> 0 | AW22: =IF(ISBLANK(L24),0,IF(ISNUMBER(SEARCH("Azure",L24)),1,0)) -> 0 | AX22: =IF(ISBLANK(M24),0,IF(ISNUMBER(SEARCH("Tableau",L24)),1,0)) -> 0 | AY22: =IF(ISBLANK(N24),0,IF(ISNUMBER(SEARCH("PowerBI",L24)),1,0)) -> 0 | AZ22: Fulltime
A23: 22 | B23: 46178 | C23: LinkedIn | D23: Data Engineer | E23: Accenture | F23: Gurgaon | G23: 3 | H23: ND | I23: ND | J23: ND | K23: PySpark | L23: None | M23: On-site | N23: Large | O23: =IF(ISBLANK(K23),0,IF(ISNUMBER(SEARCH("sql",K23)),1,0)) -> 0 | P23: =IF(ISBLANK(K23),0,IF(ISNUMBER(SEARCH("Python",K23)),1,0)) -> 0 | Q23: =IF(ISBLANK(K23),0,IF(ISNUMBER(SEARCH("PowerBI",K23)),1,0)) -> 0 | R23: =IF(ISBLANK(K23),0,IF(ISNUMBER(SEARCH("Tableau",K23)),1,0)) -> 0 | S23: =IF(ISBLANK(K23),0,IF(ISNUMBER(SEARCH("Excel",K23)),1,0)) -> 0 | T23: =IF(ISBLANK(K23),0,IF(ISNUMBER(SEARCH("Statistics",K23)),1,0)) -> 0 | U23: =IF(ISBLANK(K23),0,IF(ISNUMBER(SEARCH("AWS",K23)),1,0)) -> 0 | V23: =IF(ISBLANK(K23),0,IF(ISNUMBER(SEARCH("GCP",K23)),1,0)) -> 0 | W23: =IF(ISBLANK(K23),0,IF(ISNUMBER(SEARCH("NoSQL",K23)),1,0)) -> 0 | X23: =IF(ISBLANK(K23),0,IF(ISNUMBER(SEARCH("Data Modeling",K23)),1,0)) -> 0 | Y23: =IF(ISBLANK(K23),0,IF(ISNUMBER(SEARCH("Pandas",K23)),1,0)) -> 0 | Z23: =IF(ISBLANK(K23),0,IF(ISNUMBER(SEARCH("Numpy",K23)),1,0)) -> 0 | AA23: =IF(ISBLANK(K23),0,IF(ISNUMBER(SEARCH("Pyspark",K23)),1,0)) -> 1 | AB23: =IF(ISBLANK(K23),0,IF(ISNUMBER(SEARCH("Hadoop",K23)),1,0)) -> 0 | AC23: =IF(ISBLANK(K23),0,IF(ISNUMBER(SEARCH("ETL",K23)),1,0)) -> 0 | AD23: =IF(ISBLANK(K23),0,IF(ISNUMBER(SEARCH("Azure",K23)),1,0)) -> 0 | AE23: =IF(ISBLANK(K23),0,IF(ISNUMBER(SEARCH("Databricks",K23)),1,0)) -> 0 | AF23: =IF(ISBLANK(K23),0,IF(ISNUMBER(SEARCH("A/B Testing",K23)),1,0)) -> 0 | AG23: =IF(ISBLANK(K23),0,IF(ISNUMBER(SEARCH("Snowflake",K23)),1,0)) -> 0 | AH23: =IF(ISBLANK(K23),0,IF(ISNUMBER(SEARCH("Agile",K23)),1,0)) -> 0 | AI23: =IF(ISBLANK(K23),0,IF(ISNUMBER(SEARCH("Jira",K23)),1,0)) -> 0 | AJ23: =IF(ISBLANK(K23),0,IF(ISNUMBER(SEARCH("Git",K23)),1,0)) -> 0 | AK23: =IF(ISBLANK(K23),0,IF(ISNUMBER(SEARCH("Reporting",K23)),1,0)) -> 0 | AL23: =IF(ISBLANK(K23),0,IF(ISNUMBER(SEARCH("CI/CD",K23)),1,0)) -> 0 | AM23: =IF(ISBLANK(L23),0,IF(ISNUMBER(SEARCH("Python",L23)),1,0)) -> 0 | AN23: =IF(ISBLANK(L23),0,IF(ISNUMBER(SEARCH("SQL",L23)),1,0)) -> 0 | AO23: =IF(ISBLANK(L23),0,IF(ISNUMBER(SEARCH("Airflow",L23)),1,0)) -> 0 | AP23: =IF(ISBLANK(L23),0,IF(ISNUMBER(SEARCH("Kafka",L23)),1,0)) -> 0 | AQ23: =IF(ISBLANK(L23),0,IF(ISNUMBER(SEARCH("ML",L23)),1,0)) -> 0 | AR23: =IF(ISBLANK(L24),0,IF(ISNUMBER(SEARCH("ML",L24)),1,0)) -> 0 | AS23: =IF(ISBLANK(L25),0,IF(ISNUMBER(SEARCH("Docker",L25)),1,0)) -> 0 | AT23: =IF(ISBLANK(L25),0,IF(ISNUMBER(SEARCH("dbt",L25)),1,0)) -> 0 | AU23: =IF(ISBLANK(L25),0,IF(ISNUMBER(SEARCH("AWS",L25)),1,0)) -> 0 | AV23: =IF(ISBLANK(L25),0,IF(ISNUMBER(SEARCH("GCP",L25)),1,0)) -> 0 | AW23: =IF(ISBLANK(L25),0,IF(ISNUMBER(SEARCH("Azure",L25)),1,0)) -> 0 | AX23: =IF(ISBLANK(M25),0,IF(ISNUMBER(SEARCH("Tableau",L25)),1,0)) -> 0 | AY23: =IF(ISBLANK(N25),0,IF(ISNUMBER(SEARCH("PowerBI",L25)),1,0)) -> 0 | AZ23: Fulltime
A24: 23 | B24: 46178 | C24: LinkedIn | D24: Data Engineer | E24: Accolite | F24: Gurgaon | G24: 3 | H24: ND | I24: ND | J24: ND | K24: SQL , PySpark , Kafka , Hadoop, Python , Scala or Java, Cloud data services | L24: None | M24: On-site | N24: Medium | O24: =IF(ISBLANK(K24),0,IF(ISNUMBER(SEARCH("sql",K24)),1,0)) -> 1 | P24: =IF(ISBLANK(K24),0,IF(ISNUMBER(SEARCH("Python",K24)),1,0)) -> 1 | Q24: =IF(ISBLANK(K24),0,IF(ISNUMBER(SEARCH("PowerBI",K24)),1,0)) -> 0 | R24: =IF(ISBLANK(K24),0,IF(ISNUMBER(SEARCH("Tableau",K24)),1,0)) -> 0 | S24: =IF(ISBLANK(K24),0,IF(ISNUMBER(SEARCH("Excel",K24)),1,0)) -> 0 | T24: =IF(ISBLANK(K24),0,IF(ISNUMBER(SEARCH("Statistics",K24)),1,0)) -> 0 | U24: =IF(ISBLANK(K24),0,IF(ISNUMBER(SEARCH("AWS",K24)),1,0)) -> 0 | V24: =IF(ISBLANK(K24),0,IF(ISNUMBER(SEARCH("GCP",K24)),1,0)) -> 0 | W24: =IF(ISBLANK(K24),0,IF(ISNUMBER(SEARCH("NoSQL",K24)),1,0)) -> 0 | X24: =IF(ISBLANK(K24),0,IF(ISNUMBER(SEARCH("Data Modeling",K24)),1,0)) -> 0 | Y24: =IF(ISBLANK(K24),0,IF(ISNUMBER(SEARCH("Pandas",K24)),1,0)) -> 0 | Z24: =IF(ISBLANK(K24),0,IF(ISNUMBER(SEARCH("Numpy",K24)),1,0)) -> 0 | AA24: =IF(ISBLANK(K24),0,IF(ISNUMBER(SEARCH("Pyspark",K24)),1,0)) -> 1 | AB24: =IF(ISBLANK(K24),0,IF(ISNUMBER(SEARCH("Hadoop",K24)),1,0)) -> 1 | AC24: =IF(ISBLANK(K24),0,IF(ISNUMBER(SEARCH("ETL",K24)),1,0)) -> 0 | AD24: =IF(ISBLANK(K24),0,IF(ISNUMBER(SEARCH("Azure",K24)),1,0)) -> 0 | AE24: =IF(ISBLANK(K24),0,IF(ISNUMBER(SEARCH("Databricks",K24)),1,0)) -> 0 | AF24: =IF(ISBLANK(K24),0,IF(ISNUMBER(SEARCH("A/B Testing",K24)),1,0)) -> 0 | AG24: =IF(ISBLANK(K24),0,IF(ISNUMBER(SEARCH("Snowflake",K24)),1,0)) -> 0 | AH24: =IF(ISBLANK(K24),0,IF(ISNUMBER(SEARCH("Agile",K24)),1,0)) -> 0 | AI24: =IF(ISBLANK(K24),0,IF(ISNUMBER(SEARCH("Jira",K24)),1,0)) -> 0 | AJ24: =IF(ISBLANK(K24),0,IF(ISNUMBER(SEARCH("Git",K24)),1,0)) -> 0 | AK24: =IF(ISBLANK(K24),0,IF(ISNUMBER(SEARCH("Reporting",K24)),1,0)) -> 0 | AL24: =IF(ISBLANK(K24),0,IF(ISNUMBER(SEARCH("CI/CD",K24)),1,0)) -> 0 | AM24: =IF(ISBLANK(L24),0,IF(ISNUMBER(SEARCH("Python",L24)),1,0)) -> 0 | AN24: =IF(ISBLANK(L24),0,IF(ISNUMBER(SEARCH("SQL",L24)),1,0)) -> 0 | AO24: =IF(ISBLANK(L24),0,IF(ISNUMBER(SEARCH("Airflow",L24)),1,0)) -> 0 | AP24: =IF(ISBLANK(L24),0,IF(ISNUMBER(SEARCH("Kafka",L24)),1,0)) -> 0 | AQ24: =IF(ISBLANK(L24),0,IF(ISNUMBER(SEARCH("ML",L24)),1,0)) -> 0 | AR24: =IF(ISBLANK(L25),0,IF(ISNUMBER(SEARCH("ML",L25)),1,0)) -> 0 | AS24: =IF(ISBLANK(L26),0,IF(ISNUMBER(SEARCH("Docker",L26)),1,0)) -> 0 | AT24: =IF(ISBLANK(L26),0,IF(ISNUMBER(SEARCH("dbt",L26)),1,0)) -> 0 | AU24: =IF(ISBLANK(L26),0,IF(ISNUMBER(SEARCH("AWS",L26)),1,0)) -> 0 | AV24: =IF(ISBLANK(L26),0,IF(ISNUMBER(SEARCH("GCP",L26)),1,0)) -> 0 | AW24: =IF(ISBLANK(L26),0,IF(ISNUMBER(SEARCH("Azure",L26)),1,0)) -> 0 | AX24: =IF(ISBLANK(M26),0,IF(ISNUMBER(SEARCH("Tableau",L26)),1,0)) -> 0 | AY24: =IF(ISBLANK(N26),0,IF(ISNUMBER(SEARCH("PowerBI",L26)),1,0)) -> 0 | AZ24: Fulltime
A25: 24 | B25: 46178 | C25: LinkedIn | D25: Data Engineer | E25: Barclays | F25: Pune | G25: ND | H25: ND | I25: ND | J25: ND | K25: Pyspark,AWS Data Analytics Stack, AWS Cloud, Snowflake,dbt | L25: Airflow/Snowflake tasks, Abinitio ETL | M25: On-site | N25: Large | O25: =IF(ISBLANK(K25),0,IF(ISNUMBER(SEARCH("sql",K25)),1,0)) -> 0 | P25: =IF(ISBLANK(K25),0,IF(ISNUMBER(SEARCH("Python",K25)),1,0)) -> 0 | Q25: =IF(ISBLANK(K25),0,IF(ISNUMBER(SEARCH("PowerBI",K25)),1,0)) -> 0 | R25: =IF(ISBLANK(K25),0,IF(ISNUMBER(SEARCH("Tableau",K25)),1,0)) -> 0 | S25: =IF(ISBLANK(K25),0,IF(ISNUMBER(SEARCH("Excel",K25)),1,0)) -> 0 | T25: =IF(ISBLANK(K25),0,IF(ISNUMBER(SEARCH("Statistics",K25)),1,0)) -> 0 | U25: =IF(ISBLANK(K25),0,IF(ISNUMBER(SEARCH("AWS",K25)),1,0)) -> 1 | V25: =IF(ISBLANK(K25),0,IF(ISNUMBER(SEARCH("GCP",K25)),1,0)) -> 0 | W25: =IF(ISBLANK(K25),0,IF(ISNUMBER(SEARCH("NoSQL",K25)),1,0)) -> 0 | X25: =IF(ISBLANK(K25),0,IF(ISNUMBER(SEARCH("Data Modeling",K25)),1,0)) -> 0 | Y25: =IF(ISBLANK(K25),0,IF(ISNUMBER(SEARCH("Pandas",K25)),1,0)) -> 0 | Z25: =IF(ISBLANK(K25),0,IF(ISNUMBER(SEARCH("Numpy",K25)),1,0)) -> 0 | AA25: =IF(ISBLANK(K25),0,IF(ISNUMBER(SEARCH("Pyspark",K25)),1,0)) -> 1 | AB25: =IF(ISBLANK(K25),0,IF(ISNUMBER(SEARCH("Hadoop",K25)),1,0)) -> 0 | AC25: =IF(ISBLANK(K25),0,IF(ISNUMBER(SEARCH("ETL",K25)),1,0)) -> 0 | AD25: =IF(ISBLANK(K25),0,IF(ISNUMBER(SEARCH("Azure",K25)),1,0)) -> 0 | AE25: =IF(ISBLANK(K25),0,IF(ISNUMBER(SEARCH("Databricks",K25)),1,0)) -> 0 | AF25: =IF(ISBLANK(K25),0,IF(ISNUMBER(SEARCH("A/B Testing",K25)),1,0)) -> 0 | AG25: =IF(ISBLANK(K25),0,IF(ISNUMBER(SEARCH("Snowflake",K25)),1,0)) -> 1 | AH25: =IF(ISBLANK(K25),0,IF(ISNUMBER(SEARCH("Agile",K25)),1,0)) -> 0 | AI25: =IF(ISBLANK(K25),0,IF(ISNUMBER(SEARCH("Jira",K25)),1,0)) -> 0 | AJ25: =IF(ISBLANK(K25),0,IF(ISNUMBER(SEARCH("Git",K25)),1,0)) -> 0 | AK25: =IF(ISBLANK(K25),0,IF(ISNUMBER(SEARCH("Reporting",K25)),1,0)) -> 0 | AL25: =IF(ISBLANK(K25),0,IF(ISNUMBER(SEARCH("CI/CD",K25)),1,0)) -> 0 | AM25: =IF(ISBLANK(L25),0,IF(ISNUMBER(SEARCH("Python",L25)),1,0)) -> 0 | AN25: =IF(ISBLANK(L25),0,IF(ISNUMBER(SEARCH("SQL",L25)),1,0)) -> 0 | AO25: =IF(ISBLANK(L25),0,IF(ISNUMBER(SEARCH("Airflow",L25)),1,0)) -> 1 | AP25: =IF(ISBLANK(L25),0,IF(ISNUMBER(SEARCH("Kafka",L25)),1,0)) -> 0 | AQ25: =IF(ISBLANK(L25),0,IF(ISNUMBER(SEARCH("ML",L25)),1,0)) -> 0 | AR25: =IF(ISBLANK(L26),0,IF(ISNUMBER(SEARCH("ML",L26)),1,0)) -> 1 | AS25: =IF(ISBLANK(L27),0,IF(ISNUMBER(SEARCH("Docker",L27)),1,0)) -> 0 | AT25: =IF(ISBLANK(L27),0,IF(ISNUMBER(SEARCH("dbt",L27)),1,0)) -> 0 | AU25: =IF(ISBLANK(L27),0,IF(ISNUMBER(SEARCH("AWS",L27)),1,0)) -> 0 | AV25: =IF(ISBLANK(L27),0,IF(ISNUMBER(SEARCH("GCP",L27)),1,0)) -> 0 | AW25: =IF(ISBLANK(L27),0,IF(ISNUMBER(SEARCH("Azure",L27)),1,0)) -> 0 | AX25: =IF(ISBLANK(M27),0,IF(ISNUMBER(SEARCH("Tableau",L27)),1,0)) -> 0 | AY25: =IF(ISBLANK(N27),0,IF(ISNUMBER(SEARCH("PowerBI",L27)),1,0)) -> 0 | AZ25: Fulltime
A26: 25 | B26: 46178 | C26: LinkedIn | D26: Data Engineer | E26: Aeris | F26: Gurgaon | G26: 4 | H26: ND | I26: ND | J26: ND | K26: Python ETL , SQL , GCP. RestAPI, Git & CI/CD,Data lake design | L26: Orchestration, ML, AI agent development, BI Tools | M26: On-site | N26: Large | O26: =IF(ISBLANK(K26),0,IF(ISNUMBER(SEARCH("sql",K26)),1,0)) -> 1 | P26: =IF(ISBLANK(K26),0,IF(ISNUMBER(SEARCH("Python",K26)),1,0)) -> 1 | Q26: =IF(ISBLANK(K26),0,IF(ISNUMBER(SEARCH("PowerBI",K26)),1,0)) -> 0 | R26: =IF(ISBLANK(K26),0,IF(ISNUMBER(SEARCH("Tableau",K26)),1,0)) -> 0 | S26: =IF(ISBLANK(K26),0,IF(ISNUMBER(SEARCH("Excel",K26)),1,0)) -> 0 | T26: =IF(ISBLANK(K26),0,IF(ISNUMBER(SEARCH("Statistics",K26)),1,0)) -> 0 | U26: =IF(ISBLANK(K26),0,IF(ISNUMBER(SEARCH("AWS",K26)),1,0)) -> 0 | V26: =IF(ISBLANK(K26),0,IF(ISNUMBER(SEARCH("GCP",K26)),1,0)) -> 1 | W26: =IF(ISBLANK(K26),0,IF(ISNUMBER(SEARCH("NoSQL",K26)),1,0)) -> 0 | X26: =IF(ISBLANK(K26),0,IF(ISNUMBER(SEARCH("Data Modeling",K26)),1,0)) -> 0 | Y26: =IF(ISBLANK(K26),0,IF(ISNUMBER(SEARCH("Pandas",K26)),1,0)) -> 0 | Z26: =IF(ISBLANK(K26),0,IF(ISNUMBER(SEARCH("Numpy",K26)),1,0)) -> 0 | AA26: =IF(ISBLANK(K26),0,IF(ISNUMBER(SEARCH("Pyspark",K26)),1,0)) -> 0 | AB26: =IF(ISBLANK(K26),0,IF(ISNUMBER(SEARCH("Hadoop",K26)),1,0)) -> 0 | AC26: =IF(ISBLANK(K26),0,IF(ISNUMBER(SEARCH("ETL",K26)),1,0)) -> 1 | AD26: =IF(ISBLANK(K26),0,IF(ISNUMBER(SEARCH("Azure",K26)),1,0)) -> 0 | AE26: =IF(ISBLANK(K26),0,IF(ISNUMBER(SEARCH("Databricks",K26)),1,0)) -> 0 | AF26: =IF(ISBLANK(K26),0,IF(ISNUMBER(SEARCH("A/B Testing",K26)),1,0)) -> 0 | AG26: =IF(ISBLANK(K26),0,IF(ISNUMBER(SEARCH("Snowflake",K26)),1,0)) -> 0 | AH26: =IF(ISBLANK(K26),0,IF(ISNUMBER(SEARCH("Agile",K26)),1,0)) -> 0 | AI26: =IF(ISBLANK(K26),0,IF(ISNUMBER(SEARCH("Jira",K26)),1,0)) -> 0 | AJ26: =IF(ISBLANK(K26),0,IF(ISNUMBER(SEARCH("Git",K26)),1,0)) -> 1 | AK26: =IF(ISBLANK(K26),0,IF(ISNUMBER(SEARCH("Reporting",K26)),1,0)) -> 0 | AL26: =IF(ISBLANK(K26),0,IF(ISNUMBER(SEARCH("CI/CD",K26)),1,0)) -> 1 | AM26: =IF(ISBLANK(L26),0,IF(ISNUMBER(SEARCH("Python",L26)),1,0)) -> 0 | AN26: =IF(ISBLANK(L26),0,IF(ISNUMBER(SEARCH("SQL",L26)),1,0)) -> 0 | AO26: =IF(ISBLANK(L26),0,IF(ISNUMBER(SEARCH("Airflow",L26)),1,0)) -> 0 | AP26: =IF(ISBLANK(L26),0,IF(ISNUMBER(SEARCH("Kafka",L26)),1,0)) -> 0 | AQ26: =IF(ISBLANK(L26),0,IF(ISNUMBER(SEARCH("ML",L26)),1,0)) -> 1 | AR26: =IF(ISBLANK(L27),0,IF(ISNUMBER(SEARCH("ML",L27)),1,0)) -> 0 | AS26: =IF(ISBLANK(L28),0,IF(ISNUMBER(SEARCH("Docker",L28)),1,0)) -> 0 | AT26: =IF(ISBLANK(L28),0,IF(ISNUMBER(SEARCH("dbt",L28)),1,0)) -> 0 | AU26: =IF(ISBLANK(L28),0,IF(ISNUMBER(SEARCH("AWS",L28)),1,0)) -> 0 | AV26: =IF(ISBLANK(L28),0,IF(ISNUMBER(SEARCH("GCP",L28)),1,0)) -> 0 | AW26: =IF(ISBLANK(L28),0,IF(ISNUMBER(SEARCH("Azure",L28)),1,0)) -> 0 | AX26: =IF(ISBLANK(M28),0,IF(ISNUMBER(SEARCH("Tableau",L28)),1,0)) -> 0 | AY26: =IF(ISBLANK(N28),0,IF(ISNUMBER(SEARCH("PowerBI",L28)),1,0)) -> 0 | AZ26: Fulltime
A27: 26 | B27: 46178 | C27: LinkedIn | D27: Data Engineer | E27: DHL | F27: Chennai | G27: 3 | H27: ND | I27: ND | J27: ND | K27: Kubeflow, Python, Snowflake, Github. CI/CD, PowerBI, Microsoft 365 Tools | L27: None | M27: On-site | N27: Large | O27: =IF(ISBLANK(K27),0,IF(ISNUMBER(SEARCH("sql",K27)),1,0)) -> 0 | P27: =IF(ISBLANK(K27),0,IF(ISNUMBER(SEARCH("Python",K27)),1,0)) -> 1 | Q27: =IF(ISBLANK(K27),0,IF(ISNUMBER(SEARCH("PowerBI",K27)),1,0)) -> 1 | R27: =IF(ISBLANK(K27),0,IF(ISNUMBER(SEARCH("Tableau",K27)),1,0)) -> 0 | S27: =IF(ISBLANK(K27),0,IF(ISNUMBER(SEARCH("Excel",K27)),1,0)) -> 0 | T27: =IF(ISBLANK(K27),0,IF(ISNUMBER(SEARCH("Statistics",K27)),1,0)) -> 0 | U27: =IF(ISBLANK(K27),0,IF(ISNUMBER(SEARCH("AWS",K27)),1,0)) -> 0 | V27: =IF(ISBLANK(K27),0,IF(ISNUMBER(SEARCH("GCP",K27)),1,0)) -> 0 | W27: =IF(ISBLANK(K27),0,IF(ISNUMBER(SEARCH("NoSQL",K27)),1,0)) -> 0 | X27: =IF(ISBLANK(K27),0,IF(ISNUMBER(SEARCH("Data Modeling",K27)),1,0)) -> 0 | Y27: =IF(ISBLANK(K27),0,IF(ISNUMBER(SEARCH("Pandas",K27)),1,0)) -> 0 | Z27: =IF(ISBLANK(K27),0,IF(ISNUMBER(SEARCH("Numpy",K27)),1,0)) -> 0 | AA27: =IF(ISBLANK(K27),0,IF(ISNUMBER(SEARCH("Pyspark",K27)),1,0)) -> 0 | AB27: =IF(ISBLANK(K27),0,IF(ISNUMBER(SEARCH("Hadoop",K27)),1,0)) -> 0 | AC27: =IF(ISBLANK(K27),0,IF(ISNUMBER(SEARCH("ETL",K27)),1,0)) -> 0 | AD27: =IF(ISBLANK(K27),0,IF(ISNUMBER(SEARCH("Azure",K27)),1,0)) -> 0 | AE27: =IF(ISBLANK(K27),0,IF(ISNUMBER(SEARCH("Databricks",K27)),1,0)) -> 0 | AF27: =IF(ISBLANK(K27),0,IF(ISNUMBER(SEARCH("A/B Testing",K27)),1,0)) -> 0 | AG27: =IF(ISBLANK(K27),0,IF(ISNUMBER(SEARCH("Snowflake",K27)),1,0)) -> 1 | AH27: =IF(ISBLANK(K27),0,IF(ISNUMBER(SEARCH("Agile",K27)),1,0)) -> 0 | AI27: =IF(ISBLANK(K27),0,IF(ISNUMBER(SEARCH("Jira",K27)),1,0)) -> 0 | AJ27: =IF(ISBLANK(K27),0,IF(ISNUMBER(SEARCH("Git",K27)),1,0)) -> 1 | AK27: =IF(ISBLANK(K27),0,IF(ISNUMBER(SEARCH("Reporting",K27)),1,0)) -> 0 | AL27: =IF(ISBLANK(K27),0,IF(ISNUMBER(SEARCH("CI/CD",K27)),1,0)) -> 1 | AM27: =IF(ISBLANK(L27),0,IF(ISNUMBER(SEARCH("Python",L27)),1,0)) -> 0 | AN27: =IF(ISBLANK(L27),0,IF(ISNUMBER(SEARCH("SQL",L27)),1,0)) -> 0 | AO27: =IF(ISBLANK(L27),0,IF(ISNUMBER(SEARCH("Airflow",L27)),1,0)) -> 0 | AP27: =IF(ISBLANK(L27),0,IF(ISNUMBER(SEARCH("Kafka",L27)),1,0)) -> 0 | AQ27: =IF(ISBLANK(L27),0,IF(ISNUMBER(SEARCH("ML",L27)),1,0)) -> 0 | AR27: =IF(ISBLANK(L28),0,IF(ISNUMBER(SEARCH("ML",L28)),1,0)) -> 0 | AS27: =IF(ISBLANK(L29),0,IF(ISNUMBER(SEARCH("Docker",L29)),1,0)) -> 0 | AT27: =IF(ISBLANK(L29),0,IF(ISNUMBER(SEARCH("dbt",L29)),1,0)) -> 0 | AU27: =IF(ISBLANK(L29),0,IF(ISNUMBER(SEARCH("AWS",L29)),1,0)) -> 0 | AV27: =IF(ISBLANK(L29),0,IF(ISNUMBER(SEARCH("GCP",L29)),1,0)) -> 0 | AW27: =IF(ISBLANK(L29),0,IF(ISNUMBER(SEARCH("Azure",L29)),1,0)) -> 0 | AX27: =IF(ISBLANK(M29),0,IF(ISNUMBER(SEARCH("Tableau",L29)),1,0)) -> 0 | AY27: =IF(ISBLANK(N29),0,IF(ISNUMBER(SEARCH("PowerBI",L29)),1,0)) -> 0 | AZ27: Fulltime
A28: 27 | B28: 46178 | C28: LinkedIn | D28: Data Engineer | E28: Citi | F28: Chennai | G28: 3 | H28: 7 | I28: ND | J28: ND | K28: Python , PySpark , Databricks, Kafka, Shell Script, SQL | L28: Banking domain knowledge | M28: Hybrid | N28: Large | O28: =IF(ISBLANK(K28),0,IF(ISNUMBER(SEARCH("sql",K28)),1,0)) -> 1 | P28: =IF(ISBLANK(K28),0,IF(ISNUMBER(SEARCH("Python",K28)),1,0)) -> 1 | Q28: =IF(ISBLANK(K28),0,IF(ISNUMBER(SEARCH("PowerBI",K28)),1,0)) -> 0 | R28: =IF(ISBLANK(K28),0,IF(ISNUMBER(SEARCH("Tableau",K28)),1,0)) -> 0 | S28: =IF(ISBLANK(K28),0,IF(ISNUMBER(SEARCH("Excel",K28)),1,0)) -> 0 | T28: =IF(ISBLANK(K28),0,IF(ISNUMBER(SEARCH("Statistics",K28)),1,0)) -> 0 | U28: =IF(ISBLANK(K28),0,IF(ISNUMBER(SEARCH("AWS",K28)),1,0)) -> 0 | V28: =IF(ISBLANK(K28),0,IF(ISNUMBER(SEARCH("GCP",K28)),1,0)) -> 0 | W28: =IF(ISBLANK(K28),0,IF(ISNUMBER(SEARCH("NoSQL",K28)),1,0)) -> 0 | X28: =IF(ISBLANK(K28),0,IF(ISNUMBER(SEARCH("Data Modeling",K28)),1,0)) -> 0 | Y28: =IF(ISBLANK(K28),0,IF(ISNUMBER(SEARCH("Pandas",K28)),1,0)) -> 0 | Z28: =IF(ISBLANK(K28),0,IF(ISNUMBER(SEARCH("Numpy",K28)),1,0)) -> 0 | AA28: =IF(ISBLANK(K28),0,IF(ISNUMBER(SEARCH("Pyspark",K28)),1,0)) -> 1 | AB28: =IF(ISBLANK(K28),0,IF(ISNUMBER(SEARCH("Hadoop",K28)),1,0)) -> 0 | AC28: =IF(ISBLANK(K28),0,IF(ISNUMBER(SEARCH("ETL",K28)),1,0)) -> 0 | AD28: =IF(ISBLANK(K28),0,IF(ISNUMBER(SEARCH("Azure",K28)),1,0)) -> 0 | AE28: =IF(ISBLANK(K28),0,IF(ISNUMBER(SEARCH("Databricks",K28)),1,0)) -> 1 | AF28: =IF(ISBLANK(K28),0,IF(ISNUMBER(SEARCH("A/B Testing",K28)),1,0)) -> 0 | AG28: =IF(ISBLANK(K28),0,IF(ISNUMBER(SEARCH("Snowflake",K28)),1,0)) -> 0 | AH28: =IF(ISBLANK(K28),0,IF(ISNUMBER(SEARCH("Agile",K28)),1,0)) -> 0 | AI28: =IF(ISBLANK(K28),0,IF(ISNUMBER(SEARCH("Jira",K28)),1,0)) -> 0 | AJ28: =IF(ISBLANK(K28),0,IF(ISNUMBER(SEARCH("Git",K28)),1,0)) -> 0 | AK28: =IF(ISBLANK(K28),0,IF(ISNUMBER(SEARCH("Reporting",K28)),1,0)) -> 0 | AL28: =IF(ISBLANK(K28),0,IF(ISNUMBER(SEARCH("CI/CD",K28)),1,0)) -> 0 | AM28: =IF(ISBLANK(L28),0,IF(ISNUMBER(SEARCH("Python",L28)),1,0)) -> 0 | AN28: =IF(ISBLANK(L28),0,IF(ISNUMBER(SEARCH("SQL",L28)),1,0)) -> 0 | AO28: =IF(ISBLANK(L28),0,IF(ISNUMBER(SEARCH("Airflow",L28)),1,0)) -> 0 | AP28: =IF(ISBLANK(L28),0,IF(ISNUMBER(SEARCH("Kafka",L28)),1,0)) -> 0 | AQ28: =IF(ISBLANK(L28),0,IF(ISNUMBER(SEARCH("ML",L28)),1,0)) -> 0 | AR28: =IF(ISBLANK(L29),0,IF(ISNUMBER(SEARCH("ML",L29)),1,0)) -> 0 | AS28: =IF(ISBLANK(L30),0,IF(ISNUMBER(SEARCH("Docker",L30)),1,0)) -> 0 | AT28: =IF(ISBLANK(L30),0,IF(ISNUMBER(SEARCH("dbt",L30)),1,0)) -> 0 | AU28: =IF(ISBLANK(L30),0,IF(ISNUMBER(SEARCH("AWS",L30)),1,0)) -> 0 | AV28: =IF(ISBLANK(L30),0,IF(ISNUMBER(SEARCH("GCP",L30)),1,0)) -> 0 | AW28: =IF(ISBLANK(L30),0,IF(ISNUMBER(SEARCH("Azure",L30)),1,0)) -> 0 | AX28: =IF(ISBLANK(M30),0,IF(ISNUMBER(SEARCH("Tableau",L30)),1,0)) -> 0 | AY28: =IF(ISBLANK(N30),0,IF(ISNUMBER(SEARCH("PowerBI",L30)),1,0)) -> 0 | AZ28: Fulltime
A29: 28 | B29: 46178 | C29: LinkedIn | D29: Data Engineer | E29: Capegemini | F29: Mumbai | G29: ND | H29: ND | I29: ND | J29: ND | K29: AWS data services, Python , PySpark , ETL, Databases, CI/CD , Automation | L29: None | M29: On-site | N29: Large | O29: =IF(ISBLANK(K29),0,IF(ISNUMBER(SEARCH("sql",K29)),1,0)) -> 0 | P29: =IF(ISBLANK(K29),0,IF(ISNUMBER(SEARCH("Python",K29)),1,0)) -> 1 | Q29: =IF(ISBLANK(K29),0,IF(ISNUMBER(SEARCH("PowerBI",K29)),1,0)) -> 0 | R29: =IF(ISBLANK(K29),0,IF(ISNUMBER(SEARCH("Tableau",K29)),1,0)) -> 0 | S29: =IF(ISBLANK(K29),0,IF(ISNUMBER(SEARCH("Excel",K29)),1,0)) -> 0 | T29: =IF(ISBLANK(K29),0,IF(ISNUMBER(SEARCH("Statistics",K29)),1,0)) -> 0 | U29: =IF(ISBLANK(K29),0,IF(ISNUMBER(SEARCH("AWS",K29)),1,0)) -> 1 | V29: =IF(ISBLANK(K29),0,IF(ISNUMBER(SEARCH("GCP",K29)),1,0)) -> 0 | W29: =IF(ISBLANK(K29),0,IF(ISNUMBER(SEARCH("NoSQL",K29)),1,0)) -> 0 | X29: =IF(ISBLANK(K29),0,IF(ISNUMBER(SEARCH("Data Modeling",K29)),1,0)) -> 0 | Y29: =IF(ISBLANK(K29),0,IF(ISNUMBER(SEARCH("Pandas",K29)),1,0)) -> 0 | Z29: =IF(ISBLANK(K29),0,IF(ISNUMBER(SEARCH("Numpy",K29)),1,0)) -> 0 | AA29: =IF(ISBLANK(K29),0,IF(ISNUMBER(SEARCH("Pyspark",K29)),1,0)) -> 1 | AB29: =IF(ISBLANK(K29),0,IF(ISNUMBER(SEARCH("Hadoop",K29)),1,0)) -> 0 | AC29: =IF(ISBLANK(K29),0,IF(ISNUMBER(SEARCH("ETL",K29)),1,0)) -> 1 | AD29: =IF(ISBLANK(K29),0,IF(ISNUMBER(SEARCH("Azure",K29)),1,0)) -> 0 | AE29: =IF(ISBLANK(K29),0,IF(ISNUMBER(SEARCH("Databricks",K29)),1,0)) -> 0 | AF29: =IF(ISBLANK(K29),0,IF(ISNUMBER(SEARCH("A/B Testing",K29)),1,0)) -> 0 | AG29: =IF(ISBLANK(K29),0,IF(ISNUMBER(SEARCH("Snowflake",K29)),1,0)) -> 0 | AH29: =IF(ISBLANK(K29),0,IF(ISNUMBER(SEARCH("Agile",K29)),1,0)) -> 0 | AI29: =IF(ISBLANK(K29),0,IF(ISNUMBER(SEARCH("Jira",K29)),1,0)) -> 0 | AJ29: =IF(ISBLANK(K29),0,IF(ISNUMBER(SEARCH("Git",K29)),1,0)) -> 0 | AK29: =IF(ISBLANK(K29),0,IF(ISNUMBER(SEARCH("Reporting",K29)),1,0)) -> 0 | AL29: =IF(ISBLANK(K29),0,IF(ISNUMBER(SEARCH("CI/CD",K29)),1,0)) -> 1 | AM29: =IF(ISBLANK(L29),0,IF(ISNUMBER(SEARCH("Python",L29)),1,0)) -> 0 | AN29: =IF(ISBLANK(L29),0,IF(ISNUMBER(SEARCH("SQL",L29)),1,0)) -> 0 | AO29: =IF(ISBLANK(L29),0,IF(ISNUMBER(SEARCH("Airflow",L29)),1,0)) -> 0 | AP29: =IF(ISBLANK(L29),0,IF(ISNUMBER(SEARCH("Kafka",L29)),1,0)) -> 0 | AQ29: =IF(ISBLANK(L29),0,IF(ISNUMBER(SEARCH("ML",L29)),1,0)) -> 0 | AR29: =IF(ISBLANK(L30),0,IF(ISNUMBER(SEARCH("ML",L30)),1,0)) -> 0 | AS29: =IF(ISBLANK(L31),0,IF(ISNUMBER(SEARCH("Docker",L31)),1,0)) -> 0 | AT29: =IF(ISBLANK(L31),0,IF(ISNUMBER(SEARCH("dbt",L31)),1,0)) -> 1 | AU29: =IF(ISBLANK(L31),0,IF(ISNUMBER(SEARCH("AWS",L31)),1,0)) -> 0 | AV29: =IF(ISBLANK(L31),0,IF(ISNUMBER(SEARCH("GCP",L31)),1,0)) -> 0 | AW29: =IF(ISBLANK(L31),0,IF(ISNUMBER(SEARCH("Azure",L31)),1,0)) -> 0 | AX29: =IF(ISBLANK(M31),0,IF(ISNUMBER(SEARCH("Tableau",L31)),1,0)) -> 0 | AY29: =IF(ISBLANK(N31),0,IF(ISNUMBER(SEARCH("PowerBI",L31)),1,0)) -> 0 | AZ29: Fulltime
A30: 29 | B30: 46178 | C30: LinkedIn | D30: Data Engineer | E30: Virtusa | F30: Chennai | G30: ND | H30: ND | I30: ND | J30: ND | K30: Data Analytics, Data visualization, Jenkins, GitLab, CI/CD | L30: None | M30: Hybrid | N30: Large | O30: =IF(ISBLANK(K30),0,IF(ISNUMBER(SEARCH("sql",K30)),1,0)) -> 0 | P30: =IF(ISBLANK(K30),0,IF(ISNUMBER(SEARCH("Python",K30)),1,0)) -> 0 | Q30: =IF(ISBLANK(K30),0,IF(ISNUMBER(SEARCH("PowerBI",K30)),1,0)) -> 0 | R30: =IF(ISBLANK(K30),0,IF(ISNUMBER(SEARCH("Tableau",K30)),1,0)) -> 0 | S30: =IF(ISBLANK(K30),0,IF(ISNUMBER(SEARCH("Excel",K30)),1,0)) -> 0 | T30: =IF(ISBLANK(K30),0,IF(ISNUMBER(SEARCH("Statistics",K30)),1,0)) -> 0 | U30: =IF(ISBLANK(K30),0,IF(ISNUMBER(SEARCH("AWS",K30)),1,0)) -> 0 | V30: =IF(ISBLANK(K30),0,IF(ISNUMBER(SEARCH("GCP",K30)),1,0)) -> 0 | W30: =IF(ISBLANK(K30),0,IF(ISNUMBER(SEARCH("NoSQL",K30)),1,0)) -> 0 | X30: =IF(ISBLANK(K30),0,IF(ISNUMBER(SEARCH("Data Modeling",K30)),1,0)) -> 0 | Y30: =IF(ISBLANK(K30),0,IF(ISNUMBER(SEARCH("Pandas",K30)),1,0)) -> 0 | Z30: =IF(ISBLANK(K30),0,IF(ISNUMBER(SEARCH("Numpy",K30)),1,0)) -> 0 | AA30: =IF(ISBLANK(K30),0,IF(ISNUMBER(SEARCH("Pyspark",K30)),1,0)) -> 0 | AB30: =IF(ISBLANK(K30),0,IF(ISNUMBER(SEARCH("Hadoop",K30)),1,0)) -> 0 | AC30: =IF(ISBLANK(K30),0,IF(ISNUMBER(SEARCH("ETL",K30)),1,0)) -> 0 | AD30: =IF(ISBLANK(K30),0,IF(ISNUMBER(SEARCH("Azure",K30)),1,0)) -> 0 | AE30: =IF(ISBLANK(K30),0,IF(ISNUMBER(SEARCH("Databricks",K30)),1,0)) -> 0 | AF30: =IF(ISBLANK(K30),0,IF(ISNUMBER(SEARCH("A/B Testing",K30)),1,0)) -> 0 | AG30: =IF(ISBLANK(K30),0,IF(ISNUMBER(SEARCH("Snowflake",K30)),1,0)) -> 0 | AH30: =IF(ISBLANK(K30),0,IF(ISNUMBER(SEARCH("Agile",K30)),1,0)) -> 0 | AI30: =IF(ISBLANK(K30),0,IF(ISNUMBER(SEARCH("Jira",K30)),1,0)) -> 0 | AJ30: =IF(ISBLANK(K30),0,IF(ISNUMBER(SEARCH("Git",K30)),1,0)) -> 1 | AK30: =IF(ISBLANK(K30),0,IF(ISNUMBER(SEARCH("Reporting",K30)),1,0)) -> 0 | AL30: =IF(ISBLANK(K30),0,IF(ISNUMBER(SEARCH("CI/CD",K30)),1,0)) -> 1 | AM30: =IF(ISBLANK(L30),0,IF(ISNUMBER(SEARCH("Python",L30)),1,0)) -> 0 | AN30: =IF(ISBLANK(L30),0,IF(ISNUMBER(SEARCH("SQL",L30)),1,0)) -> 0 | AO30: =IF(ISBLANK(L30),0,IF(ISNUMBER(SEARCH("Airflow",L30)),1,0)) -> 0 | AP30: =IF(ISBLANK(L30),0,IF(ISNUMBER(SEARCH("Kafka",L30)),1,0)) -> 0 | AQ30: =IF(ISBLANK(L30),0,IF(ISNUMBER(SEARCH("ML",L30)),1,0)) -> 0 | AR30: =IF(ISBLANK(L31),0,IF(ISNUMBER(SEARCH("ML",L31)),1,0)) -> 1 | AS30: =IF(ISBLANK(L32),0,IF(ISNUMBER(SEARCH("Docker",L32)),1,0)) -> 0 | AT30: =IF(ISBLANK(L32),0,IF(ISNUMBER(SEARCH("dbt",L32)),1,0)) -> 0 | AU30: =IF(ISBLANK(L32),0,IF(ISNUMBER(SEARCH("AWS",L32)),1,0)) -> 0 | AV30: =IF(ISBLANK(L32),0,IF(ISNUMBER(SEARCH("GCP",L32)),1,0)) -> 0 | AW30: =IF(ISBLANK(L32),0,IF(ISNUMBER(SEARCH("Azure",L32)),1,0)) -> 0 | AX30: =IF(ISBLANK(M32),0,IF(ISNUMBER(SEARCH("Tableau",L32)),1,0)) -> 0 | AY30: =IF(ISBLANK(N32),0,IF(ISNUMBER(SEARCH("PowerBI",L32)),1,0)) -> 0 | AZ30: Fulltime
A31: 30 | B31: 46178 | C31: LinkedIn | D31: Data Engineer | E31: Emergent | F31: Bengaluru | G31: 3 | H31: ND | I31: ND | J31: ND | K31: Python , SQL , Cloud Data Platforms, Data modeling , Data warehousing | L31: ML pipelines, MLOps, DevOps Practices , dbt, Kafka or similar technologies | M31: On-site | N31: Startup | O31: =IF(ISBLANK(K31),0,IF(ISNUMBER(SEARCH("sql",K31)),1,0)) -> 1 | P31: =IF(ISBLANK(K31),0,IF(ISNUMBER(SEARCH("Python",K31)),1,0)) -> 1 | Q31: =IF(ISBLANK(K31),0,IF(ISNUMBER(SEARCH("PowerBI",K31)),1,0)) -> 0 | R31: =IF(ISBLANK(K31),0,IF(ISNUMBER(SEARCH("Tableau",K31)),1,0)) -> 0 | S31: =IF(ISBLANK(K31),0,IF(ISNUMBER(SEARCH("Excel",K31)),1,0)) -> 0 | T31: =IF(ISBLANK(K31),0,IF(ISNUMBER(SEARCH("Statistics",K31)),1,0)) -> 0 | U31: =IF(ISBLANK(K31),0,IF(ISNUMBER(SEARCH("AWS",K31)),1,0)) -> 0 | V31: =IF(ISBLANK(K31),0,IF(ISNUMBER(SEARCH("GCP",K31)),1,0)) -> 0 | W31: =IF(ISBLANK(K31),0,IF(ISNUMBER(SEARCH("NoSQL",K31)),1,0)) -> 0 | X31: =IF(ISBLANK(K31),0,IF(ISNUMBER(SEARCH("Data Modeling",K31)),1,0)) -> 1 | Y31: =IF(ISBLANK(K31),0,IF(ISNUMBER(SEARCH("Pandas",K31)),1,0)) -> 0 | Z31: =IF(ISBLANK(K31),0,IF(ISNUMBER(SEARCH("Numpy",K31)),1,0)) -> 0 | AA31: =IF(ISBLANK(K31),0,IF(ISNUMBER(SEARCH("Pyspark",K31)),1,0)) -> 0 | AB31: =IF(ISBLANK(K31),0,IF(ISNUMBER(SEARCH("Hadoop",K31)),1,0)) -> 0 | AC31: =IF(ISBLANK(K31),0,IF(ISNUMBER(SEARCH("ETL",K31)),1,0)) -> 0 | AD31: =IF(ISBLANK(K31),0,IF(ISNUMBER(SEARCH("Azure",K31)),1,0)) -> 0 | AE31: =IF(ISBLANK(K31),0,IF(ISNUMBER(SEARCH("Databricks",K31)),1,0)) -> 0 | AF31: =IF(ISBLANK(K31),0,IF(ISNUMBER(SEARCH("A/B Testing",K31)),1,0)) -> 0 | AG31: =IF(ISBLANK(K31),0,IF(ISNUMBER(SEARCH("Snowflake",K31)),1,0)) -> 0 | AH31: =IF(ISBLANK(K31),0,IF(ISNUMBER(SEARCH("Agile",K31)),1,0)) -> 0 | AI31: =IF(ISBLANK(K31),0,IF(ISNUMBER(SEARCH("Jira",K31)),1,0)) -> 0 | AJ31: =IF(ISBLANK(K31),0,IF(ISNUMBER(SEARCH("Git",K31)),1,0)) -> 0 | AK31: =IF(ISBLANK(K31),0,IF(ISNUMBER(SEARCH("Reporting",K31)),1,0)) -> 0 | AL31: =IF(ISBLANK(K31),0,IF(ISNUMBER(SEARCH("CI/CD",K31)),1,0)) -> 0 | AM31: =IF(ISBLANK(L31),0,IF(ISNUMBER(SEARCH("Python",L31)),1,0)) -> 0 | AN31: =IF(ISBLANK(L31),0,IF(ISNUMBER(SEARCH("SQL",L31)),1,0)) -> 0 | AO31: =IF(ISBLANK(L31),0,IF(ISNUMBER(SEARCH("Airflow",L31)),1,0)) -> 0 | AP31: =IF(ISBLANK(L31),0,IF(ISNUMBER(SEARCH("Kafka",L31)),1,0)) -> 1 | AQ31: =IF(ISBLANK(L31),0,IF(ISNUMBER(SEARCH("ML",L31)),1,0)) -> 1 | AR31: =IF(ISBLANK(L32),0,IF(ISNUMBER(SEARCH("ML",L32)),1,0)) -> 0 | AS31: =IF(ISBLANK(L33),0,IF(ISNUMBER(SEARCH("Docker",L33)),1,0)) -> 0 | AT31: =IF(ISBLANK(L33),0,IF(ISNUMBER(SEARCH("dbt",L33)),1,0)) -> 0 | AU31: =IF(ISBLANK(L33),0,IF(ISNUMBER(SEARCH("AWS",L33)),1,0)) -> 0 | AV31: =IF(ISBLANK(L33),0,IF(ISNUMBER(SEARCH("GCP",L33)),1,0)) -> 0 | AW31: =IF(ISBLANK(L33),0,IF(ISNUMBER(SEARCH("Azure",L33)),1,0)) -> 0 | AX31: =IF(ISBLANK(M33),0,IF(ISNUMBER(SEARCH("Tableau",L33)),1,0)) -> 0 | AY31: =IF(ISBLANK(N33),0,IF(ISNUMBER(SEARCH("PowerBI",L33)),1,0)) -> 0 | AZ31: Fulltime
A32: 31 | B32: 46178 | C32: LinkedIn | D32: Data Engineer | E32: Atlys | F32: Delhi | G32: 1 | H32: 3 | I32: ND | J32: ND | K32: Python, FastAPI, SQL, Data Pipelines, ETL,Databases | L32: Postgres , Clickhouse, Understandong of LLMs | M32: On-site | N32: Startup | O32: =IF(ISBLANK(K32),0,IF(ISNUMBER(SEARCH("sql",K32)),1,0)) -> 1 | P32: =IF(ISBLANK(K32),0,IF(ISNUMBER(SEARCH("Python",K32)),1,0)) -> 1 | Q32: =IF(ISBLANK(K32),0,IF(ISNUMBER(SEARCH("PowerBI",K32)),1,0)) -> 0 | R32: =IF(ISBLANK(K32),0,IF(ISNUMBER(SEARCH("Tableau",K32)),1,0)) -> 0 | S32: =IF(ISBLANK(K32),0,IF(ISNUMBER(SEARCH("Excel",K32)),1,0)) -> 0 | T32: =IF(ISBLANK(K32),0,IF(ISNUMBER(SEARCH("Statistics",K32)),1,0)) -> 0 | U32: =IF(ISBLANK(K32),0,IF(ISNUMBER(SEARCH("AWS",K32)),1,0)) -> 0 | V32: =IF(ISBLANK(K32),0,IF(ISNUMBER(SEARCH("GCP",K32)),1,0)) -> 0 | W32: =IF(ISBLANK(K32),0,IF(ISNUMBER(SEARCH("NoSQL",K32)),1,0)) -> 0 | X32: =IF(ISBLANK(K32),0,IF(ISNUMBER(SEARCH("Data Modeling",K32)),1,0)) -> 0 | Y32: =IF(ISBLANK(K32),0,IF(ISNUMBER(SEARCH("Pandas",K32)),1,0)) -> 0 | Z32: =IF(ISBLANK(K32),0,IF(ISNUMBER(SEARCH("Numpy",K32)),1,0)) -> 0 | AA32: =IF(ISBLANK(K32),0,IF(ISNUMBER(SEARCH("Pyspark",K32)),1,0)) -> 0 | AB32: =IF(ISBLANK(K32),0,IF(ISNUMBER(SEARCH("Hadoop",K32)),1,0)) -> 0 | AC32: =IF(ISBLANK(K32),0,IF(ISNUMBER(SEARCH("ETL",K32)),1,0)) -> 1 | AD32: =IF(ISBLANK(K32),0,IF(ISNUMBER(SEARCH("Azure",K32)),1,0)) -> 0 | AE32: =IF(ISBLANK(K32),0,IF(ISNUMBER(SEARCH("Databricks",K32)),1,0)) -> 0 | AF32: =IF(ISBLANK(K32),0,IF(ISNUMBER(SEARCH("A/B Testing",K32)),1,0)) -> 0 | AG32: =IF(ISBLANK(K32),0,IF(ISNUMBER(SEARCH("Snowflake",K32)),1,0)) -> 0 | AH32: =IF(ISBLANK(K32),0,IF(ISNUMBER(SEARCH("Agile",K32)),1,0)) -> 0 | AI32: =IF(ISBLANK(K32),0,IF(ISNUMBER(SEARCH("Jira",K32)),1,0)) -> 0 | AJ32: =IF(ISBLANK(K32),0,IF(ISNUMBER(SEARCH("Git",K32)),1,0)) -> 0 | AK32: =IF(ISBLANK(K32),0,IF(ISNUMBER(SEARCH("Reporting",K32)),1,0)) -> 0 | AL32: =IF(ISBLANK(K32),0,IF(ISNUMBER(SEARCH("CI/CD",K32)),1,0)) -> 0 | AM32: =IF(ISBLANK(L32),0,IF(ISNUMBER(SEARCH("Python",L32)),1,0)) -> 0 | AN32: =IF(ISBLANK(L32),0,IF(ISNUMBER(SEARCH("SQL",L32)),1,0)) -> 0 | AO32: =IF(ISBLANK(L32),0,IF(ISNUMBER(SEARCH("Airflow",L32)),1,0)) -> 0 | AP32: =IF(ISBLANK(L32),0,IF(ISNUMBER(SEARCH("Kafka",L32)),1,0)) -> 0 | AQ32: =IF(ISBLANK(L32),0,IF(ISNUMBER(SEARCH("ML",L32)),1,0)) -> 0 | AR32: =IF(ISBLANK(L33),0,IF(ISNUMBER(SEARCH("ML",L33)),1,0)) -> 0 | AS32: =IF(ISBLANK(L34),0,IF(ISNUMBER(SEARCH("Docker",L34)),1,0)) -> 0 | AT32: =IF(ISBLANK(L34),0,IF(ISNUMBER(SEARCH("dbt",L34)),1,0)) -> 0 | AU32: =IF(ISBLANK(L34),0,IF(ISNUMBER(SEARCH("AWS",L34)),1,0)) -> 0 | AV32: =IF(ISBLANK(L34),0,IF(ISNUMBER(SEARCH("GCP",L34)),1,0)) -> 0 | AW32: =IF(ISBLANK(L34),0,IF(ISNUMBER(SEARCH("Azure",L34)),1,0)) -> 0 | AX32: =IF(ISBLANK(M34),0,IF(ISNUMBER(SEARCH("Tableau",L34)),1,0)) -> 0 | AY32: =IF(ISBLANK(N34),0,IF(ISNUMBER(SEARCH("PowerBI",L34)),1,0)) -> 0 | AZ32: Fulltime
A33: 32 | B33: 46178 | C33: LinkedIn | D33: Data Engineer | E33: Synechron | F33: Bengaluru | G33: 7 | H33: 12 | I33: ND | J33: ND | K33: AWS Services, SQL , Data modeling, Python | L33: Big data tools , Airflow, CI/CD pipelines | M33: Hybrid | N33: Medium | O33: =IF(ISBLANK(K33),0,IF(ISNUMBER(SEARCH("sql",K33)),1,0)) -> 1 | P33: =IF(ISBLANK(K33),0,IF(ISNUMBER(SEARCH("Python",K33)),1,0)) -> 1 | Q33: =IF(ISBLANK(K33),0,IF(ISNUMBER(SEARCH("PowerBI",K33)),1,0)) -> 0 | R33: =IF(ISBLANK(K33),0,IF(ISNUMBER(SEARCH("Tableau",K33)),1,0)) -> 0 | S33: =IF(ISBLANK(K33),0,IF(ISNUMBER(SEARCH("Excel",K33)),1,0)) -> 0 | T33: =IF(ISBLANK(K33),0,IF(ISNUMBER(SEARCH("Statistics",K33)),1,0)) -> 0 | U33: =IF(ISBLANK(K33),0,IF(ISNUMBER(SEARCH("AWS",K33)),1,0)) -> 1 | V33: =IF(ISBLANK(K33),0,IF(ISNUMBER(SEARCH("GCP",K33)),1,0)) -> 0 | W33: =IF(ISBLANK(K33),0,IF(ISNUMBER(SEARCH("NoSQL",K33)),1,0)) -> 0 | X33: =IF(ISBLANK(K33),0,IF(ISNUMBER(SEARCH("Data Modeling",K33)),1,0)) -> 1 | Y33: =IF(ISBLANK(K33),0,IF(ISNUMBER(SEARCH("Pandas",K33)),1,0)) -> 0 | Z33: =IF(ISBLANK(K33),0,IF(ISNUMBER(SEARCH("Numpy",K33)),1,0)) -> 0 | AA33: =IF(ISBLANK(K33),0,IF(ISNUMBER(SEARCH("Pyspark",K33)),1,0)) -> 0 | AB33: =IF(ISBLANK(K33),0,IF(ISNUMBER(SEARCH("Hadoop",K33)),1,0)) -> 0 | AC33: =IF(ISBLANK(K33),0,IF(ISNUMBER(SEARCH("ETL",K33)),1,0)) -> 0 | AD33: =IF(ISBLANK(K33),0,IF(ISNUMBER(SEARCH("Azure",K33)),1,0)) -> 0 | AE33: =IF(ISBLANK(K33),0,IF(ISNUMBER(SEARCH("Databricks",K33)),1,0)) -> 0 | AF33: =IF(ISBLANK(K33),0,IF(ISNUMBER(SEARCH("A/B Testing",K33)),1,0)) -> 0 | AG33: =IF(ISBLANK(K33),0,IF(ISNUMBER(SEARCH("Snowflake",K33)),1,0)) -> 0 | AH33: =IF(ISBLANK(K33),0,IF(ISNUMBER(SEARCH("Agile",K33)),1,0)) -> 0 | AI33: =IF(ISBLANK(K33),0,IF(ISNUMBER(SEARCH("Jira",K33)),1,0)) -> 0 | AJ33: =IF(ISBLANK(K33),0,IF(ISNUMBER(SEARCH("Git",K33)),1,0)) -> 0 | AK33: =IF(ISBLANK(K33),0,IF(ISNUMBER(SEARCH("Reporting",K33)),1,0)) -> 0 | AL33: =IF(ISBLANK(K33),0,IF(ISNUMBER(SEARCH("CI/CD",K33)),1,0)) -> 0 | AM33: =IF(ISBLANK(L33),0,IF(ISNUMBER(SEARCH("Python",L33)),1,0)) -> 0 | AN33: =IF(ISBLANK(L33),0,IF(ISNUMBER(SEARCH("SQL",L33)),1,0)) -> 0 | AO33: =IF(ISBLANK(L33),0,IF(ISNUMBER(SEARCH("Airflow",L33)),1,0)) -> 1 | AP33: =IF(ISBLANK(L33),0,IF(ISNUMBER(SEARCH("Kafka",L33)),1,0)) -> 0 | AQ33: =IF(ISBLANK(L33),0,IF(ISNUMBER(SEARCH("ML",L33)),1,0)) -> 0 | AR33: =IF(ISBLANK(L34),0,IF(ISNUMBER(SEARCH("ML",L34)),1,0)) -> 0 | AS33: =IF(ISBLANK(L35),0,IF(ISNUMBER(SEARCH("Docker",L35)),1,0)) -> 1 | AT33: =IF(ISBLANK(L35),0,IF(ISNUMBER(SEARCH("dbt",L35)),1,0)) -> 0 | AU33: =IF(ISBLANK(L35),0,IF(ISNUMBER(SEARCH("AWS",L35)),1,0)) -> 0 | AV33: =IF(ISBLANK(L35),0,IF(ISNUMBER(SEARCH("GCP",L35)),1,0)) -> 0 | AW33: =IF(ISBLANK(L35),0,IF(ISNUMBER(SEARCH("Azure",L35)),1,0)) -> 0 | AX33: =IF(ISBLANK(M35),0,IF(ISNUMBER(SEARCH("Tableau",L35)),1,0)) -> 0 | AY33: =IF(ISBLANK(N35),0,IF(ISNUMBER(SEARCH("PowerBI",L35)),1,0)) -> 0 | AZ33: Fulltime
A34: 33 | B34: 46178 | C34: LinkedIn | D34: Data Engineer | E34: NAB | F34: Gurgaon | G34: ND | H34: ND | I34: ND | J34: ND | K34: SQL , Python, Pyspark | L34: Experience with databricks or similar cloud based platforms | M34: On-site | N34: Large | O34: =IF(ISBLANK(K34),0,IF(ISNUMBER(SEARCH("sql",K34)),1,0)) -> 1 | P34: =IF(ISBLANK(K34),0,IF(ISNUMBER(SEARCH("Python",K34)),1,0)) -> 1 | Q34: =IF(ISBLANK(K34),0,IF(ISNUMBER(SEARCH("PowerBI",K34)),1,0)) -> 0 | R34: =IF(ISBLANK(K34),0,IF(ISNUMBER(SEARCH("Tableau",K34)),1,0)) -> 0 | S34: =IF(ISBLANK(K34),0,IF(ISNUMBER(SEARCH("Excel",K34)),1,0)) -> 0 | T34: =IF(ISBLANK(K34),0,IF(ISNUMBER(SEARCH("Statistics",K34)),1,0)) -> 0 | U34: =IF(ISBLANK(K34),0,IF(ISNUMBER(SEARCH("AWS",K34)),1,0)) -> 0 | V34: =IF(ISBLANK(K34),0,IF(ISNUMBER(SEARCH("GCP",K34)),1,0)) -> 0 | W34: =IF(ISBLANK(K34),0,IF(ISNUMBER(SEARCH("NoSQL",K34)),1,0)) -> 0 | X34: =IF(ISBLANK(K34),0,IF(ISNUMBER(SEARCH("Data Modeling",K34)),1,0)) -> 0 | Y34: =IF(ISBLANK(K34),0,IF(ISNUMBER(SEARCH("Pandas",K34)),1,0)) -> 0 | Z34: =IF(ISBLANK(K34),0,IF(ISNUMBER(SEARCH("Numpy",K34)),1,0)) -> 0 | AA34: =IF(ISBLANK(K34),0,IF(ISNUMBER(SEARCH("Pyspark",K34)),1,0)) -> 1 | AB34: =IF(ISBLANK(K34),0,IF(ISNUMBER(SEARCH("Hadoop",K34)),1,0)) -> 0 | AC34: =IF(ISBLANK(K34),0,IF(ISNUMBER(SEARCH("ETL",K34)),1,0)) -> 0 | AD34: =IF(ISBLANK(K34),0,IF(ISNUMBER(SEARCH("Azure",K34)),1,0)) -> 0 | AE34: =IF(ISBLANK(K34),0,IF(ISNUMBER(SEARCH("Databricks",K34)),1,0)) -> 0 | AF34: =IF(ISBLANK(K34),0,IF(ISNUMBER(SEARCH("A/B Testing",K34)),1,0)) -> 0 | AG34: =IF(ISBLANK(K34),0,IF(ISNUMBER(SEARCH("Snowflake",K34)),1,0)) -> 0 | AH34: =IF(ISBLANK(K34),0,IF(ISNUMBER(SEARCH("Agile",K34)),1,0)) -> 0 | AI34: =IF(ISBLANK(K34),0,IF(ISNUMBER(SEARCH("Jira",K34)),1,0)) -> 0 | AJ34: =IF(ISBLANK(K34),0,IF(ISNUMBER(SEARCH("Git",K34)),1,0)) -> 0 | AK34: =IF(ISBLANK(K34),0,IF(ISNUMBER(SEARCH("Reporting",K34)),1,0)) -> 0 | AL34: =IF(ISBLANK(K34),0,IF(ISNUMBER(SEARCH("CI/CD",K34)),1,0)) -> 0 | AM34: =IF(ISBLANK(L34),0,IF(ISNUMBER(SEARCH("Python",L34)),1,0)) -> 0 | AN34: =IF(ISBLANK(L34),0,IF(ISNUMBER(SEARCH("SQL",L34)),1,0)) -> 0 | AO34: =IF(ISBLANK(L34),0,IF(ISNUMBER(SEARCH("Airflow",L34)),1,0)) -> 0 | AP34: =IF(ISBLANK(L34),0,IF(ISNUMBER(SEARCH("Kafka",L34)),1,0)) -> 0 | AQ34: =IF(ISBLANK(L34),0,IF(ISNUMBER(SEARCH("ML",L34)),1,0)) -> 0 | AR34: =IF(ISBLANK(L35),0,IF(ISNUMBER(SEARCH("ML",L35)),1,0)) -> 0 | AS34: =IF(ISBLANK(L36),0,IF(ISNUMBER(SEARCH("Docker",L36)),1,0)) -> 0 | AT34: =IF(ISBLANK(L36),0,IF(ISNUMBER(SEARCH("dbt",L36)),1,0)) -> 0 | AU34: =IF(ISBLANK(L36),0,IF(ISNUMBER(SEARCH("AWS",L36)),1,0)) -> 0 | AV34: =IF(ISBLANK(L36),0,IF(ISNUMBER(SEARCH("GCP",L36)),1,0)) -> 0 | AW34: =IF(ISBLANK(L36),0,IF(ISNUMBER(SEARCH("Azure",L36)),1,0)) -> 0 | AX34: =IF(ISBLANK(M36),0,IF(ISNUMBER(SEARCH("Tableau",L36)),1,0)) -> 0 | AY34: =IF(ISBLANK(N36),0,IF(ISNUMBER(SEARCH("PowerBI",L36)),1,0)) -> 0 | AZ34: Fulltime
A35: 34 | B35: 46178 | C35: LinkedIn | D35: Data Engineer | E35: UST | F35: Bengaluru | G35: 4 | H35: 6 | I35: ND | J35: ND | K35: Python, RESTAPIs , SQL , Data pipelines, Data parsing | L35: RAG , VectorDB, Cloud and docker platforms , Front emd frameworks | M35: On-site | N35: Medium | O35: =IF(ISBLANK(K35),0,IF(ISNUMBER(SEARCH("sql",K35)),1,0)) -> 1 | P35: =IF(ISBLANK(K35),0,IF(ISNUMBER(SEARCH("Python",K35)),1,0)) -> 1 | Q35: =IF(ISBLANK(K35),0,IF(ISNUMBER(SEARCH("PowerBI",K35)),1,0)) -> 0 | R35: =IF(ISBLANK(K35),0,IF(ISNUMBER(SEARCH("Tableau",K35)),1,0)) -> 0 | S35: =IF(ISBLANK(K35),0,IF(ISNUMBER(SEARCH("Excel",K35)),1,0)) -> 0 | T35: =IF(ISBLANK(K35),0,IF(ISNUMBER(SEARCH("Statistics",K35)),1,0)) -> 0 | U35: =IF(ISBLANK(K35),0,IF(ISNUMBER(SEARCH("AWS",K35)),1,0)) -> 0 | V35: =IF(ISBLANK(K35),0,IF(ISNUMBER(SEARCH("GCP",K35)),1,0)) -> 0 | W35: =IF(ISBLANK(K35),0,IF(ISNUMBER(SEARCH("NoSQL",K35)),1,0)) -> 0 | X35: =IF(ISBLANK(K35),0,IF(ISNUMBER(SEARCH("Data Modeling",K35)),1,0)) -> 0 | Y35: =IF(ISBLANK(K35),0,IF(ISNUMBER(SEARCH("Pandas",K35)),1,0)) -> 0 | Z35: =IF(ISBLANK(K35),0,IF(ISNUMBER(SEARCH("Numpy",K35)),1,0)) -> 0 | AA35: =IF(ISBLANK(K35),0,IF(ISNUMBER(SEARCH("Pyspark",K35)),1,0)) -> 0 | AB35: =IF(ISBLANK(K35),0,IF(ISNUMBER(SEARCH("Hadoop",K35)),1,0)) -> 0 | AC35: =IF(ISBLANK(K35),0,IF(ISNUMBER(SEARCH("ETL",K35)),1,0)) -> 0 | AD35: =IF(ISBLANK(K35),0,IF(ISNUMBER(SEARCH("Azure",K35)),1,0)) -> 0 | AE35: =IF(ISBLANK(K35),0,IF(ISNUMBER(SEARCH("Databricks",K35)),1,0)) -> 0 | AF35: =IF(ISBLANK(K35),0,IF(ISNUMBER(SEARCH("A/B Testing",K35)),1,0)) -> 0 | AG35: =IF(ISBLANK(K35),0,IF(ISNUMBER(SEARCH("Snowflake",K35)),1,0)) -> 0 | AH35: =IF(ISBLANK(K35),0,IF(ISNUMBER(SEARCH("Agile",K35)),1,0)) -> 0 | AI35: =IF(ISBLANK(K35),0,IF(ISNUMBER(SEARCH("Jira",K35)),1,0)) -> 0 | AJ35: =IF(ISBLANK(K35),0,IF(ISNUMBER(SEARCH("Git",K35)),1,0)) -> 0 | AK35: =IF(ISBLANK(K35),0,IF(ISNUMBER(SEARCH("Reporting",K35)),1,0)) -> 0 | AL35: =IF(ISBLANK(K35),0,IF(ISNUMBER(SEARCH("CI/CD",K35)),1,0)) -> 0 | AM35: =IF(ISBLANK(L35),0,IF(ISNUMBER(SEARCH("Python",L35)),1,0)) -> 0 | AN35: =IF(ISBLANK(L35),0,IF(ISNUMBER(SEARCH("SQL",L35)),1,0)) -> 0 | AO35: =IF(ISBLANK(L35),0,IF(ISNUMBER(SEARCH("Airflow",L35)),1,0)) -> 0 | AP35: =IF(ISBLANK(L35),0,IF(ISNUMBER(SEARCH("Kafka",L35)),1,0)) -> 0 | AQ35: =IF(ISBLANK(L35),0,IF(ISNUMBER(SEARCH("ML",L35)),1,0)) -> 0 | AR35: =IF(ISBLANK(L36),0,IF(ISNUMBER(SEARCH("ML",L36)),1,0)) -> 0 | AS35: =IF(ISBLANK(L37),0,IF(ISNUMBER(SEARCH("Docker",L37)),1,0)) -> 0 | AT35: =IF(ISBLANK(L37),0,IF(ISNUMBER(SEARCH("dbt",L37)),1,0)) -> 0 | AU35: =IF(ISBLANK(L37),0,IF(ISNUMBER(SEARCH("AWS",L37)),1,0)) -> 0 | AV35: =IF(ISBLANK(L37),0,IF(ISNUMBER(SEARCH("GCP",L37)),1,0)) -> 0 | AW35: =IF(ISBLANK(L37),0,IF(ISNUMBER(SEARCH("Azure",L37)),1,0)) -> 0 | AX35: =IF(ISBLANK(M37),0,IF(ISNUMBER(SEARCH("Tableau",L37)),1,0)) -> 0 | AY35: =IF(ISBLANK(N37),0,IF(ISNUMBER(SEARCH("PowerBI",L37)),1,0)) -> 0 | AZ35: Fulltime
A36: 35 | B36: 46178 | C36: LinkedIn | D36: Data Engineer | E36: Definitive Healthcare | F36: Bengaluru | G36: 2 | H36: 5 | I36: ND | J36: ND | K36: Python, Databricks, pyspark, Airflow, AWS S3, Argo Workflows, SQL | L36: None | M36: On-site | N36: Large | O36: =IF(ISBLANK(K36),0,IF(ISNUMBER(SEARCH("sql",K36)),1,0)) -> 1 | P36: =IF(ISBLANK(K36),0,IF(ISNUMBER(SEARCH("Python",K36)),1,0)) -> 1 | Q36: =IF(ISBLANK(K36),0,IF(ISNUMBER(SEARCH("PowerBI",K36)),1,0)) -> 0 | R36: =IF(ISBLANK(K36),0,IF(ISNUMBER(SEARCH("Tableau",K36)),1,0)) -> 0 | S36: =IF(ISBLANK(K36),0,IF(ISNUMBER(SEARCH("Excel",K36)),1,0)) -> 0 | T36: =IF(ISBLANK(K36),0,IF(ISNUMBER(SEARCH("Statistics",K36)),1,0)) -> 0 | U36: =IF(ISBLANK(K36),0,IF(ISNUMBER(SEARCH("AWS",K36)),1,0)) -> 1 | V36: =IF(ISBLANK(K36),0,IF(ISNUMBER(SEARCH("GCP",K36)),1,0)) -> 0 | W36: =IF(ISBLANK(K36),0,IF(ISNUMBER(SEARCH("NoSQL",K36)),1,0)) -> 0 | X36: =IF(ISBLANK(K36),0,IF(ISNUMBER(SEARCH("Data Modeling",K36)),1,0)) -> 0 | Y36: =IF(ISBLANK(K36),0,IF(ISNUMBER(SEARCH("Pandas",K36)),1,0)) -> 0 | Z36: =IF(ISBLANK(K36),0,IF(ISNUMBER(SEARCH("Numpy",K36)),1,0)) -> 0 | AA36: =IF(ISBLANK(K36),0,IF(ISNUMBER(SEARCH("Pyspark",K36)),1,0)) -> 1 | AB36: =IF(ISBLANK(K36),0,IF(ISNUMBER(SEARCH("Hadoop",K36)),1,0)) -> 0 | AC36: =IF(ISBLANK(K36),0,IF(ISNUMBER(SEARCH("ETL",K36)),1,0)) -> 0 | AD36: =IF(ISBLANK(K36),0,IF(ISNUMBER(SEARCH("Azure",K36)),1,0)) -> 0 | AE36: =IF(ISBLANK(K36),0,IF(ISNUMBER(SEARCH("Databricks",K36)),1,0)) -> 1 | AF36: =IF(ISBLANK(K36),0,IF(ISNUMBER(SEARCH("A/B Testing",K36)),1,0)) -> 0 | AG36: =IF(ISBLANK(K36),0,IF(ISNUMBER(SEARCH("Snowflake",K36)),1,0)) -> 0 | AH36: =IF(ISBLANK(K36),0,IF(ISNUMBER(SEARCH("Agile",K36)),1,0)) -> 0 | AI36: =IF(ISBLANK(K36),0,IF(ISNUMBER(SEARCH("Jira",K36)),1,0)) -> 0 | AJ36: =IF(ISBLANK(K36),0,IF(ISNUMBER(SEARCH("Git",K36)),1,0)) -> 0 | AK36: =IF(ISBLANK(K36),0,IF(ISNUMBER(SEARCH("Reporting",K36)),1,0)) -> 0 | AL36: =IF(ISBLANK(K36),0,IF(ISNUMBER(SEARCH("CI/CD",K36)),1,0)) -> 0 | AM36: =IF(ISBLANK(L36),0,IF(ISNUMBER(SEARCH("Python",L36)),1,0)) -> 0 | AN36: =IF(ISBLANK(L36),0,IF(ISNUMBER(SEARCH("SQL",L36)),1,0)) -> 0 | AO36: =IF(ISBLANK(L36),0,IF(ISNUMBER(SEARCH("Airflow",L36)),1,0)) -> 0 | AP36: =IF(ISBLANK(L36),0,IF(ISNUMBER(SEARCH("Kafka",L36)),1,0)) -> 0 | AQ36: =IF(ISBLANK(L36),0,IF(ISNUMBER(SEARCH("ML",L36)),1,0)) -> 0 | AR36: =IF(ISBLANK(L37),0,IF(ISNUMBER(SEARCH("ML",L37)),1,0)) -> 0 | AS36: =IF(ISBLANK(L38),0,IF(ISNUMBER(SEARCH("Docker",L38)),1,0)) -> 0 | AT36: =IF(ISBLANK(L38),0,IF(ISNUMBER(SEARCH("dbt",L38)),1,0)) -> 0 | AU36: =IF(ISBLANK(L38),0,IF(ISNUMBER(SEARCH("AWS",L38)),1,0)) -> 0 | AV36: =IF(ISBLANK(L38),0,IF(ISNUMBER(SEARCH("GCP",L38)),1,0)) -> 0 | AW36: =IF(ISBLANK(L38),0,IF(ISNUMBER(SEARCH("Azure",L38)),1,0)) -> 0 | AX36: =IF(ISBLANK(M38),0,IF(ISNUMBER(SEARCH("Tableau",L38)),1,0)) -> 0 | AY36: =IF(ISBLANK(N38),0,IF(ISNUMBER(SEARCH("PowerBI",L38)),1,0)) -> 0 | AZ36: Fulltime
A37: 36 | B37: 46178 | C37: LinkedIn | D37: Data Engineer | E37: LTM | F37: Bengaluru | G37: 2 | H37: 5 | I37: ND | J37: ND | K37: GCP , Big Query, Python | L37: Airflow, Hadoop , RDBMS, NoSQL databases | M37: Hybrid | N37: Medium | O37: =IF(ISBLANK(K37),0,IF(ISNUMBER(SEARCH("sql",K37)),1,0)) -> 0 | P37: =IF(ISBLANK(K37),0,IF(ISNUMBER(SEARCH("Python",K37)),1,0)) -> 1 | Q37: =IF(ISBLANK(K37),0,IF(ISNUMBER(SEARCH("PowerBI",K37)),1,0)) -> 0 | R37: =IF(ISBLANK(K37),0,IF(ISNUMBER(SEARCH("Tableau",K37)),1,0)) -> 0 | S37: =IF(ISBLANK(K37),0,IF(ISNUMBER(SEARCH("Excel",K37)),1,0)) -> 0 | T37: =IF(ISBLANK(K37),0,IF(ISNUMBER(SEARCH("Statistics",K37)),1,0)) -> 0 | U37: =IF(ISBLANK(K37),0,IF(ISNUMBER(SEARCH("AWS",K37)),1,0)) -> 0 | V37: =IF(ISBLANK(K37),0,IF(ISNUMBER(SEARCH("GCP",K37)),1,0)) -> 1 | W37: =IF(ISBLANK(K37),0,IF(ISNUMBER(SEARCH("NoSQL",K37)),1,0)) -> 0 | X37: =IF(ISBLANK(K37),0,IF(ISNUMBER(SEARCH("Data Modeling",K37)),1,0)) -> 0 | Y37: =IF(ISBLANK(K37),0,IF(ISNUMBER(SEARCH("Pandas",K37)),1,0)) -> 0 | Z37: =IF(ISBLANK(K37),0,IF(ISNUMBER(SEARCH("Numpy",K37)),1,0)) -> 0 | AA37: =IF(ISBLANK(K37),0,IF(ISNUMBER(SEARCH("Pyspark",K37)),1,0)) -> 0 | AB37: =IF(ISBLANK(K37),0,IF(ISNUMBER(SEARCH("Hadoop",K37)),1,0)) -> 0 | AC37: =IF(ISBLANK(K37),0,IF(ISNUMBER(SEARCH("ETL",K37)),1,0)) -> 0 | AD37: =IF(ISBLANK(K37),0,IF(ISNUMBER(SEARCH("Azure",K37)),1,0)) -> 0 | AE37: =IF(ISBLANK(K37),0,IF(ISNUMBER(SEARCH("Databricks",K37)),1,0)) -> 0 | AF37: =IF(ISBLANK(K37),0,IF(ISNUMBER(SEARCH("A/B Testing",K37)),1,0)) -> 0 | AG37: =IF(ISBLANK(K37),0,IF(ISNUMBER(SEARCH("Snowflake",K37)),1,0)) -> 0 | AH37: =IF(ISBLANK(K37),0,IF(ISNUMBER(SEARCH("Agile",K37)),1,0)) -> 0 | AI37: =IF(ISBLANK(K37),0,IF(ISNUMBER(SEARCH("Jira",K37)),1,0)) -> 0 | AJ37: =IF(ISBLANK(K37),0,IF(ISNUMBER(SEARCH("Git",K37)),1,0)) -> 0 | AK37: =IF(ISBLANK(K37),0,IF(ISNUMBER(SEARCH("Reporting",K37)),1,0)) -> 0 | AL37: =IF(ISBLANK(K37),0,IF(ISNUMBER(SEARCH("CI/CD",K37)),1,0)) -> 0 | AM37: =IF(ISBLANK(L37),0,IF(ISNUMBER(SEARCH("Python",L37)),1,0)) -> 0 | AN37: =IF(ISBLANK(L37),0,IF(ISNUMBER(SEARCH("SQL",L37)),1,0)) -> 1 | AO37: =IF(ISBLANK(L37),0,IF(ISNUMBER(SEARCH("Airflow",L37)),1,0)) -> 1 | AP37: =IF(ISBLANK(L37),0,IF(ISNUMBER(SEARCH("Kafka",L37)),1,0)) -> 0 | AQ37: =IF(ISBLANK(L37),0,IF(ISNUMBER(SEARCH("ML",L37)),1,0)) -> 0 | AR37: =IF(ISBLANK(L38),0,IF(ISNUMBER(SEARCH("ML",L38)),1,0)) -> 0 | AS37: =IF(ISBLANK(L39),0,IF(ISNUMBER(SEARCH("Docker",L39)),1,0)) -> 0 | AT37: =IF(ISBLANK(L39),0,IF(ISNUMBER(SEARCH("dbt",L39)),1,0)) -> 0 | AU37: =IF(ISBLANK(L39),0,IF(ISNUMBER(SEARCH("AWS",L39)),1,0)) -> 0 | AV37: =IF(ISBLANK(L39),0,IF(ISNUMBER(SEARCH("GCP",L39)),1,0)) -> 0 | AW37: =IF(ISBLANK(L39),0,IF(ISNUMBER(SEARCH("Azure",L39)),1,0)) -> 0 | AX37: =IF(ISBLANK(M39),0,IF(ISNUMBER(SEARCH("Tableau",L39)),1,0)) -> 0 | AY37: =IF(ISBLANK(N39),0,IF(ISNUMBER(SEARCH("PowerBI",L39)),1,0)) -> 0 | AZ37: Fulltime
A38: 37 | B38: 46178 | C38: LinkedIn | D38: Business Analyst | E38: Hyring | F38: Bengaluru | G38: 3 | H38: 6 | I38: ND | J38: ND | K38: SQL , Python , APIs, Excel | L38: Familiarity with AI powered tools | M38: Hybrid | N38: Medium | O38: =IF(ISBLANK(K38),0,IF(ISNUMBER(SEARCH("sql",K38)),1,0)) -> 1 | P38: =IF(ISBLANK(K38),0,IF(ISNUMBER(SEARCH("Python",K38)),1,0)) -> 1 | Q38: =IF(ISBLANK(K38),0,IF(ISNUMBER(SEARCH("PowerBI",K38)),1,0)) -> 0 | R38: =IF(ISBLANK(K38),0,IF(ISNUMBER(SEARCH("Tableau",K38)),1,0)) -> 0 | S38: =IF(ISBLANK(K38),0,IF(ISNUMBER(SEARCH("Excel",K38)),1,0)) -> 1 | T38: =IF(ISBLANK(K38),0,IF(ISNUMBER(SEARCH("Statistics",K38)),1,0)) -> 0 | U38: =IF(ISBLANK(K38),0,IF(ISNUMBER(SEARCH("AWS",K38)),1,0)) -> 0 | V38: =IF(ISBLANK(K38),0,IF(ISNUMBER(SEARCH("GCP",K38)),1,0)) -> 0 | W38: =IF(ISBLANK(K38),0,IF(ISNUMBER(SEARCH("NoSQL",K38)),1,0)) -> 0 | X38: =IF(ISBLANK(K38),0,IF(ISNUMBER(SEARCH("Data Modeling",K38)),1,0)) -> 0 | Y38: =IF(ISBLANK(K38),0,IF(ISNUMBER(SEARCH("Pandas",K38)),1,0)) -> 0 | Z38: =IF(ISBLANK(K38),0,IF(ISNUMBER(SEARCH("Numpy",K38)),1,0)) -> 0 | AA38: =IF(ISBLANK(K38),0,IF(ISNUMBER(SEARCH("Pyspark",K38)),1,0)) -> 0 | AB38: =IF(ISBLANK(K38),0,IF(ISNUMBER(SEARCH("Hadoop",K38)),1,0)) -> 0 | AC38: =IF(ISBLANK(K38),0,IF(ISNUMBER(SEARCH("ETL",K38)),1,0)) -> 0 | AD38: =IF(ISBLANK(K38),0,IF(ISNUMBER(SEARCH("Azure",K38)),1,0)) -> 0 | AE38: =IF(ISBLANK(K38),0,IF(ISNUMBER(SEARCH("Databricks",K38)),1,0)) -> 0 | AF38: =IF(ISBLANK(K38),0,IF(ISNUMBER(SEARCH("A/B Testing",K38)),1,0)) -> 0 | AG38: =IF(ISBLANK(K38),0,IF(ISNUMBER(SEARCH("Snowflake",K38)),1,0)) -> 0 | AH38: =IF(ISBLANK(K38),0,IF(ISNUMBER(SEARCH("Agile",K38)),1,0)) -> 0 | AI38: =IF(ISBLANK(K38),0,IF(ISNUMBER(SEARCH("Jira",K38)),1,0)) -> 0 | AJ38: =IF(ISBLANK(K38),0,IF(ISNUMBER(SEARCH("Git",K38)),1,0)) -> 0 | AK38: =IF(ISBLANK(K38),0,IF(ISNUMBER(SEARCH("Reporting",K38)),1,0)) -> 0 | AL38: =IF(ISBLANK(K38),0,IF(ISNUMBER(SEARCH("CI/CD",K38)),1,0)) -> 0 | AM38: =IF(ISBLANK(L38),0,IF(ISNUMBER(SEARCH("Python",L38)),1,0)) -> 0 | AN38: =IF(ISBLANK(L38),0,IF(ISNUMBER(SEARCH("SQL",L38)),1,0)) -> 0 | AO38: =IF(ISBLANK(L38),0,IF(ISNUMBER(SEARCH("Airflow",L38)),1,0)) -> 0 | AP38: =IF(ISBLANK(L38),0,IF(ISNUMBER(SEARCH("Kafka",L38)),1,0)) -> 0 | AQ38: =IF(ISBLANK(L38),0,IF(ISNUMBER(SEARCH("ML",L38)),1,0)) -> 0 | AR38: =IF(ISBLANK(L39),0,IF(ISNUMBER(SEARCH("ML",L39)),1,0)) -> 0 | AS38: =IF(ISBLANK(L40),0,IF(ISNUMBER(SEARCH("Docker",L40)),1,0)) -> 0 | AT38: =IF(ISBLANK(L40),0,IF(ISNUMBER(SEARCH("dbt",L40)),1,0)) -> 0 | AU38: =IF(ISBLANK(L40),0,IF(ISNUMBER(SEARCH("AWS",L40)),1,0)) -> 0 | AV38: =IF(ISBLANK(L40),0,IF(ISNUMBER(SEARCH("GCP",L40)),1,0)) -> 0 | AW38: =IF(ISBLANK(L40),0,IF(ISNUMBER(SEARCH("Azure",L40)),1,0)) -> 0 | AX38: =IF(ISBLANK(M40),0,IF(ISNUMBER(SEARCH("Tableau",L40)),1,0)) -> 0 | AY38: =IF(ISBLANK(N40),0,IF(ISNUMBER(SEARCH("PowerBI",L40)),1,0)) -> 0 | AZ38: Fulltime
A39: 38 | B39: 46178 | C39: LinkedIn | D39: Business Analyst | E39: Shuru | F39: Mumbai | G39: 2 | H39: 3 | I39: ND | J39: ND | K39: SQL, Excel | L39: Fintech Knowledge | M39: Hybrid | N39: Small | O39: =IF(ISBLANK(K39),0,IF(ISNUMBER(SEARCH("sql",K39)),1,0)) -> 1 | P39: =IF(ISBLANK(K39),0,IF(ISNUMBER(SEARCH("Python",K39)),1,0)) -> 0 | Q39: =IF(ISBLANK(K39),0,IF(ISNUMBER(SEARCH("PowerBI",K39)),1,0)) -> 0 | R39: =IF(ISBLANK(K39),0,IF(ISNUMBER(SEARCH("Tableau",K39)),1,0)) -> 0 | S39: =IF(ISBLANK(K39),0,IF(ISNUMBER(SEARCH("Excel",K39)),1,0)) -> 1 | T39: =IF(ISBLANK(K39),0,IF(ISNUMBER(SEARCH("Statistics",K39)),1,0)) -> 0 | U39: =IF(ISBLANK(K39),0,IF(ISNUMBER(SEARCH("AWS",K39)),1,0)) -> 0 | V39: =IF(ISBLANK(K39),0,IF(ISNUMBER(SEARCH("GCP",K39)),1,0)) -> 0 | W39: =IF(ISBLANK(K39),0,IF(ISNUMBER(SEARCH("NoSQL",K39)),1,0)) -> 0 | X39: =IF(ISBLANK(K39),0,IF(ISNUMBER(SEARCH("Data Modeling",K39)),1,0)) -> 0 | Y39: =IF(ISBLANK(K39),0,IF(ISNUMBER(SEARCH("Pandas",K39)),1,0)) -> 0 | Z39: =IF(ISBLANK(K39),0,IF(ISNUMBER(SEARCH("Numpy",K39)),1,0)) -> 0 | AA39: =IF(ISBLANK(K39),0,IF(ISNUMBER(SEARCH("Pyspark",K39)),1,0)) -> 0 | AB39: =IF(ISBLANK(K39),0,IF(ISNUMBER(SEARCH("Hadoop",K39)),1,0)) -> 0 | AC39: =IF(ISBLANK(K39),0,IF(ISNUMBER(SEARCH("ETL",K39)),1,0)) -> 0 | AD39: =IF(ISBLANK(K39),0,IF(ISNUMBER(SEARCH("Azure",K39)),1,0)) -> 0 | AE39: =IF(ISBLANK(K39),0,IF(ISNUMBER(SEARCH("Databricks",K39)),1,0)) -> 0 | AF39: =IF(ISBLANK(K39),0,IF(ISNUMBER(SEARCH("A/B Testing",K39)),1,0)) -> 0 | AG39: =IF(ISBLANK(K39),0,IF(ISNUMBER(SEARCH("Snowflake",K39)),1,0)) -> 0 | AH39: =IF(ISBLANK(K39),0,IF(ISNUMBER(SEARCH("Agile",K39)),1,0)) -> 0 | AI39: =IF(ISBLANK(K39),0,IF(ISNUMBER(SEARCH("Jira",K39)),1,0)) -> 0 | AJ39: =IF(ISBLANK(K39),0,IF(ISNUMBER(SEARCH("Git",K39)),1,0)) -> 0 | AK39: =IF(ISBLANK(K39),0,IF(ISNUMBER(SEARCH("Reporting",K39)),1,0)) -> 0 | AL39: =IF(ISBLANK(K39),0,IF(ISNUMBER(SEARCH("CI/CD",K39)),1,0)) -> 0 | AM39: =IF(ISBLANK(L39),0,IF(ISNUMBER(SEARCH("Python",L39)),1,0)) -> 0 | AN39: =IF(ISBLANK(L39),0,IF(ISNUMBER(SEARCH("SQL",L39)),1,0)) -> 0 | AO39: =IF(ISBLANK(L39),0,IF(ISNUMBER(SEARCH("Airflow",L39)),1,0)) -> 0 | AP39: =IF(ISBLANK(L39),0,IF(ISNUMBER(SEARCH("Kafka",L39)),1,0)) -> 0 | AQ39: =IF(ISBLANK(L39),0,IF(ISNUMBER(SEARCH("ML",L39)),1,0)) -> 0 | AR39: =IF(ISBLANK(L40),0,IF(ISNUMBER(SEARCH("ML",L40)),1,0)) -> 0 | AS39: =IF(ISBLANK(L41),0,IF(ISNUMBER(SEARCH("Docker",L41)),1,0)) -> 0 | AT39: =IF(ISBLANK(L41),0,IF(ISNUMBER(SEARCH("dbt",L41)),1,0)) -> 0 | AU39: =IF(ISBLANK(L41),0,IF(ISNUMBER(SEARCH("AWS",L41)),1,0)) -> 0 | AV39: =IF(ISBLANK(L41),0,IF(ISNUMBER(SEARCH("GCP",L41)),1,0)) -> 0 | AW39: =IF(ISBLANK(L41),0,IF(ISNUMBER(SEARCH("Azure",L41)),1,0)) -> 0 | AX39: =IF(ISBLANK(M41),0,IF(ISNUMBER(SEARCH("Tableau",L41)),1,0)) -> 0 | AY39: =IF(ISBLANK(N41),0,IF(ISNUMBER(SEARCH("PowerBI",L41)),1,0)) -> 0 | AZ39: Fulltime
A40: 39 | B40: 46178 | C40: LinkedIn | D40: Business Analyst | E40: GIVA | F40: Bengaluru | G40: 2 | H40: 5 | I40: ND | J40: ND | K40: SQL, Advanced Excel | L40: Python, VBA, Google Bigquery | M40: On-site | N40: Medium | O40: =IF(ISBLANK(K40),0,IF(ISNUMBER(SEARCH("sql",K40)),1,0)) -> 1 | P40: =IF(ISBLANK(K40),0,IF(ISNUMBER(SEARCH("Python",K40)),1,0)) -> 0 | Q40: =IF(ISBLANK(K40),0,IF(ISNUMBER(SEARCH("PowerBI",K40)),1,0)) -> 0 | R40: =IF(ISBLANK(K40),0,IF(ISNUMBER(SEARCH("Tableau",K40)),1,0)) -> 0 | S40: =IF(ISBLANK(K40),0,IF(ISNUMBER(SEARCH("Excel",K40)),1,0)) -> 1 | T40: =IF(ISBLANK(K40),0,IF(ISNUMBER(SEARCH("Statistics",K40)),1,0)) -> 0 | U40: =IF(ISBLANK(K40),0,IF(ISNUMBER(SEARCH("AWS",K40)),1,0)) -> 0 | V40: =IF(ISBLANK(K40),0,IF(ISNUMBER(SEARCH("GCP",K40)),1,0)) -> 0 | W40: =IF(ISBLANK(K40),0,IF(ISNUMBER(SEARCH("NoSQL",K40)),1,0)) -> 0 | X40: =IF(ISBLANK(K40),0,IF(ISNUMBER(SEARCH("Data Modeling",K40)),1,0)) -> 0 | Y40: =IF(ISBLANK(K40),0,IF(ISNUMBER(SEARCH("Pandas",K40)),1,0)) -> 0 | Z40: =IF(ISBLANK(K40),0,IF(ISNUMBER(SEARCH("Numpy",K40)),1,0)) -> 0 | AA40: =IF(ISBLANK(K40),0,IF(ISNUMBER(SEARCH("Pyspark",K40)),1,0)) -> 0 | AB40: =IF(ISBLANK(K40),0,IF(ISNUMBER(SEARCH("Hadoop",K40)),1,0)) -> 0 | AC40: =IF(ISBLANK(K40),0,IF(ISNUMBER(SEARCH("ETL",K40)),1,0)) -> 0 | AD40: =IF(ISBLANK(K40),0,IF(ISNUMBER(SEARCH("Azure",K40)),1,0)) -> 0 | AE40: =IF(ISBLANK(K40),0,IF(ISNUMBER(SEARCH("Databricks",K40)),1,0)) -> 0 | AF40: =IF(ISBLANK(K40),0,IF(ISNUMBER(SEARCH("A/B Testing",K40)),1,0)) -> 0 | AG40: =IF(ISBLANK(K40),0,IF(ISNUMBER(SEARCH("Snowflake",K40)),1,0)) -> 0 | AH40: =IF(ISBLANK(K40),0,IF(ISNUMBER(SEARCH("Agile",K40)),1,0)) -> 0 | AI40: =IF(ISBLANK(K40),0,IF(ISNUMBER(SEARCH("Jira",K40)),1,0)) -> 0 | AJ40: =IF(ISBLANK(K40),0,IF(ISNUMBER(SEARCH("Git",K40)),1,0)) -> 0 | AK40: =IF(ISBLANK(K40),0,IF(ISNUMBER(SEARCH("Reporting",K40)),1,0)) -> 0 | AL40: =IF(ISBLANK(K40),0,IF(ISNUMBER(SEARCH("CI/CD",K40)),1,0)) -> 0 | AM40: =IF(ISBLANK(L40),0,IF(ISNUMBER(SEARCH("Python",L40)),1,0)) -> 1 | AN40: =IF(ISBLANK(L40),0,IF(ISNUMBER(SEARCH("SQL",L40)),1,0)) -> 0 | AO40: =IF(ISBLANK(L40),0,IF(ISNUMBER(SEARCH("Airflow",L40)),1,0)) -> 0 | AP40: =IF(ISBLANK(L40),0,IF(ISNUMBER(SEARCH("Kafka",L40)),1,0)) -> 0 | AQ40: =IF(ISBLANK(L40),0,IF(ISNUMBER(SEARCH("ML",L40)),1,0)) -> 0 | AR40: =IF(ISBLANK(L41),0,IF(ISNUMBER(SEARCH("ML",L41)),1,0)) -> 0 | AS40: =IF(ISBLANK(L42),0,IF(ISNUMBER(SEARCH("Docker",L42)),1,0)) -> 0 | AT40: =IF(ISBLANK(L42),0,IF(ISNUMBER(SEARCH("dbt",L42)),1,0)) -> 0 | AU40: =IF(ISBLANK(L42),0,IF(ISNUMBER(SEARCH("AWS",L42)),1,0)) -> 0 | AV40: =IF(ISBLANK(L42),0,IF(ISNUMBER(SEARCH("GCP",L42)),1,0)) -> 0 | AW40: =IF(ISBLANK(L42),0,IF(ISNUMBER(SEARCH("Azure",L42)),1,0)) -> 0 | AX40: =IF(ISBLANK(M42),0,IF(ISNUMBER(SEARCH("Tableau",L42)),1,0)) -> 0 | AY40: =IF(ISBLANK(N42),0,IF(ISNUMBER(SEARCH("PowerBI",L42)),1,0)) -> 0 | AZ40: Fulltime
A41: 40 | B41: 46178 | C41: LinkedIn | D41: Business Analyst | E41: Livespace | F41: Bengaluru | G41: 2 | H41: 4 | I41: ND | J41: ND | K41: Excel , SQL | L41: None | M41: On-site | N41: Medium | O41: =IF(ISBLANK(K41),0,IF(ISNUMBER(SEARCH("sql",K41)),1,0)) -> 1 | P41: =IF(ISBLANK(K41),0,IF(ISNUMBER(SEARCH("Python",K41)),1,0)) -> 0 | Q41: =IF(ISBLANK(K41),0,IF(ISNUMBER(SEARCH("PowerBI",K41)),1,0)) -> 0 | R41: =IF(ISBLANK(K41),0,IF(ISNUMBER(SEARCH("Tableau",K41)),1,0)) -> 0 | S41: =IF(ISBLANK(K41),0,IF(ISNUMBER(SEARCH("Excel",K41)),1,0)) -> 1 | T41: =IF(ISBLANK(K41),0,IF(ISNUMBER(SEARCH("Statistics",K41)),1,0)) -> 0 | U41: =IF(ISBLANK(K41),0,IF(ISNUMBER(SEARCH("AWS",K41)),1,0)) -> 0 | V41: =IF(ISBLANK(K41),0,IF(ISNUMBER(SEARCH("GCP",K41)),1,0)) -> 0 | W41: =IF(ISBLANK(K41),0,IF(ISNUMBER(SEARCH("NoSQL",K41)),1,0)) -> 0 | X41: =IF(ISBLANK(K41),0,IF(ISNUMBER(SEARCH("Data Modeling",K41)),1,0)) -> 0 | Y41: =IF(ISBLANK(K41),0,IF(ISNUMBER(SEARCH("Pandas",K41)),1,0)) -> 0 | Z41: =IF(ISBLANK(K41),0,IF(ISNUMBER(SEARCH("Numpy",K41)),1,0)) -> 0 | AA41: =IF(ISBLANK(K41),0,IF(ISNUMBER(SEARCH("Pyspark",K41)),1,0)) -> 0 | AB41: =IF(ISBLANK(K41),0,IF(ISNUMBER(SEARCH("Hadoop",K41)),1,0)) -> 0 | AC41: =IF(ISBLANK(K41),0,IF(ISNUMBER(SEARCH("ETL",K41)),1,0)) -> 0 | AD41: =IF(ISBLANK(K41),0,IF(ISNUMBER(SEARCH("Azure",K41)),1,0)) -> 0 | AE41: =IF(ISBLANK(K41),0,IF(ISNUMBER(SEARCH("Databricks",K41)),1,0)) -> 0 | AF41: =IF(ISBLANK(K41),0,IF(ISNUMBER(SEARCH("A/B Testing",K41)),1,0)) -> 0 | AG41: =IF(ISBLANK(K41),0,IF(ISNUMBER(SEARCH("Snowflake",K41)),1,0)) -> 0 | AH41: =IF(ISBLANK(K41),0,IF(ISNUMBER(SEARCH("Agile",K41)),1,0)) -> 0 | AI41: =IF(ISBLANK(K41),0,IF(ISNUMBER(SEARCH("Jira",K41)),1,0)) -> 0 | AJ41: =IF(ISBLANK(K41),0,IF(ISNUMBER(SEARCH("Git",K41)),1,0)) -> 0 | AK41: =IF(ISBLANK(K41),0,IF(ISNUMBER(SEARCH("Reporting",K41)),1,0)) -> 0 | AL41: =IF(ISBLANK(K41),0,IF(ISNUMBER(SEARCH("CI/CD",K41)),1,0)) -> 0 | AM41: =IF(ISBLANK(L41),0,IF(ISNUMBER(SEARCH("Python",L41)),1,0)) -> 0 | AN41: =IF(ISBLANK(L41),0,IF(ISNUMBER(SEARCH("SQL",L41)),1,0)) -> 0 | AO41: =IF(ISBLANK(L41),0,IF(ISNUMBER(SEARCH("Airflow",L41)),1,0)) -> 0 | AP41: =IF(ISBLANK(L41),0,IF(ISNUMBER(SEARCH("Kafka",L41)),1,0)) -> 0 | AQ41: =IF(ISBLANK(L41),0,IF(ISNUMBER(SEARCH("ML",L41)),1,0)) -> 0 | AR41: =IF(ISBLANK(L42),0,IF(ISNUMBER(SEARCH("ML",L42)),1,0)) -> 0 | AS41: =IF(ISBLANK(L43),0,IF(ISNUMBER(SEARCH("Docker",L43)),1,0)) -> 0 | AT41: =IF(ISBLANK(L43),0,IF(ISNUMBER(SEARCH("dbt",L43)),1,0)) -> 0 | AU41: =IF(ISBLANK(L43),0,IF(ISNUMBER(SEARCH("AWS",L43)),1,0)) -> 0 | AV41: =IF(ISBLANK(L43),0,IF(ISNUMBER(SEARCH("GCP",L43)),1,0)) -> 0 | AW41: =IF(ISBLANK(L43),0,IF(ISNUMBER(SEARCH("Azure",L43)),1,0)) -> 0 | AX41: =IF(ISBLANK(M43),0,IF(ISNUMBER(SEARCH("Tableau",L43)),1,0)) -> 0 | AY41: =IF(ISBLANK(N43),0,IF(ISNUMBER(SEARCH("PowerBI",L43)),1,0)) -> 0 | AZ41: Fulltime
A42: 41 | B42: 46178 | C42: LinkedIn | D42: Business Analyst | E42: Meesho | F42: Bengaluru | G42: 2 | H42: ND | I42: ND | J42: ND | K42: SQL , Python | L42: None | M42: On-site | N42: Large | O42: =IF(ISBLANK(K42),0,IF(ISNUMBER(SEARCH("sql",K42)),1,0)) -> 1 | P42: =IF(ISBLANK(K42),0,IF(ISNUMBER(SEARCH("Python",K42)),1,0)) -> 1 | Q42: =IF(ISBLANK(K42),0,IF(ISNUMBER(SEARCH("PowerBI",K42)),1,0)) -> 0 | R42: =IF(ISBLANK(K42),0,IF(ISNUMBER(SEARCH("Tableau",K42)),1,0)) -> 0 | S42: =IF(ISBLANK(K42),0,IF(ISNUMBER(SEARCH("Excel",K42)),1,0)) -> 0 | T42: =IF(ISBLANK(K42),0,IF(ISNUMBER(SEARCH("Statistics",K42)),1,0)) -> 0 | U42: =IF(ISBLANK(K42),0,IF(ISNUMBER(SEARCH("AWS",K42)),1,0)) -> 0 | V42: =IF(ISBLANK(K42),0,IF(ISNUMBER(SEARCH("GCP",K42)),1,0)) -> 0 | W42: =IF(ISBLANK(K42),0,IF(ISNUMBER(SEARCH("NoSQL",K42)),1,0)) -> 0 | X42: =IF(ISBLANK(K42),0,IF(ISNUMBER(SEARCH("Data Modeling",K42)),1,0)) -> 0 | Y42: =IF(ISBLANK(K42),0,IF(ISNUMBER(SEARCH("Pandas",K42)),1,0)) -> 0 | Z42: =IF(ISBLANK(K42),0,IF(ISNUMBER(SEARCH("Numpy",K42)),1,0)) -> 0 | AA42: =IF(ISBLANK(K42),0,IF(ISNUMBER(SEARCH("Pyspark",K42)),1,0)) -> 0 | AB42: =IF(ISBLANK(K42),0,IF(ISNUMBER(SEARCH("Hadoop",K42)),1,0)) -> 0 | AC42: =IF(ISBLANK(K42),0,IF(ISNUMBER(SEARCH("ETL",K42)),1,0)) -> 0 | AD42: =IF(ISBLANK(K42),0,IF(ISNUMBER(SEARCH("Azure",K42)),1,0)) -> 0 | AE42: =IF(ISBLANK(K42),0,IF(ISNUMBER(SEARCH("Databricks",K42)),1,0)) -> 0 | AF42: =IF(ISBLANK(K42),0,IF(ISNUMBER(SEARCH("A/B Testing",K42)),1,0)) -> 0 | AG42: =IF(ISBLANK(K42),0,IF(ISNUMBER(SEARCH("Snowflake",K42)),1,0)) -> 0 | AH42: =IF(ISBLANK(K42),0,IF(ISNUMBER(SEARCH("Agile",K42)),1,0)) -> 0 | AI42: =IF(ISBLANK(K42),0,IF(ISNUMBER(SEARCH("Jira",K42)),1,0)) -> 0 | AJ42: =IF(ISBLANK(K42),0,IF(ISNUMBER(SEARCH("Git",K42)),1,0)) -> 0 | AK42: =IF(ISBLANK(K42),0,IF(ISNUMBER(SEARCH("Reporting",K42)),1,0)) -> 0 | AL42: =IF(ISBLANK(K42),0,IF(ISNUMBER(SEARCH("CI/CD",K42)),1,0)) -> 0 | AM42: =IF(ISBLANK(L42),0,IF(ISNUMBER(SEARCH("Python",L42)),1,0)) -> 0 | AN42: =IF(ISBLANK(L42),0,IF(ISNUMBER(SEARCH("SQL",L42)),1,0)) -> 0 | AO42: =IF(ISBLANK(L42),0,IF(ISNUMBER(SEARCH("Airflow",L42)),1,0)) -> 0 | AP42: =IF(ISBLANK(L42),0,IF(ISNUMBER(SEARCH("Kafka",L42)),1,0)) -> 0 | AQ42: =IF(ISBLANK(L42),0,IF(ISNUMBER(SEARCH("ML",L42)),1,0)) -> 0 | AR42: =IF(ISBLANK(L43),0,IF(ISNUMBER(SEARCH("ML",L43)),1,0)) -> 0 | AS42: =IF(ISBLANK(L44),0,IF(ISNUMBER(SEARCH("Docker",L44)),1,0)) -> 0 | AT42: =IF(ISBLANK(L44),0,IF(ISNUMBER(SEARCH("dbt",L44)),1,0)) -> 0 | AU42: =IF(ISBLANK(L44),0,IF(ISNUMBER(SEARCH("AWS",L44)),1,0)) -> 0 | AV42: =IF(ISBLANK(L44),0,IF(ISNUMBER(SEARCH("GCP",L44)),1,0)) -> 0 | AW42: =IF(ISBLANK(L44),0,IF(ISNUMBER(SEARCH("Azure",L44)),1,0)) -> 0 | AX42: =IF(ISBLANK(M44),0,IF(ISNUMBER(SEARCH("Tableau",L44)),1,0)) -> 0 | AY42: =IF(ISBLANK(N44),0,IF(ISNUMBER(SEARCH("PowerBI",L44)),1,0)) -> 0 | AZ42: Fulltime
A43: 42 | B43: 46178 | C43: LinkedIn | D43: Business Analyst | E43: Onit India | F43: Pune | G43: 3 | H43: ND | I43: ND | J43: ND | K43: RDMS, SaaS | L43: None | M43: On-site | N43: Large | O43: =IF(ISBLANK(K43),0,IF(ISNUMBER(SEARCH("sql",K43)),1,0)) -> 0 | P43: =IF(ISBLANK(K43),0,IF(ISNUMBER(SEARCH("Python",K43)),1,0)) -> 0 | Q43: =IF(ISBLANK(K43),0,IF(ISNUMBER(SEARCH("PowerBI",K43)),1,0)) -> 0 | R43: =IF(ISBLANK(K43),0,IF(ISNUMBER(SEARCH("Tableau",K43)),1,0)) -> 0 | S43: =IF(ISBLANK(K43),0,IF(ISNUMBER(SEARCH("Excel",K43)),1,0)) -> 0 | T43: =IF(ISBLANK(K43),0,IF(ISNUMBER(SEARCH("Statistics",K43)),1,0)) -> 0 | U43: =IF(ISBLANK(K43),0,IF(ISNUMBER(SEARCH("AWS",K43)),1,0)) -> 0 | V43: =IF(ISBLANK(K43),0,IF(ISNUMBER(SEARCH("GCP",K43)),1,0)) -> 0 | W43: =IF(ISBLANK(K43),0,IF(ISNUMBER(SEARCH("NoSQL",K43)),1,0)) -> 0 | X43: =IF(ISBLANK(K43),0,IF(ISNUMBER(SEARCH("Data Modeling",K43)),1,0)) -> 0 | Y43: =IF(ISBLANK(K43),0,IF(ISNUMBER(SEARCH("Pandas",K43)),1,0)) -> 0 | Z43: =IF(ISBLANK(K43),0,IF(ISNUMBER(SEARCH("Numpy",K43)),1,0)) -> 0 | AA43: =IF(ISBLANK(K43),0,IF(ISNUMBER(SEARCH("Pyspark",K43)),1,0)) -> 0 | AB43: =IF(ISBLANK(K43),0,IF(ISNUMBER(SEARCH("Hadoop",K43)),1,0)) -> 0 | AC43: =IF(ISBLANK(K43),0,IF(ISNUMBER(SEARCH("ETL",K43)),1,0)) -> 0 | AD43: =IF(ISBLANK(K43),0,IF(ISNUMBER(SEARCH("Azure",K43)),1,0)) -> 0 | AE43: =IF(ISBLANK(K43),0,IF(ISNUMBER(SEARCH("Databricks",K43)),1,0)) -> 0 | AF43: =IF(ISBLANK(K43),0,IF(ISNUMBER(SEARCH("A/B Testing",K43)),1,0)) -> 0 | AG43: =IF(ISBLANK(K43),0,IF(ISNUMBER(SEARCH("Snowflake",K43)),1,0)) -> 0 | AH43: =IF(ISBLANK(K43),0,IF(ISNUMBER(SEARCH("Agile",K43)),1,0)) -> 0 | AI43: =IF(ISBLANK(K43),0,IF(ISNUMBER(SEARCH("Jira",K43)),1,0)) -> 0 | AJ43: =IF(ISBLANK(K43),0,IF(ISNUMBER(SEARCH("Git",K43)),1,0)) -> 0 | AK43: =IF(ISBLANK(K43),0,IF(ISNUMBER(SEARCH("Reporting",K43)),1,0)) -> 0 | AL43: =IF(ISBLANK(K43),0,IF(ISNUMBER(SEARCH("CI/CD",K43)),1,0)) -> 0 | AM43: =IF(ISBLANK(L43),0,IF(ISNUMBER(SEARCH("Python",L43)),1,0)) -> 0 | AN43: =IF(ISBLANK(L43),0,IF(ISNUMBER(SEARCH("SQL",L43)),1,0)) -> 0 | AO43: =IF(ISBLANK(L43),0,IF(ISNUMBER(SEARCH("Airflow",L43)),1,0)) -> 0 | AP43: =IF(ISBLANK(L43),0,IF(ISNUMBER(SEARCH("Kafka",L43)),1,0)) -> 0 | AQ43: =IF(ISBLANK(L43),0,IF(ISNUMBER(SEARCH("ML",L43)),1,0)) -> 0 | AR43: =IF(ISBLANK(L44),0,IF(ISNUMBER(SEARCH("ML",L44)),1,0)) -> 0 | AS43: =IF(ISBLANK(L45),0,IF(ISNUMBER(SEARCH("Docker",L45)),1,0)) -> 0 | AT43: =IF(ISBLANK(L45),0,IF(ISNUMBER(SEARCH("dbt",L45)),1,0)) -> 0 | AU43: =IF(ISBLANK(L45),0,IF(ISNUMBER(SEARCH("AWS",L45)),1,0)) -> 0 | AV43: =IF(ISBLANK(L45),0,IF(ISNUMBER(SEARCH("GCP",L45)),1,0)) -> 0 | AW43: =IF(ISBLANK(L45),0,IF(ISNUMBER(SEARCH("Azure",L45)),1,0)) -> 0 | AX43: =IF(ISBLANK(M45),0,IF(ISNUMBER(SEARCH("Tableau",L45)),1,0)) -> 0 | AY43: =IF(ISBLANK(N45),0,IF(ISNUMBER(SEARCH("PowerBI",L45)),1,0)) -> 0 | AZ43: Fulltime
A44: 43 | B44: 46178 | C44: LinkedIn | D44: Business Analyst | E44: DriveX | F44: Bengaluru | G44: ND | H44: ND | I44: ND | J44: ND | K44: SQL , Excel Advanced, Reporting | L44: None | M44: On-site | N44: Medium | O44: =IF(ISBLANK(K44),0,IF(ISNUMBER(SEARCH("sql",K44)),1,0)) -> 1 | P44: =IF(ISBLANK(K44),0,IF(ISNUMBER(SEARCH("Python",K44)),1,0)) -> 0 | Q44: =IF(ISBLANK(K44),0,IF(ISNUMBER(SEARCH("PowerBI",K44)),1,0)) -> 0 | R44: =IF(ISBLANK(K44),0,IF(ISNUMBER(SEARCH("Tableau",K44)),1,0)) -> 0 | S44: =IF(ISBLANK(K44),0,IF(ISNUMBER(SEARCH("Excel",K44)),1,0)) -> 1 | T44: =IF(ISBLANK(K44),0,IF(ISNUMBER(SEARCH("Statistics",K44)),1,0)) -> 0 | U44: =IF(ISBLANK(K44),0,IF(ISNUMBER(SEARCH("AWS",K44)),1,0)) -> 0 | V44: =IF(ISBLANK(K44),0,IF(ISNUMBER(SEARCH("GCP",K44)),1,0)) -> 0 | W44: =IF(ISBLANK(K44),0,IF(ISNUMBER(SEARCH("NoSQL",K44)),1,0)) -> 0 | X44: =IF(ISBLANK(K44),0,IF(ISNUMBER(SEARCH("Data Modeling",K44)),1,0)) -> 0 | Y44: =IF(ISBLANK(K44),0,IF(ISNUMBER(SEARCH("Pandas",K44)),1,0)) -> 0 | Z44: =IF(ISBLANK(K44),0,IF(ISNUMBER(SEARCH("Numpy",K44)),1,0)) -> 0 | AA44: =IF(ISBLANK(K44),0,IF(ISNUMBER(SEARCH("Pyspark",K44)),1,0)) -> 0 | AB44: =IF(ISBLANK(K44),0,IF(ISNUMBER(SEARCH("Hadoop",K44)),1,0)) -> 0 | AC44: =IF(ISBLANK(K44),0,IF(ISNUMBER(SEARCH("ETL",K44)),1,0)) -> 0 | AD44: =IF(ISBLANK(K44),0,IF(ISNUMBER(SEARCH("Azure",K44)),1,0)) -> 0 | AE44: =IF(ISBLANK(K44),0,IF(ISNUMBER(SEARCH("Databricks",K44)),1,0)) -> 0 | AF44: =IF(ISBLANK(K44),0,IF(ISNUMBER(SEARCH("A/B Testing",K44)),1,0)) -> 0 | AG44: =IF(ISBLANK(K44),0,IF(ISNUMBER(SEARCH("Snowflake",K44)),1,0)) -> 0 | AH44: =IF(ISBLANK(K44),0,IF(ISNUMBER(SEARCH("Agile",K44)),1,0)) -> 0 | AI44: =IF(ISBLANK(K44),0,IF(ISNUMBER(SEARCH("Jira",K44)),1,0)) -> 0 | AJ44: =IF(ISBLANK(K44),0,IF(ISNUMBER(SEARCH("Git",K44)),1,0)) -> 0 | AK44: =IF(ISBLANK(K44),0,IF(ISNUMBER(SEARCH("Reporting",K44)),1,0)) -> 1 | AL44: =IF(ISBLANK(K44),0,IF(ISNUMBER(SEARCH("CI/CD",K44)),1,0)) -> 0 | AM44: =IF(ISBLANK(L44),0,IF(ISNUMBER(SEARCH("Python",L44)),1,0)) -> 0 | AN44: =IF(ISBLANK(L44),0,IF(ISNUMBER(SEARCH("SQL",L44)),1,0)) -> 0 | AO44: =IF(ISBLANK(L44),0,IF(ISNUMBER(SEARCH("Airflow",L44)),1,0)) -> 0 | AP44: =IF(ISBLANK(L44),0,IF(ISNUMBER(SEARCH("Kafka",L44)),1,0)) -> 0 | AQ44: =IF(ISBLANK(L44),0,IF(ISNUMBER(SEARCH("ML",L44)),1,0)) -> 0 | AR44: =IF(ISBLANK(L45),0,IF(ISNUMBER(SEARCH("ML",L45)),1,0)) -> 0 | AS44: =IF(ISBLANK(L46),0,IF(ISNUMBER(SEARCH("Docker",L46)),1,0)) -> 0 | AT44: =IF(ISBLANK(L46),0,IF(ISNUMBER(SEARCH("dbt",L46)),1,0)) -> 0 | AU44: =IF(ISBLANK(L46),0,IF(ISNUMBER(SEARCH("AWS",L46)),1,0)) -> 0 | AV44: =IF(ISBLANK(L46),0,IF(ISNUMBER(SEARCH("GCP",L46)),1,0)) -> 0 | AW44: =IF(ISBLANK(L46),0,IF(ISNUMBER(SEARCH("Azure",L46)),1,0)) -> 0 | AX44: =IF(ISBLANK(M46),0,IF(ISNUMBER(SEARCH("Tableau",L46)),1,0)) -> 0 | AY44: =IF(ISBLANK(N46),0,IF(ISNUMBER(SEARCH("PowerBI",L46)),1,0)) -> 0 | AZ44: Fulltime
A45: 44 | B45: 46178 | C45: LinkedIn | D45: Business Analyst | E45: ZopSmart | F45: Bengaluru | G45: 3 | H45: 4 | I45: ND | J45: ND | K45: Github, Documentation, Dashboarding , SEO practices | L45: None | M45: On-site | N45: Small | O45: =IF(ISBLANK(K45),0,IF(ISNUMBER(SEARCH("sql",K45)),1,0)) -> 0 | P45: =IF(ISBLANK(K45),0,IF(ISNUMBER(SEARCH("Python",K45)),1,0)) -> 0 | Q45: =IF(ISBLANK(K45),0,IF(ISNUMBER(SEARCH("PowerBI",K45)),1,0)) -> 0 | R45: =IF(ISBLANK(K45),0,IF(ISNUMBER(SEARCH("Tableau",K45)),1,0)) -> 0 | S45: =IF(ISBLANK(K45),0,IF(ISNUMBER(SEARCH("Excel",K45)),1,0)) -> 0 | T45: =IF(ISBLANK(K45),0,IF(ISNUMBER(SEARCH("Statistics",K45)),1,0)) -> 0 | U45: =IF(ISBLANK(K45),0,IF(ISNUMBER(SEARCH("AWS",K45)),1,0)) -> 0 | V45: =IF(ISBLANK(K45),0,IF(ISNUMBER(SEARCH("GCP",K45)),1,0)) -> 0 | W45: =IF(ISBLANK(K45),0,IF(ISNUMBER(SEARCH("NoSQL",K45)),1,0)) -> 0 | X45: =IF(ISBLANK(K45),0,IF(ISNUMBER(SEARCH("Data Modeling",K45)),1,0)) -> 0 | Y45: =IF(ISBLANK(K45),0,IF(ISNUMBER(SEARCH("Pandas",K45)),1,0)) -> 0 | Z45: =IF(ISBLANK(K45),0,IF(ISNUMBER(SEARCH("Numpy",K45)),1,0)) -> 0 | AA45: =IF(ISBLANK(K45),0,IF(ISNUMBER(SEARCH("Pyspark",K45)),1,0)) -> 0 | AB45: =IF(ISBLANK(K45),0,IF(ISNUMBER(SEARCH("Hadoop",K45)),1,0)) -> 0 | AC45: =IF(ISBLANK(K45),0,IF(ISNUMBER(SEARCH("ETL",K45)),1,0)) -> 0 | AD45: =IF(ISBLANK(K45),0,IF(ISNUMBER(SEARCH("Azure",K45)),1,0)) -> 0 | AE45: =IF(ISBLANK(K45),0,IF(ISNUMBER(SEARCH("Databricks",K45)),1,0)) -> 0 | AF45: =IF(ISBLANK(K45),0,IF(ISNUMBER(SEARCH("A/B Testing",K45)),1,0)) -> 0 | AG45: =IF(ISBLANK(K45),0,IF(ISNUMBER(SEARCH("Snowflake",K45)),1,0)) -> 0 | AH45: =IF(ISBLANK(K45),0,IF(ISNUMBER(SEARCH("Agile",K45)),1,0)) -> 0 | AI45: =IF(ISBLANK(K45),0,IF(ISNUMBER(SEARCH("Jira",K45)),1,0)) -> 0 | AJ45: =IF(ISBLANK(K45),0,IF(ISNUMBER(SEARCH("Git",K45)),1,0)) -> 1 | AK45: =IF(ISBLANK(K45),0,IF(ISNUMBER(SEARCH("Reporting",K45)),1,0)) -> 0 | AL45: =IF(ISBLANK(K45),0,IF(ISNUMBER(SEARCH("CI/CD",K45)),1,0)) -> 0 | AM45: =IF(ISBLANK(L45),0,IF(ISNUMBER(SEARCH("Python",L45)),1,0)) -> 0 | AN45: =IF(ISBLANK(L45),0,IF(ISNUMBER(SEARCH("SQL",L45)),1,0)) -> 0 | AO45: =IF(ISBLANK(L45),0,IF(ISNUMBER(SEARCH("Airflow",L45)),1,0)) -> 0 | AP45: =IF(ISBLANK(L45),0,IF(ISNUMBER(SEARCH("Kafka",L45)),1,0)) -> 0 | AQ45: =IF(ISBLANK(L45),0,IF(ISNUMBER(SEARCH("ML",L45)),1,0)) -> 0 | AR45: =IF(ISBLANK(L46),0,IF(ISNUMBER(SEARCH("ML",L46)),1,0)) -> 0 | AS45: =IF(ISBLANK(L47),0,IF(ISNUMBER(SEARCH("Docker",L47)),1,0)) -> 0 | AT45: =IF(ISBLANK(L47),0,IF(ISNUMBER(SEARCH("dbt",L47)),1,0)) -> 0 | AU45: =IF(ISBLANK(L47),0,IF(ISNUMBER(SEARCH("AWS",L47)),1,0)) -> 0 | AV45: =IF(ISBLANK(L47),0,IF(ISNUMBER(SEARCH("GCP",L47)),1,0)) -> 0 | AW45: =IF(ISBLANK(L47),0,IF(ISNUMBER(SEARCH("Azure",L47)),1,0)) -> 0 | AX45: =IF(ISBLANK(M47),0,IF(ISNUMBER(SEARCH("Tableau",L47)),1,0)) -> 0 | AY45: =IF(ISBLANK(N47),0,IF(ISNUMBER(SEARCH("PowerBI",L47)),1,0)) -> 0 | AZ45: Fulltime
A46: 45 | B46: 46178 | C46: LinkedIn | D46: Business Analyst | E46: IntouchCX | F46: Bengaluru | G46: 1 | H46: 3 | I46: ND | J46: ND | K46: Excel , CRM | L46: None | M46: On-site | N46: Small | O46: =IF(ISBLANK(K46),0,IF(ISNUMBER(SEARCH("sql",K46)),1,0)) -> 0 | P46: =IF(ISBLANK(K46),0,IF(ISNUMBER(SEARCH("Python",K46)),1,0)) -> 0 | Q46: =IF(ISBLANK(K46),0,IF(ISNUMBER(SEARCH("PowerBI",K46)),1,0)) -> 0 | R46: =IF(ISBLANK(K46),0,IF(ISNUMBER(SEARCH("Tableau",K46)),1,0)) -> 0 | S46: =IF(ISBLANK(K46),0,IF(ISNUMBER(SEARCH("Excel",K46)),1,0)) -> 1 | T46: =IF(ISBLANK(K46),0,IF(ISNUMBER(SEARCH("Statistics",K46)),1,0)) -> 0 | U46: =IF(ISBLANK(K46),0,IF(ISNUMBER(SEARCH("AWS",K46)),1,0)) -> 0 | V46: =IF(ISBLANK(K46),0,IF(ISNUMBER(SEARCH("GCP",K46)),1,0)) -> 0 | W46: =IF(ISBLANK(K46),0,IF(ISNUMBER(SEARCH("NoSQL",K46)),1,0)) -> 0 | X46: =IF(ISBLANK(K46),0,IF(ISNUMBER(SEARCH("Data Modeling",K46)),1,0)) -> 0 | Y46: =IF(ISBLANK(K46),0,IF(ISNUMBER(SEARCH("Pandas",K46)),1,0)) -> 0 | Z46: =IF(ISBLANK(K46),0,IF(ISNUMBER(SEARCH("Numpy",K46)),1,0)) -> 0 | AA46: =IF(ISBLANK(K46),0,IF(ISNUMBER(SEARCH("Pyspark",K46)),1,0)) -> 0 | AB46: =IF(ISBLANK(K46),0,IF(ISNUMBER(SEARCH("Hadoop",K46)),1,0)) -> 0 | AC46: =IF(ISBLANK(K46),0,IF(ISNUMBER(SEARCH("ETL",K46)),1,0)) -> 0 | AD46: =IF(ISBLANK(K46),0,IF(ISNUMBER(SEARCH("Azure",K46)),1,0)) -> 0 | AE46: =IF(ISBLANK(K46),0,IF(ISNUMBER(SEARCH("Databricks",K46)),1,0)) -> 0 | AF46: =IF(ISBLANK(K46),0,IF(ISNUMBER(SEARCH("A/B Testing",K46)),1,0)) -> 0 | AG46: =IF(ISBLANK(K46),0,IF(ISNUMBER(SEARCH("Snowflake",K46)),1,0)) -> 0 | AH46: =IF(ISBLANK(K46),0,IF(ISNUMBER(SEARCH("Agile",K46)),1,0)) -> 0 | AI46: =IF(ISBLANK(K46),0,IF(ISNUMBER(SEARCH("Jira",K46)),1,0)) -> 0 | AJ46: =IF(ISBLANK(K46),0,IF(ISNUMBER(SEARCH("Git",K46)),1,0)) -> 0 | AK46: =IF(ISBLANK(K46),0,IF(ISNUMBER(SEARCH("Reporting",K46)),1,0)) -> 0 | AL46: =IF(ISBLANK(K46),0,IF(ISNUMBER(SEARCH("CI/CD",K46)),1,0)) -> 0 | AM46: =IF(ISBLANK(L46),0,IF(ISNUMBER(SEARCH("Python",L46)),1,0)) -> 0 | AN46: =IF(ISBLANK(L46),0,IF(ISNUMBER(SEARCH("SQL",L46)),1,0)) -> 0 | AO46: =IF(ISBLANK(L46),0,IF(ISNUMBER(SEARCH("Airflow",L46)),1,0)) -> 0 | AP46: =IF(ISBLANK(L46),0,IF(ISNUMBER(SEARCH("Kafka",L46)),1,0)) -> 0 | AQ46: =IF(ISBLANK(L46),0,IF(ISNUMBER(SEARCH("ML",L46)),1,0)) -> 0 | AR46: =IF(ISBLANK(L47),0,IF(ISNUMBER(SEARCH("ML",L47)),1,0)) -> 0 | AS46: =IF(ISBLANK(L48),0,IF(ISNUMBER(SEARCH("Docker",L48)),1,0)) -> 0 | AT46: =IF(ISBLANK(L48),0,IF(ISNUMBER(SEARCH("dbt",L48)),1,0)) -> 0 | AU46: =IF(ISBLANK(L48),0,IF(ISNUMBER(SEARCH("AWS",L48)),1,0)) -> 0 | AV46: =IF(ISBLANK(L48),0,IF(ISNUMBER(SEARCH("GCP",L48)),1,0)) -> 0 | AW46: =IF(ISBLANK(L48),0,IF(ISNUMBER(SEARCH("Azure",L48)),1,0)) -> 0 | AX46: =IF(ISBLANK(M48),0,IF(ISNUMBER(SEARCH("Tableau",L48)),1,0)) -> 0 | AY46: =IF(ISBLANK(N48),0,IF(ISNUMBER(SEARCH("PowerBI",L48)),1,0)) -> 0 | AZ46: Fulltime
A47: 46 | B47: 46178 | C47: LinkedIn | D47: Business Analyst | E47: BNB Paribas | F47: Bengaluru | G47: ND | H47: ND | I47: ND | J47: ND | K47: SQL,Jira , BDD test case drafting | L47: None | M47: On-site | N47: Medium | O47: =IF(ISBLANK(K47),0,IF(ISNUMBER(SEARCH("sql",K47)),1,0)) -> 1 | P47: =IF(ISBLANK(K47),0,IF(ISNUMBER(SEARCH("Python",K47)),1,0)) -> 0 | Q47: =IF(ISBLANK(K47),0,IF(ISNUMBER(SEARCH("PowerBI",K47)),1,0)) -> 0 | R47: =IF(ISBLANK(K47),0,IF(ISNUMBER(SEARCH("Tableau",K47)),1,0)) -> 0 | S47: =IF(ISBLANK(K47),0,IF(ISNUMBER(SEARCH("Excel",K47)),1,0)) -> 0 | T47: =IF(ISBLANK(K47),0,IF(ISNUMBER(SEARCH("Statistics",K47)),1,0)) -> 0 | U47: =IF(ISBLANK(K47),0,IF(ISNUMBER(SEARCH("AWS",K47)),1,0)) -> 0 | V47: =IF(ISBLANK(K47),0,IF(ISNUMBER(SEARCH("GCP",K47)),1,0)) -> 0 | W47: =IF(ISBLANK(K47),0,IF(ISNUMBER(SEARCH("NoSQL",K47)),1,0)) -> 0 | X47: =IF(ISBLANK(K47),0,IF(ISNUMBER(SEARCH("Data Modeling",K47)),1,0)) -> 0 | Y47: =IF(ISBLANK(K47),0,IF(ISNUMBER(SEARCH("Pandas",K47)),1,0)) -> 0 | Z47: =IF(ISBLANK(K47),0,IF(ISNUMBER(SEARCH("Numpy",K47)),1,0)) -> 0 | AA47: =IF(ISBLANK(K47),0,IF(ISNUMBER(SEARCH("Pyspark",K47)),1,0)) -> 0 | AB47: =IF(ISBLANK(K47),0,IF(ISNUMBER(SEARCH("Hadoop",K47)),1,0)) -> 0 | AC47: =IF(ISBLANK(K47),0,IF(ISNUMBER(SEARCH("ETL",K47)),1,0)) -> 0 | AD47: =IF(ISBLANK(K47),0,IF(ISNUMBER(SEARCH("Azure",K47)),1,0)) -> 0 | AE47: =IF(ISBLANK(K47),0,IF(ISNUMBER(SEARCH("Databricks",K47)),1,0)) -> 0 | AF47: =IF(ISBLANK(K47),0,IF(ISNUMBER(SEARCH("A/B Testing",K47)),1,0)) -> 0 | AG47: =IF(ISBLANK(K47),0,IF(ISNUMBER(SEARCH("Snowflake",K47)),1,0)) -> 0 | AH47: =IF(ISBLANK(K47),0,IF(ISNUMBER(SEARCH("Agile",K47)),1,0)) -> 0 | AI47: =IF(ISBLANK(K47),0,IF(ISNUMBER(SEARCH("Jira",K47)),1,0)) -> 1 | AJ47: =IF(ISBLANK(K47),0,IF(ISNUMBER(SEARCH("Git",K47)),1,0)) -> 0 | AK47: =IF(ISBLANK(K47),0,IF(ISNUMBER(SEARCH("Reporting",K47)),1,0)) -> 0 | AL47: =IF(ISBLANK(K47),0,IF(ISNUMBER(SEARCH("CI/CD",K47)),1,0)) -> 0 | AM47: =IF(ISBLANK(L47),0,IF(ISNUMBER(SEARCH("Python",L47)),1,0)) -> 0 | AN47: =IF(ISBLANK(L47),0,IF(ISNUMBER(SEARCH("SQL",L47)),1,0)) -> 0 | AO47: =IF(ISBLANK(L47),0,IF(ISNUMBER(SEARCH("Airflow",L47)),1,0)) -> 0 | AP47: =IF(ISBLANK(L47),0,IF(ISNUMBER(SEARCH("Kafka",L47)),1,0)) -> 0 | AQ47: =IF(ISBLANK(L47),0,IF(ISNUMBER(SEARCH("ML",L47)),1,0)) -> 0 | AR47: =IF(ISBLANK(L48),0,IF(ISNUMBER(SEARCH("ML",L48)),1,0)) -> 0 | AS47: =IF(ISBLANK(L49),0,IF(ISNUMBER(SEARCH("Docker",L49)),1,0)) -> 0 | AT47: =IF(ISBLANK(L49),0,IF(ISNUMBER(SEARCH("dbt",L49)),1,0)) -> 0 | AU47: =IF(ISBLANK(L49),0,IF(ISNUMBER(SEARCH("AWS",L49)),1,0)) -> 0 | AV47: =IF(ISBLANK(L49),0,IF(ISNUMBER(SEARCH("GCP",L49)),1,0)) -> 0 | AW47: =IF(ISBLANK(L49),0,IF(ISNUMBER(SEARCH("Azure",L49)),1,0)) -> 0 | AX47: =IF(ISBLANK(M49),0,IF(ISNUMBER(SEARCH("Tableau",L49)),1,0)) -> 0 | AY47: =IF(ISBLANK(N49),0,IF(ISNUMBER(SEARCH("PowerBI",L49)),1,0)) -> 0 | AZ47: Fulltime
A48: 47 | B48: 46178 | C48: LinkedIn | D48: Business Analyst | E48: Macquaire Group | F48: Hyderabad | G48: 1 | H48: 5 | I48: ND | J48: ND | K48: Scrum , Kanban , Finance Knowledge | L48: None | M48: On-site | N48: Medium | O48: =IF(ISBLANK(K48),0,IF(ISNUMBER(SEARCH("sql",K48)),1,0)) -> 0 | P48: =IF(ISBLANK(K48),0,IF(ISNUMBER(SEARCH("Python",K48)),1,0)) -> 0 | Q48: =IF(ISBLANK(K48),0,IF(ISNUMBER(SEARCH("PowerBI",K48)),1,0)) -> 0 | R48: =IF(ISBLANK(K48),0,IF(ISNUMBER(SEARCH("Tableau",K48)),1,0)) -> 0 | S48: =IF(ISBLANK(K48),0,IF(ISNUMBER(SEARCH("Excel",K48)),1,0)) -> 0 | T48: =IF(ISBLANK(K48),0,IF(ISNUMBER(SEARCH("Statistics",K48)),1,0)) -> 0 | U48: =IF(ISBLANK(K48),0,IF(ISNUMBER(SEARCH("AWS",K48)),1,0)) -> 0 | V48: =IF(ISBLANK(K48),0,IF(ISNUMBER(SEARCH("GCP",K48)),1,0)) -> 0 | W48: =IF(ISBLANK(K48),0,IF(ISNUMBER(SEARCH("NoSQL",K48)),1,0)) -> 0 | X48: =IF(ISBLANK(K48),0,IF(ISNUMBER(SEARCH("Data Modeling",K48)),1,0)) -> 0 | Y48: =IF(ISBLANK(K48),0,IF(ISNUMBER(SEARCH("Pandas",K48)),1,0)) -> 0 | Z48: =IF(ISBLANK(K48),0,IF(ISNUMBER(SEARCH("Numpy",K48)),1,0)) -> 0 | AA48: =IF(ISBLANK(K48),0,IF(ISNUMBER(SEARCH("Pyspark",K48)),1,0)) -> 0 | AB48: =IF(ISBLANK(K48),0,IF(ISNUMBER(SEARCH("Hadoop",K48)),1,0)) -> 0 | AC48: =IF(ISBLANK(K48),0,IF(ISNUMBER(SEARCH("ETL",K48)),1,0)) -> 0 | AD48: =IF(ISBLANK(K48),0,IF(ISNUMBER(SEARCH("Azure",K48)),1,0)) -> 0 | AE48: =IF(ISBLANK(K48),0,IF(ISNUMBER(SEARCH("Databricks",K48)),1,0)) -> 0 | AF48: =IF(ISBLANK(K48),0,IF(ISNUMBER(SEARCH("A/B Testing",K48)),1,0)) -> 0 | AG48: =IF(ISBLANK(K48),0,IF(ISNUMBER(SEARCH("Snowflake",K48)),1,0)) -> 0 | AH48: =IF(ISBLANK(K48),0,IF(ISNUMBER(SEARCH("Agile",K48)),1,0)) -> 0 | AI48: =IF(ISBLANK(K48),0,IF(ISNUMBER(SEARCH("Jira",K48)),1,0)) -> 0 | AJ48: =IF(ISBLANK(K48),0,IF(ISNUMBER(SEARCH("Git",K48)),1,0)) -> 0 | AK48: =IF(ISBLANK(K48),0,IF(ISNUMBER(SEARCH("Reporting",K48)),1,0)) -> 0 | AL48: =IF(ISBLANK(K48),0,IF(ISNUMBER(SEARCH("CI/CD",K48)),1,0)) -> 0 | AM48: =IF(ISBLANK(L48),0,IF(ISNUMBER(SEARCH("Python",L48)),1,0)) -> 0 | AN48: =IF(ISBLANK(L48),0,IF(ISNUMBER(SEARCH("SQL",L48)),1,0)) -> 0 | AO48: =IF(ISBLANK(L48),0,IF(ISNUMBER(SEARCH("Airflow",L48)),1,0)) -> 0 | AP48: =IF(ISBLANK(L48),0,IF(ISNUMBER(SEARCH("Kafka",L48)),1,0)) -> 0 | AQ48: =IF(ISBLANK(L48),0,IF(ISNUMBER(SEARCH("ML",L48)),1,0)) -> 0 | AR48: =IF(ISBLANK(L49),0,IF(ISNUMBER(SEARCH("ML",L49)),1,0)) -> 0 | AS48: =IF(ISBLANK(L50),0,IF(ISNUMBER(SEARCH("Docker",L50)),1,0)) -> 0 | AT48: =IF(ISBLANK(L50),0,IF(ISNUMBER(SEARCH("dbt",L50)),1,0)) -> 0 | AU48: =IF(ISBLANK(L50),0,IF(ISNUMBER(SEARCH("AWS",L50)),1,0)) -> 0 | AV48: =IF(ISBLANK(L50),0,IF(ISNUMBER(SEARCH("GCP",L50)),1,0)) -> 0 | AW48: =IF(ISBLANK(L50),0,IF(ISNUMBER(SEARCH("Azure",L50)),1,0)) -> 0 | AX48: =IF(ISBLANK(M50),0,IF(ISNUMBER(SEARCH("Tableau",L50)),1,0)) -> 0 | AY48: =IF(ISBLANK(N50),0,IF(ISNUMBER(SEARCH("PowerBI",L50)),1,0)) -> 0 | AZ48: Fulltime
A49: 48 | B49: 46178 | C49: LinkedIn | D49: Business Analyst | E49: Chargebee | F49: Chennai | G49: 3 | H49: 5 | I49: ND | J49: ND | K49: Excel,SQL,CRM | L49: None | M49: Hybrid | N49: Medium | O49: =IF(ISBLANK(K49),0,IF(ISNUMBER(SEARCH("sql",K49)),1,0)) -> 1 | P49: =IF(ISBLANK(K49),0,IF(ISNUMBER(SEARCH("Python",K49)),1,0)) -> 0 | Q49: =IF(ISBLANK(K49),0,IF(ISNUMBER(SEARCH("PowerBI",K49)),1,0)) -> 0 | R49: =IF(ISBLANK(K49),0,IF(ISNUMBER(SEARCH("Tableau",K49)),1,0)) -> 0 | S49: =IF(ISBLANK(K49),0,IF(ISNUMBER(SEARCH("Excel",K49)),1,0)) -> 1 | T49: =IF(ISBLANK(K49),0,IF(ISNUMBER(SEARCH("Statistics",K49)),1,0)) -> 0 | U49: =IF(ISBLANK(K49),0,IF(ISNUMBER(SEARCH("AWS",K49)),1,0)) -> 0 | V49: =IF(ISBLANK(K49),0,IF(ISNUMBER(SEARCH("GCP",K49)),1,0)) -> 0 | W49: =IF(ISBLANK(K49),0,IF(ISNUMBER(SEARCH("NoSQL",K49)),1,0)) -> 0 | X49: =IF(ISBLANK(K49),0,IF(ISNUMBER(SEARCH("Data Modeling",K49)),1,0)) -> 0 | Y49: =IF(ISBLANK(K49),0,IF(ISNUMBER(SEARCH("Pandas",K49)),1,0)) -> 0 | Z49: =IF(ISBLANK(K49),0,IF(ISNUMBER(SEARCH("Numpy",K49)),1,0)) -> 0 | AA49: =IF(ISBLANK(K49),0,IF(ISNUMBER(SEARCH("Pyspark",K49)),1,0)) -> 0 | AB49: =IF(ISBLANK(K49),0,IF(ISNUMBER(SEARCH("Hadoop",K49)),1,0)) -> 0 | AC49: =IF(ISBLANK(K49),0,IF(ISNUMBER(SEARCH("ETL",K49)),1,0)) -> 0 | AD49: =IF(ISBLANK(K49),0,IF(ISNUMBER(SEARCH("Azure",K49)),1,0)) -> 0 | AE49: =IF(ISBLANK(K49),0,IF(ISNUMBER(SEARCH("Databricks",K49)),1,0)) -> 0 | AF49: =IF(ISBLANK(K49),0,IF(ISNUMBER(SEARCH("A/B Testing",K49)),1,0)) -> 0 | AG49: =IF(ISBLANK(K49),0,IF(ISNUMBER(SEARCH("Snowflake",K49)),1,0)) -> 0 | AH49: =IF(ISBLANK(K49),0,IF(ISNUMBER(SEARCH("Agile",K49)),1,0)) -> 0 | AI49: =IF(ISBLANK(K49),0,IF(ISNUMBER(SEARCH("Jira",K49)),1,0)) -> 0 | AJ49: =IF(ISBLANK(K49),0,IF(ISNUMBER(SEARCH("Git",K49)),1,0)) -> 0 | AK49: =IF(ISBLANK(K49),0,IF(ISNUMBER(SEARCH("Reporting",K49)),1,0)) -> 0 | AL49: =IF(ISBLANK(K49),0,IF(ISNUMBER(SEARCH("CI/CD",K49)),1,0)) -> 0 | AM49: =IF(ISBLANK(L49),0,IF(ISNUMBER(SEARCH("Python",L49)),1,0)) -> 0 | AN49: =IF(ISBLANK(L49),0,IF(ISNUMBER(SEARCH("SQL",L49)),1,0)) -> 0 | AO49: =IF(ISBLANK(L49),0,IF(ISNUMBER(SEARCH("Airflow",L49)),1,0)) -> 0 | AP49: =IF(ISBLANK(L49),0,IF(ISNUMBER(SEARCH("Kafka",L49)),1,0)) -> 0 | AQ49: =IF(ISBLANK(L49),0,IF(ISNUMBER(SEARCH("ML",L49)),1,0)) -> 0 | AR49: =IF(ISBLANK(L50),0,IF(ISNUMBER(SEARCH("ML",L50)),1,0)) -> 0 | AS49: =IF(ISBLANK(L51),0,IF(ISNUMBER(SEARCH("Docker",L51)),1,0)) -> 0 | AT49: =IF(ISBLANK(L51),0,IF(ISNUMBER(SEARCH("dbt",L51)),1,0)) -> 0 | AU49: =IF(ISBLANK(L51),0,IF(ISNUMBER(SEARCH("AWS",L51)),1,0)) -> 0 | AV49: =IF(ISBLANK(L51),0,IF(ISNUMBER(SEARCH("GCP",L51)),1,0)) -> 0 | AW49: =IF(ISBLANK(L51),0,IF(ISNUMBER(SEARCH("Azure",L51)),1,0)) -> 0 | AX49: =IF(ISBLANK(M51),0,IF(ISNUMBER(SEARCH("Tableau",L51)),1,0)) -> 0 | AY49: =IF(ISBLANK(N51),0,IF(ISNUMBER(SEARCH("PowerBI",L51)),1,0)) -> 0 | AZ49: Fulltime
A50: 49 | B50: 46178 | C50: LinkedIn | D50: Business Analyst | E50: Indofast Energy | F50: Bengaluru | G50: 2 | H50: 5 | I50: ND | J50: ND | K50: Excel,PowerBI/Tableau | L50: Fleet , Logistics , Operations knowledge | M50: On-site | N50: Small | O50: =IF(ISBLANK(K50),0,IF(ISNUMBER(SEARCH("sql",K50)),1,0)) -> 0 | P50: =IF(ISBLANK(K50),0,IF(ISNUMBER(SEARCH("Python",K50)),1,0)) -> 0 | Q50: =IF(ISBLANK(K50),0,IF(ISNUMBER(SEARCH("PowerBI",K50)),1,0)) -> 1 | R50: =IF(ISBLANK(K50),0,IF(ISNUMBER(SEARCH("Tableau",K50)),1,0)) -> 1 | S50: =IF(ISBLANK(K50),0,IF(ISNUMBER(SEARCH("Excel",K50)),1,0)) -> 1 | T50: =IF(ISBLANK(K50),0,IF(ISNUMBER(SEARCH("Statistics",K50)),1,0)) -> 0 | U50: =IF(ISBLANK(K50),0,IF(ISNUMBER(SEARCH("AWS",K50)),1,0)) -> 0 | V50: =IF(ISBLANK(K50),0,IF(ISNUMBER(SEARCH("GCP",K50)),1,0)) -> 0 | W50: =IF(ISBLANK(K50),0,IF(ISNUMBER(SEARCH("NoSQL",K50)),1,0)) -> 0 | X50: =IF(ISBLANK(K50),0,IF(ISNUMBER(SEARCH("Data Modeling",K50)),1,0)) -> 0 | Y50: =IF(ISBLANK(K50),0,IF(ISNUMBER(SEARCH("Pandas",K50)),1,0)) -> 0 | Z50: =IF(ISBLANK(K50),0,IF(ISNUMBER(SEARCH("Numpy",K50)),1,0)) -> 0 | AA50: =IF(ISBLANK(K50),0,IF(ISNUMBER(SEARCH("Pyspark",K50)),1,0)) -> 0 | AB50: =IF(ISBLANK(K50),0,IF(ISNUMBER(SEARCH("Hadoop",K50)),1,0)) -> 0 | AC50: =IF(ISBLANK(K50),0,IF(ISNUMBER(SEARCH("ETL",K50)),1,0)) -> 0 | AD50: =IF(ISBLANK(K50),0,IF(ISNUMBER(SEARCH("Azure",K50)),1,0)) -> 0 | AE50: =IF(ISBLANK(K50),0,IF(ISNUMBER(SEARCH("Databricks",K50)),1,0)) -> 0 | AF50: =IF(ISBLANK(K50),0,IF(ISNUMBER(SEARCH("A/B Testing",K50)),1,0)) -> 0 | AG50: =IF(ISBLANK(K50),0,IF(ISNUMBER(SEARCH("Snowflake",K50)),1,0)) -> 0 | AH50: =IF(ISBLANK(K50),0,IF(ISNUMBER(SEARCH("Agile",K50)),1,0)) -> 0 | AI50: =IF(ISBLANK(K50),0,IF(ISNUMBER(SEARCH("Jira",K50)),1,0)) -> 0 | AJ50: =IF(ISBLANK(K50),0,IF(ISNUMBER(SEARCH("Git",K50)),1,0)) -> 0 | AK50: =IF(ISBLANK(K50),0,IF(ISNUMBER(SEARCH("Reporting",K50)),1,0)) -> 0 | AL50: =IF(ISBLANK(K50),0,IF(ISNUMBER(SEARCH("CI/CD",K50)),1,0)) -> 0 | AM50: =IF(ISBLANK(L50),0,IF(ISNUMBER(SEARCH("Python",L50)),1,0)) -> 0 | AN50: =IF(ISBLANK(L50),0,IF(ISNUMBER(SEARCH("SQL",L50)),1,0)) -> 0 | AO50: =IF(ISBLANK(L50),0,IF(ISNUMBER(SEARCH("Airflow",L50)),1,0)) -> 0 | AP50: =IF(ISBLANK(L50),0,IF(ISNUMBER(SEARCH("Kafka",L50)),1,0)) -> 0 | AQ50: =IF(ISBLANK(L50),0,IF(ISNUMBER(SEARCH("ML",L50)),1,0)) -> 0 | AR50: =IF(ISBLANK(L51),0,IF(ISNUMBER(SEARCH("ML",L51)),1,0)) -> 0 | AS50: =IF(ISBLANK(L52),0,IF(ISNUMBER(SEARCH("Docker",L52)),1,0)) -> 0 | AT50: =IF(ISBLANK(L52),0,IF(ISNUMBER(SEARCH("dbt",L52)),1,0)) -> 0 | AU50: =IF(ISBLANK(L52),0,IF(ISNUMBER(SEARCH("AWS",L52)),1,0)) -> 0 | AV50: =IF(ISBLANK(L52),0,IF(ISNUMBER(SEARCH("GCP",L52)),1,0)) -> 0 | AW50: =IF(ISBLANK(L52),0,IF(ISNUMBER(SEARCH("Azure",L52)),1,0)) -> 0 | AX50: =IF(ISBLANK(M52),0,IF(ISNUMBER(SEARCH("Tableau",L52)),1,0)) -> 0 | AY50: =IF(ISBLANK(N52),0,IF(ISNUMBER(SEARCH("PowerBI",L52)),1,0)) -> 0 | AZ50: Fulltime
A51: 50 | B51: 46178 | C51: LinkedIn | D51: Business Analyst | E51: Swiss Re | F51: Bengaluru | G51: 1 | H51: 5 | I51: ND | J51: ND | K51: ETL, Python, SQL | L51: LLMs , Knowledge of Health Insurance | M51: On-site | N51: Large | O51: =IF(ISBLANK(K51),0,IF(ISNUMBER(SEARCH("sql",K51)),1,0)) -> 1 | P51: =IF(ISBLANK(K51),0,IF(ISNUMBER(SEARCH("Python",K51)),1,0)) -> 1 | Q51: =IF(ISBLANK(K51),0,IF(ISNUMBER(SEARCH("PowerBI",K51)),1,0)) -> 0 | R51: =IF(ISBLANK(K51),0,IF(ISNUMBER(SEARCH("Tableau",K51)),1,0)) -> 0 | S51: =IF(ISBLANK(K51),0,IF(ISNUMBER(SEARCH("Excel",K51)),1,0)) -> 0 | T51: =IF(ISBLANK(K51),0,IF(ISNUMBER(SEARCH("Statistics",K51)),1,0)) -> 0 | U51: =IF(ISBLANK(K51),0,IF(ISNUMBER(SEARCH("AWS",K51)),1,0)) -> 0 | V51: =IF(ISBLANK(K51),0,IF(ISNUMBER(SEARCH("GCP",K51)),1,0)) -> 0 | W51: =IF(ISBLANK(K51),0,IF(ISNUMBER(SEARCH("NoSQL",K51)),1,0)) -> 0 | X51: =IF(ISBLANK(K51),0,IF(ISNUMBER(SEARCH("Data Modeling",K51)),1,0)) -> 0 | Y51: =IF(ISBLANK(K51),0,IF(ISNUMBER(SEARCH("Pandas",K51)),1,0)) -> 0 | Z51: =IF(ISBLANK(K51),0,IF(ISNUMBER(SEARCH("Numpy",K51)),1,0)) -> 0 | AA51: =IF(ISBLANK(K51),0,IF(ISNUMBER(SEARCH("Pyspark",K51)),1,0)) -> 0 | AB51: =IF(ISBLANK(K51),0,IF(ISNUMBER(SEARCH("Hadoop",K51)),1,0)) -> 0 | AC51: =IF(ISBLANK(K51),0,IF(ISNUMBER(SEARCH("ETL",K51)),1,0)) -> 1 | AD51: =IF(ISBLANK(K51),0,IF(ISNUMBER(SEARCH("Azure",K51)),1,0)) -> 0 | AE51: =IF(ISBLANK(K51),0,IF(ISNUMBER(SEARCH("Databricks",K51)),1,0)) -> 0 | AF51: =IF(ISBLANK(K51),0,IF(ISNUMBER(SEARCH("A/B Testing",K51)),1,0)) -> 0 | AG51: =IF(ISBLANK(K51),0,IF(ISNUMBER(SEARCH("Snowflake",K51)),1,0)) -> 0 | AH51: =IF(ISBLANK(K51),0,IF(ISNUMBER(SEARCH("Agile",K51)),1,0)) -> 0 | AI51: =IF(ISBLANK(K51),0,IF(ISNUMBER(SEARCH("Jira",K51)),1,0)) -> 0 | AJ51: =IF(ISBLANK(K51),0,IF(ISNUMBER(SEARCH("Git",K51)),1,0)) -> 0 | AK51: =IF(ISBLANK(K51),0,IF(ISNUMBER(SEARCH("Reporting",K51)),1,0)) -> 0 | AL51: =IF(ISBLANK(K51),0,IF(ISNUMBER(SEARCH("CI/CD",K51)),1,0)) -> 0 | AM51: =IF(ISBLANK(L51),0,IF(ISNUMBER(SEARCH("Python",L51)),1,0)) -> 0 | AN51: =IF(ISBLANK(L51),0,IF(ISNUMBER(SEARCH("SQL",L51)),1,0)) -> 0 | AO51: =IF(ISBLANK(L51),0,IF(ISNUMBER(SEARCH("Airflow",L51)),1,0)) -> 0 | AP51: =IF(ISBLANK(L51),0,IF(ISNUMBER(SEARCH("Kafka",L51)),1,0)) -> 0 | AQ51: =IF(ISBLANK(L51),0,IF(ISNUMBER(SEARCH("ML",L51)),1,0)) -> 0 | AR51: =IF(ISBLANK(L52),0,IF(ISNUMBER(SEARCH("ML",L52)),1,0)) -> 0 | AS51: =IF(ISBLANK(L53),0,IF(ISNUMBER(SEARCH("Docker",L53)),1,0)) -> 0 | AT51: =IF(ISBLANK(L53),0,IF(ISNUMBER(SEARCH("dbt",L53)),1,0)) -> 0 | AU51: =IF(ISBLANK(L53),0,IF(ISNUMBER(SEARCH("AWS",L53)),1,0)) -> 0 | AV51: =IF(ISBLANK(L53),0,IF(ISNUMBER(SEARCH("GCP",L53)),1,0)) -> 0 | AW51: =IF(ISBLANK(L53),0,IF(ISNUMBER(SEARCH("Azure",L53)),1,0)) -> 0 | AX51: =IF(ISBLANK(M53),0,IF(ISNUMBER(SEARCH("Tableau",L53)),1,0)) -> 0 | AY51: =IF(ISBLANK(N53),0,IF(ISNUMBER(SEARCH("PowerBI",L53)),1,0)) -> 0 | AZ51: Fulltime
A52: 51 | B52: 46178 | C52: LinkedIn | D52: Data Analyst | E52: Airtel Payments Bank | F52: Bengaluru | G52: ND | H52: ND | I52: ND | J52: ND | K52: SQL , PowerBI, Excel | L52: None | M52: On-site | N52: Large | O52: =IF(ISBLANK(K52),0,IF(ISNUMBER(SEARCH("sql",K52)),1,0)) -> 1 | P52: =IF(ISBLANK(K52),0,IF(ISNUMBER(SEARCH("Python",K52)),1,0)) -> 0 | Q52: =IF(ISBLANK(K52),0,IF(ISNUMBER(SEARCH("PowerBI",K52)),1,0)) -> 1 | R52: =IF(ISBLANK(K52),0,IF(ISNUMBER(SEARCH("Tableau",K52)),1,0)) -> 0 | S52: =IF(ISBLANK(K52),0,IF(ISNUMBER(SEARCH("Excel",K52)),1,0)) -> 1 | T52: =IF(ISBLANK(K52),0,IF(ISNUMBER(SEARCH("Statistics",K52)),1,0)) -> 0 | U52: =IF(ISBLANK(K52),0,IF(ISNUMBER(SEARCH("AWS",K52)),1,0)) -> 0 | V52: =IF(ISBLANK(K52),0,IF(ISNUMBER(SEARCH("GCP",K52)),1,0)) -> 0 | W52: =IF(ISBLANK(K52),0,IF(ISNUMBER(SEARCH("NoSQL",K52)),1,0)) -> 0 | X52: =IF(ISBLANK(K52),0,IF(ISNUMBER(SEARCH("Data Modeling",K52)),1,0)) -> 0 | Y52: =IF(ISBLANK(K52),0,IF(ISNUMBER(SEARCH("Pandas",K52)),1,0)) -> 0 | Z52: =IF(ISBLANK(K52),0,IF(ISNUMBER(SEARCH("Numpy",K52)),1,0)) -> 0 | AA52: =IF(ISBLANK(K52),0,IF(ISNUMBER(SEARCH("Pyspark",K52)),1,0)) -> 0 | AB52: =IF(ISBLANK(K52),0,IF(ISNUMBER(SEARCH("Hadoop",K52)),1,0)) -> 0 | AC52: =IF(ISBLANK(K52),0,IF(ISNUMBER(SEARCH("ETL",K52)),1,0)) -> 0 | AD52: =IF(ISBLANK(K52),0,IF(ISNUMBER(SEARCH("Azure",K52)),1,0)) -> 0 | AE52: =IF(ISBLANK(K52),0,IF(ISNUMBER(SEARCH("Databricks",K52)),1,0)) -> 0 | AF52: =IF(ISBLANK(K52),0,IF(ISNUMBER(SEARCH("A/B Testing",K52)),1,0)) -> 0 | AG52: =IF(ISBLANK(K52),0,IF(ISNUMBER(SEARCH("Snowflake",K52)),1,0)) -> 0 | AH52: =IF(ISBLANK(K52),0,IF(ISNUMBER(SEARCH("Agile",K52)),1,0)) -> 0 | AI52: =IF(ISBLANK(K52),0,IF(ISNUMBER(SEARCH("Jira",K52)),1,0)) -> 0 | AJ52: =IF(ISBLANK(K52),0,IF(ISNUMBER(SEARCH("Git",K52)),1,0)) -> 0 | AK52: =IF(ISBLANK(K52),0,IF(ISNUMBER(SEARCH("Reporting",K52)),1,0)) -> 0 | AL52: =IF(ISBLANK(K52),0,IF(ISNUMBER(SEARCH("CI/CD",K52)),1,0)) -> 0 | AM52: =IF(ISBLANK(L52),0,IF(ISNUMBER(SEARCH("Python",L52)),1,0)) -> 0 | AN52: =IF(ISBLANK(L52),0,IF(ISNUMBER(SEARCH("SQL",L52)),1,0)) -> 0 | AO52: =IF(ISBLANK(L52),0,IF(ISNUMBER(SEARCH("Airflow",L52)),1,0)) -> 0 | AP52: =IF(ISBLANK(L52),0,IF(ISNUMBER(SEARCH("Kafka",L52)),1,0)) -> 0 | AQ52: =IF(ISBLANK(L52),0,IF(ISNUMBER(SEARCH("ML",L52)),1,0)) -> 0 | AR52: =IF(ISBLANK(L53),0,IF(ISNUMBER(SEARCH("ML",L53)),1,0)) -> 0 | AS52: =IF(ISBLANK(L54),0,IF(ISNUMBER(SEARCH("Docker",L54)),1,0)) -> 0 | AT52: =IF(ISBLANK(L54),0,IF(ISNUMBER(SEARCH("dbt",L54)),1,0)) -> 0 | AU52: =IF(ISBLANK(L54),0,IF(ISNUMBER(SEARCH("AWS",L54)),1,0)) -> 0 | AV52: =IF(ISBLANK(L54),0,IF(ISNUMBER(SEARCH("GCP",L54)),1,0)) -> 0 | AW52: =IF(ISBLANK(L54),0,IF(ISNUMBER(SEARCH("Azure",L54)),1,0)) -> 0 | AX52: =IF(ISBLANK(M54),0,IF(ISNUMBER(SEARCH("Tableau",L54)),1,0)) -> 0 | AY52: =IF(ISBLANK(N54),0,IF(ISNUMBER(SEARCH("PowerBI",L54)),1,0)) -> 0 | AZ52: Fulltime
A53: 52 | B53: 46178 | C53: LinkedIn | D53: MIS Analyst | E53: TWRW - The House of Brands | F53: Bengaluru | G53: 1 | H53: 3 | I53: ND | J53: ND | K53: Excel, Python , Databases,MIS Analysis, | L53: Exposure to automation, AI tools, or analytics platforms | M53: On-site | N53: Small | O53: =IF(ISBLANK(K53),0,IF(ISNUMBER(SEARCH("sql",K53)),1,0)) -> 0 | P53: =IF(ISBLANK(K53),0,IF(ISNUMBER(SEARCH("Python",K53)),1,0)) -> 1 | Q53: =IF(ISBLANK(K53),0,IF(ISNUMBER(SEARCH("PowerBI",K53)),1,0)) -> 0 | R53: =IF(ISBLANK(K53),0,IF(ISNUMBER(SEARCH("Tableau",K53)),1,0)) -> 0 | S53: =IF(ISBLANK(K53),0,IF(ISNUMBER(SEARCH("Excel",K53)),1,0)) -> 1 | T53: =IF(ISBLANK(K53),0,IF(ISNUMBER(SEARCH("Statistics",K53)),1,0)) -> 0 | U53: =IF(ISBLANK(K53),0,IF(ISNUMBER(SEARCH("AWS",K53)),1,0)) -> 0 | V53: =IF(ISBLANK(K53),0,IF(ISNUMBER(SEARCH("GCP",K53)),1,0)) -> 0 | W53: =IF(ISBLANK(K53),0,IF(ISNUMBER(SEARCH("NoSQL",K53)),1,0)) -> 0 | X53: =IF(ISBLANK(K53),0,IF(ISNUMBER(SEARCH("Data Modeling",K53)),1,0)) -> 0 | Y53: =IF(ISBLANK(K53),0,IF(ISNUMBER(SEARCH("Pandas",K53)),1,0)) -> 0 | Z53: =IF(ISBLANK(K53),0,IF(ISNUMBER(SEARCH("Numpy",K53)),1,0)) -> 0 | AA53: =IF(ISBLANK(K53),0,IF(ISNUMBER(SEARCH("Pyspark",K53)),1,0)) -> 0 | AB53: =IF(ISBLANK(K53),0,IF(ISNUMBER(SEARCH("Hadoop",K53)),1,0)) -> 0 | AC53: =IF(ISBLANK(K53),0,IF(ISNUMBER(SEARCH("ETL",K53)),1,0)) -> 0 | AD53: =IF(ISBLANK(K53),0,IF(ISNUMBER(SEARCH("Azure",K53)),1,0)) -> 0 | AE53: =IF(ISBLANK(K53),0,IF(ISNUMBER(SEARCH("Databricks",K53)),1,0)) -> 0 | AF53: =IF(ISBLANK(K53),0,IF(ISNUMBER(SEARCH("A/B Testing",K53)),1,0)) -> 0 | AG53: =IF(ISBLANK(K53),0,IF(ISNUMBER(SEARCH("Snowflake",K53)),1,0)) -> 0 | AH53: =IF(ISBLANK(K53),0,IF(ISNUMBER(SEARCH("Agile",K53)),1,0)) -> 0 | AI53: =IF(ISBLANK(K53),0,IF(ISNUMBER(SEARCH("Jira",K53)),1,0)) -> 0 | AJ53: =IF(ISBLANK(K53),0,IF(ISNUMBER(SEARCH("Git",K53)),1,0)) -> 0 | AK53: =IF(ISBLANK(K53),0,IF(ISNUMBER(SEARCH("Reporting",K53)),1,0)) -> 0 | AL53: =IF(ISBLANK(K53),0,IF(ISNUMBER(SEARCH("CI/CD",K53)),1,0)) -> 0 | AM53: =IF(ISBLANK(L53),0,IF(ISNUMBER(SEARCH("Python",L53)),1,0)) -> 0 | AN53: =IF(ISBLANK(L53),0,IF(ISNUMBER(SEARCH("SQL",L53)),1,0)) -> 0 | AO53: =IF(ISBLANK(L53),0,IF(ISNUMBER(SEARCH("Airflow",L53)),1,0)) -> 0 | AP53: =IF(ISBLANK(L53),0,IF(ISNUMBER(SEARCH("Kafka",L53)),1,0)) -> 0 | AQ53: =IF(ISBLANK(L53),0,IF(ISNUMBER(SEARCH("ML",L53)),1,0)) -> 0 | AR53: =IF(ISBLANK(L54),0,IF(ISNUMBER(SEARCH("ML",L54)),1,0)) -> 0 | AS53: =IF(ISBLANK(L55),0,IF(ISNUMBER(SEARCH("Docker",L55)),1,0)) -> 0 | AT53: =IF(ISBLANK(L55),0,IF(ISNUMBER(SEARCH("dbt",L55)),1,0)) -> 0 | AU53: =IF(ISBLANK(L55),0,IF(ISNUMBER(SEARCH("AWS",L55)),1,0)) -> 0 | AV53: =IF(ISBLANK(L55),0,IF(ISNUMBER(SEARCH("GCP",L55)),1,0)) -> 0 | AW53: =IF(ISBLANK(L55),0,IF(ISNUMBER(SEARCH("Azure",L55)),1,0)) -> 0 | AX53: =IF(ISBLANK(M55),0,IF(ISNUMBER(SEARCH("Tableau",L55)),1,0)) -> 1 | AY53: =IF(ISBLANK(N55),0,IF(ISNUMBER(SEARCH("PowerBI",L55)),1,0)) -> 1 | AZ53: Fulltime
A54: 53 | B54: 46178 | C54: LinkedIn | D54: MIS Analyst | E54: Launch Ventures | F54: Delhi | G54: 3 | H54: 6 | I54: ND | J54: ND | K54: Excel, Reporting, BI Tools | L54: None | M54: On-site | N54: Medium | O54: =IF(ISBLANK(K54),0,IF(ISNUMBER(SEARCH("sql",K54)),1,0)) -> 0 | P54: =IF(ISBLANK(K54),0,IF(ISNUMBER(SEARCH("Python",K54)),1,0)) -> 0 | Q54: =IF(ISBLANK(K54),0,IF(ISNUMBER(SEARCH("PowerBI",K54)),1,0)) -> 0 | R54: =IF(ISBLANK(K54),0,IF(ISNUMBER(SEARCH("Tableau",K54)),1,0)) -> 0 | S54: =IF(ISBLANK(K54),0,IF(ISNUMBER(SEARCH("Excel",K54)),1,0)) -> 1 | T54: =IF(ISBLANK(K54),0,IF(ISNUMBER(SEARCH("Statistics",K54)),1,0)) -> 0 | U54: =IF(ISBLANK(K54),0,IF(ISNUMBER(SEARCH("AWS",K54)),1,0)) -> 0 | V54: =IF(ISBLANK(K54),0,IF(ISNUMBER(SEARCH("GCP",K54)),1,0)) -> 0 | W54: =IF(ISBLANK(K54),0,IF(ISNUMBER(SEARCH("NoSQL",K54)),1,0)) -> 0 | X54: =IF(ISBLANK(K54),0,IF(ISNUMBER(SEARCH("Data Modeling",K54)),1,0)) -> 0 | Y54: =IF(ISBLANK(K54),0,IF(ISNUMBER(SEARCH("Pandas",K54)),1,0)) -> 0 | Z54: =IF(ISBLANK(K54),0,IF(ISNUMBER(SEARCH("Numpy",K54)),1,0)) -> 0 | AA54: =IF(ISBLANK(K54),0,IF(ISNUMBER(SEARCH("Pyspark",K54)),1,0)) -> 0 | AB54: =IF(ISBLANK(K54),0,IF(ISNUMBER(SEARCH("Hadoop",K54)),1,0)) -> 0 | AC54: =IF(ISBLANK(K54),0,IF(ISNUMBER(SEARCH("ETL",K54)),1,0)) -> 0 | AD54: =IF(ISBLANK(K54),0,IF(ISNUMBER(SEARCH("Azure",K54)),1,0)) -> 0 | AE54: =IF(ISBLANK(K54),0,IF(ISNUMBER(SEARCH("Databricks",K54)),1,0)) -> 0 | AF54: =IF(ISBLANK(K54),0,IF(ISNUMBER(SEARCH("A/B Testing",K54)),1,0)) -> 0 | AG54: =IF(ISBLANK(K54),0,IF(ISNUMBER(SEARCH("Snowflake",K54)),1,0)) -> 0 | AH54: =IF(ISBLANK(K54),0,IF(ISNUMBER(SEARCH("Agile",K54)),1,0)) -> 0 | AI54: =IF(ISBLANK(K54),0,IF(ISNUMBER(SEARCH("Jira",K54)),1,0)) -> 0 | AJ54: =IF(ISBLANK(K54),0,IF(ISNUMBER(SEARCH("Git",K54)),1,0)) -> 0 | AK54: =IF(ISBLANK(K54),0,IF(ISNUMBER(SEARCH("Reporting",K54)),1,0)) -> 1 | AL54: =IF(ISBLANK(K54),0,IF(ISNUMBER(SEARCH("CI/CD",K54)),1,0)) -> 0 | AM54: =IF(ISBLANK(L54),0,IF(ISNUMBER(SEARCH("Python",L54)),1,0)) -> 0 | AN54: =IF(ISBLANK(L54),0,IF(ISNUMBER(SEARCH("SQL",L54)),1,0)) -> 0 | AO54: =IF(ISBLANK(L54),0,IF(ISNUMBER(SEARCH("Airflow",L54)),1,0)) -> 0 | AP54: =IF(ISBLANK(L54),0,IF(ISNUMBER(SEARCH("Kafka",L54)),1,0)) -> 0 | AQ54: =IF(ISBLANK(L54),0,IF(ISNUMBER(SEARCH("ML",L54)),1,0)) -> 0 | AR54: =IF(ISBLANK(L55),0,IF(ISNUMBER(SEARCH("ML",L55)),1,0)) -> 0 | AS54: =IF(ISBLANK(L56),0,IF(ISNUMBER(SEARCH("Docker",L56)),1,0)) -> 0 | AT54: =IF(ISBLANK(L56),0,IF(ISNUMBER(SEARCH("dbt",L56)),1,0)) -> 0 | AU54: =IF(ISBLANK(L56),0,IF(ISNUMBER(SEARCH("AWS",L56)),1,0)) -> 0 | AV54: =IF(ISBLANK(L56),0,IF(ISNUMBER(SEARCH("GCP",L56)),1,0)) -> 0 | AW54: =IF(ISBLANK(L56),0,IF(ISNUMBER(SEARCH("Azure",L56)),1,0)) -> 0 | AX54: =IF(ISBLANK(M56),0,IF(ISNUMBER(SEARCH("Tableau",L56)),1,0)) -> 0 | AY54: =IF(ISBLANK(N56),0,IF(ISNUMBER(SEARCH("PowerBI",L56)),1,0)) -> 0 | AZ54: Fulltime
A55: 54 | B55: 46178 | C55: LinkedIn | D55: MIS Analyst | E55: dentsu | F55: Pune | G55: ND | H55: ND | I55: ND | J55: ND | K55: Excel, BI Reporting | L55: SQL , BI tools like PowerBI , Tableau | M55: On-site | N55: Medium | O55: =IF(ISBLANK(K55),0,IF(ISNUMBER(SEARCH("sql",K55)),1,0)) -> 0 | P55: =IF(ISBLANK(K55),0,IF(ISNUMBER(SEARCH("Python",K55)),1,0)) -> 0 | Q55: =IF(ISBLANK(K55),0,IF(ISNUMBER(SEARCH("PowerBI",K55)),1,0)) -> 0 | R55: =IF(ISBLANK(K55),0,IF(ISNUMBER(SEARCH("Tableau",K55)),1,0)) -> 0 | S55: =IF(ISBLANK(K55),0,IF(ISNUMBER(SEARCH("Excel",K55)),1,0)) -> 1 | T55: =IF(ISBLANK(K55),0,IF(ISNUMBER(SEARCH("Statistics",K55)),1,0)) -> 0 | U55: =IF(ISBLANK(K55),0,IF(ISNUMBER(SEARCH("AWS",K55)),1,0)) -> 0 | V55: =IF(ISBLANK(K55),0,IF(ISNUMBER(SEARCH("GCP",K55)),1,0)) -> 0 | W55: =IF(ISBLANK(K55),0,IF(ISNUMBER(SEARCH("NoSQL",K55)),1,0)) -> 0 | X55: =IF(ISBLANK(K55),0,IF(ISNUMBER(SEARCH("Data Modeling",K55)),1,0)) -> 0 | Y55: =IF(ISBLANK(K55),0,IF(ISNUMBER(SEARCH("Pandas",K55)),1,0)) -> 0 | Z55: =IF(ISBLANK(K55),0,IF(ISNUMBER(SEARCH("Numpy",K55)),1,0)) -> 0 | AA55: =IF(ISBLANK(K55),0,IF(ISNUMBER(SEARCH("Pyspark",K55)),1,0)) -> 0 | AB55: =IF(ISBLANK(K55),0,IF(ISNUMBER(SEARCH("Hadoop",K55)),1,0)) -> 0 | AC55: =IF(ISBLANK(K55),0,IF(ISNUMBER(SEARCH("ETL",K55)),1,0)) -> 0 | AD55: =IF(ISBLANK(K55),0,IF(ISNUMBER(SEARCH("Azure",K55)),1,0)) -> 0 | AE55: =IF(ISBLANK(K55),0,IF(ISNUMBER(SEARCH("Databricks",K55)),1,0)) -> 0 | AF55: =IF(ISBLANK(K55),0,IF(ISNUMBER(SEARCH("A/B Testing",K55)),1,0)) -> 0 | AG55: =IF(ISBLANK(K55),0,IF(ISNUMBER(SEARCH("Snowflake",K55)),1,0)) -> 0 | AH55: =IF(ISBLANK(K55),0,IF(ISNUMBER(SEARCH("Agile",K55)),1,0)) -> 0 | AI55: =IF(ISBLANK(K55),0,IF(ISNUMBER(SEARCH("Jira",K55)),1,0)) -> 0 | AJ55: =IF(ISBLANK(K55),0,IF(ISNUMBER(SEARCH("Git",K55)),1,0)) -> 0 | AK55: =IF(ISBLANK(K55),0,IF(ISNUMBER(SEARCH("Reporting",K55)),1,0)) -> 1 | AL55: =IF(ISBLANK(K55),0,IF(ISNUMBER(SEARCH("CI/CD",K55)),1,0)) -> 0 | AM55: =IF(ISBLANK(L55),0,IF(ISNUMBER(SEARCH("Python",L55)),1,0)) -> 0 | AN55: =IF(ISBLANK(L55),0,IF(ISNUMBER(SEARCH("SQL",L55)),1,0)) -> 1 | AO55: =IF(ISBLANK(L55),0,IF(ISNUMBER(SEARCH("Airflow",L55)),1,0)) -> 0 | AP55: =IF(ISBLANK(L55),0,IF(ISNUMBER(SEARCH("Kafka",L55)),1,0)) -> 0 | AQ55: =IF(ISBLANK(L55),0,IF(ISNUMBER(SEARCH("ML",L55)),1,0)) -> 0 | AR55: =IF(ISBLANK(L56),0,IF(ISNUMBER(SEARCH("ML",L56)),1,0)) -> 0 | AS55: =IF(ISBLANK(L57),0,IF(ISNUMBER(SEARCH("Docker",L57)),1,0)) -> 0 | AT55: =IF(ISBLANK(L57),0,IF(ISNUMBER(SEARCH("dbt",L57)),1,0)) -> 0 | AU55: =IF(ISBLANK(L57),0,IF(ISNUMBER(SEARCH("AWS",L57)),1,0)) -> 0 | AV55: =IF(ISBLANK(L57),0,IF(ISNUMBER(SEARCH("GCP",L57)),1,0)) -> 0 | AW55: =IF(ISBLANK(L57),0,IF(ISNUMBER(SEARCH("Azure",L57)),1,0)) -> 0 | AX55: =IF(ISBLANK(M57),0,IF(ISNUMBER(SEARCH("Tableau",L57)),1,0)) -> 0 | AY55: =IF(ISBLANK(N57),0,IF(ISNUMBER(SEARCH("PowerBI",L57)),1,0)) -> 0 | AZ55: Fulltime
A56: 55 | B56: 46178 | C56: LinkedIn | D56: Business Analyst | E56: Rupeek | F56: Bengaluru | G56: 1 | H56: 2 | I56: ND | J56: ND | K56: Excel, Hive,SQL, Tableau , MSTR | L56: None | M56: On-site | N56: Startup | O56: =IF(ISBLANK(K56),0,IF(ISNUMBER(SEARCH("sql",K56)),1,0)) -> 1 | P56: =IF(ISBLANK(K56),0,IF(ISNUMBER(SEARCH("Python",K56)),1,0)) -> 0 | Q56: =IF(ISBLANK(K56),0,IF(ISNUMBER(SEARCH("PowerBI",K56)),1,0)) -> 0 | R56: =IF(ISBLANK(K56),0,IF(ISNUMBER(SEARCH("Tableau",K56)),1,0)) -> 1 | S56: =IF(ISBLANK(K56),0,IF(ISNUMBER(SEARCH("Excel",K56)),1,0)) -> 1 | T56: =IF(ISBLANK(K56),0,IF(ISNUMBER(SEARCH("Statistics",K56)),1,0)) -> 0 | U56: =IF(ISBLANK(K56),0,IF(ISNUMBER(SEARCH("AWS",K56)),1,0)) -> 0 | V56: =IF(ISBLANK(K56),0,IF(ISNUMBER(SEARCH("GCP",K56)),1,0)) -> 0 | W56: =IF(ISBLANK(K56),0,IF(ISNUMBER(SEARCH("NoSQL",K56)),1,0)) -> 0 | X56: =IF(ISBLANK(K56),0,IF(ISNUMBER(SEARCH("Data Modeling",K56)),1,0)) -> 0 | Y56: =IF(ISBLANK(K56),0,IF(ISNUMBER(SEARCH("Pandas",K56)),1,0)) -> 0 | Z56: =IF(ISBLANK(K56),0,IF(ISNUMBER(SEARCH("Numpy",K56)),1,0)) -> 0 | AA56: =IF(ISBLANK(K56),0,IF(ISNUMBER(SEARCH("Pyspark",K56)),1,0)) -> 0 | AB56: =IF(ISBLANK(K56),0,IF(ISNUMBER(SEARCH("Hadoop",K56)),1,0)) -> 0 | AC56: =IF(ISBLANK(K56),0,IF(ISNUMBER(SEARCH("ETL",K56)),1,0)) -> 0 | AD56: =IF(ISBLANK(K56),0,IF(ISNUMBER(SEARCH("Azure",K56)),1,0)) -> 0 | AE56: =IF(ISBLANK(K56),0,IF(ISNUMBER(SEARCH("Databricks",K56)),1,0)) -> 0 | AF56: =IF(ISBLANK(K56),0,IF(ISNUMBER(SEARCH("A/B Testing",K56)),1,0)) -> 0 | AG56: =IF(ISBLANK(K56),0,IF(ISNUMBER(SEARCH("Snowflake",K56)),1,0)) -> 0 | AH56: =IF(ISBLANK(K56),0,IF(ISNUMBER(SEARCH("Agile",K56)),1,0)) -> 0 | AI56: =IF(ISBLANK(K56),0,IF(ISNUMBER(SEARCH("Jira",K56)),1,0)) -> 0 | AJ56: =IF(ISBLANK(K56),0,IF(ISNUMBER(SEARCH("Git",K56)),1,0)) -> 0 | AK56: =IF(ISBLANK(K56),0,IF(ISNUMBER(SEARCH("Reporting",K56)),1,0)) -> 0 | AL56: =IF(ISBLANK(K56),0,IF(ISNUMBER(SEARCH("CI/CD",K56)),1,0)) -> 0 | AM56: =IF(ISBLANK(L56),0,IF(ISNUMBER(SEARCH("Python",L56)),1,0)) -> 0 | AN56: =IF(ISBLANK(L56),0,IF(ISNUMBER(SEARCH("SQL",L56)),1,0)) -> 0 | AO56: =IF(ISBLANK(L56),0,IF(ISNUMBER(SEARCH("Airflow",L56)),1,0)) -> 0 | AP56: =IF(ISBLANK(L56),0,IF(ISNUMBER(SEARCH("Kafka",L56)),1,0)) -> 0 | AQ56: =IF(ISBLANK(L56),0,IF(ISNUMBER(SEARCH("ML",L56)),1,0)) -> 0 | AR56: =IF(ISBLANK(L57),0,IF(ISNUMBER(SEARCH("ML",L57)),1,0)) -> 0 | AS56: =IF(ISBLANK(L58),0,IF(ISNUMBER(SEARCH("Docker",L58)),1,0)) -> 1 | AT56: =IF(ISBLANK(L58),0,IF(ISNUMBER(SEARCH("dbt",L58)),1,0)) -> 0 | AU56: =IF(ISBLANK(L58),0,IF(ISNUMBER(SEARCH("AWS",L58)),1,0)) -> 1 | AV56: =IF(ISBLANK(L58),0,IF(ISNUMBER(SEARCH("GCP",L58)),1,0)) -> 0 | AW56: =IF(ISBLANK(L58),0,IF(ISNUMBER(SEARCH("Azure",L58)),1,0)) -> 0 | AX56: =IF(ISBLANK(M58),0,IF(ISNUMBER(SEARCH("Tableau",L58)),1,0)) -> 0 | AY56: =IF(ISBLANK(N58),0,IF(ISNUMBER(SEARCH("PowerBI",L58)),1,0)) -> 0 | AZ56: Fulltime
A57: 56 | B57: 46178 | C57: LinkedIn | D57: BI Developer | E57: EXL | F57: Gurgaon | G57: ND | H57: ND | I57: ND | J57: ND | K57: Excel, SQL,DAX,ETL | L57: None | M57: On-site | N57: Large | O57: =IF(ISBLANK(K57),0,IF(ISNUMBER(SEARCH("sql",K57)),1,0)) -> 1 | P57: =IF(ISBLANK(K57),0,IF(ISNUMBER(SEARCH("Python",K57)),1,0)) -> 0 | Q57: =IF(ISBLANK(K57),0,IF(ISNUMBER(SEARCH("PowerBI",K57)),1,0)) -> 0 | R57: =IF(ISBLANK(K57),0,IF(ISNUMBER(SEARCH("Tableau",K57)),1,0)) -> 0 | S57: =IF(ISBLANK(K57),0,IF(ISNUMBER(SEARCH("Excel",K57)),1,0)) -> 1 | T57: =IF(ISBLANK(K57),0,IF(ISNUMBER(SEARCH("Statistics",K57)),1,0)) -> 0 | U57: =IF(ISBLANK(K57),0,IF(ISNUMBER(SEARCH("AWS",K57)),1,0)) -> 0 | V57: =IF(ISBLANK(K57),0,IF(ISNUMBER(SEARCH("GCP",K57)),1,0)) -> 0 | W57: =IF(ISBLANK(K57),0,IF(ISNUMBER(SEARCH("NoSQL",K57)),1,0)) -> 0 | X57: =IF(ISBLANK(K57),0,IF(ISNUMBER(SEARCH("Data Modeling",K57)),1,0)) -> 0 | Y57: =IF(ISBLANK(K57),0,IF(ISNUMBER(SEARCH("Pandas",K57)),1,0)) -> 0 | Z57: =IF(ISBLANK(K57),0,IF(ISNUMBER(SEARCH("Numpy",K57)),1,0)) -> 0 | AA57: =IF(ISBLANK(K57),0,IF(ISNUMBER(SEARCH("Pyspark",K57)),1,0)) -> 0 | AB57: =IF(ISBLANK(K57),0,IF(ISNUMBER(SEARCH("Hadoop",K57)),1,0)) -> 0 | AC57: =IF(ISBLANK(K57),0,IF(ISNUMBER(SEARCH("ETL",K57)),1,0)) -> 1 | AD57: =IF(ISBLANK(K57),0,IF(ISNUMBER(SEARCH("Azure",K57)),1,0)) -> 0 | AE57: =IF(ISBLANK(K57),0,IF(ISNUMBER(SEARCH("Databricks",K57)),1,0)) -> 0 | AF57: =IF(ISBLANK(K57),0,IF(ISNUMBER(SEARCH("A/B Testing",K57)),1,0)) -> 0 | AG57: =IF(ISBLANK(K57),0,IF(ISNUMBER(SEARCH("Snowflake",K57)),1,0)) -> 0 | AH57: =IF(ISBLANK(K57),0,IF(ISNUMBER(SEARCH("Agile",K57)),1,0)) -> 0 | AI57: =IF(ISBLANK(K57),0,IF(ISNUMBER(SEARCH("Jira",K57)),1,0)) -> 0 | AJ57: =IF(ISBLANK(K57),0,IF(ISNUMBER(SEARCH("Git",K57)),1,0)) -> 0 | AK57: =IF(ISBLANK(K57),0,IF(ISNUMBER(SEARCH("Reporting",K57)),1,0)) -> 0 | AL57: =IF(ISBLANK(K57),0,IF(ISNUMBER(SEARCH("CI/CD",K57)),1,0)) -> 0 | AM57: =IF(ISBLANK(L57),0,IF(ISNUMBER(SEARCH("Python",L57)),1,0)) -> 0 | AN57: =IF(ISBLANK(L57),0,IF(ISNUMBER(SEARCH("SQL",L57)),1,0)) -> 0 | AO57: =IF(ISBLANK(L57),0,IF(ISNUMBER(SEARCH("Airflow",L57)),1,0)) -> 0 | AP57: =IF(ISBLANK(L57),0,IF(ISNUMBER(SEARCH("Kafka",L57)),1,0)) -> 0 | AQ57: =IF(ISBLANK(L57),0,IF(ISNUMBER(SEARCH("ML",L57)),1,0)) -> 0 | AR57: =IF(ISBLANK(L58),0,IF(ISNUMBER(SEARCH("ML",L58)),1,0)) -> 0 | AS57: =IF(ISBLANK(L59),0,IF(ISNUMBER(SEARCH("Docker",L59)),1,0)) -> 0 | AT57: =IF(ISBLANK(L59),0,IF(ISNUMBER(SEARCH("dbt",L59)),1,0)) -> 0 | AU57: =IF(ISBLANK(L59),0,IF(ISNUMBER(SEARCH("AWS",L59)),1,0)) -> 0 | AV57: =IF(ISBLANK(L59),0,IF(ISNUMBER(SEARCH("GCP",L59)),1,0)) -> 0 | AW57: =IF(ISBLANK(L59),0,IF(ISNUMBER(SEARCH("Azure",L59)),1,0)) -> 0 | AX57: =IF(ISBLANK(M59),0,IF(ISNUMBER(SEARCH("Tableau",L59)),1,0)) -> 0 | AY57: =IF(ISBLANK(N59),0,IF(ISNUMBER(SEARCH("PowerBI",L59)),1,0)) -> 0 | AZ57: Fulltime
A58: 57 | B58: 46178 | C58: LinkedIn | D58: BI Developer | E58: Arth | F58: Hyderabad | G58: 3 | H58: ND | I58: ND | J58: ND | K58: PowerBI,Python,SQL, ETL | L58: Exposure to Docker, AWS deployments, or CI/CD pipelines. | M58: On-site | N58: Medium | O58: =IF(ISBLANK(K58),0,IF(ISNUMBER(SEARCH("sql",K58)),1,0)) -> 1 | P58: =IF(ISBLANK(K58),0,IF(ISNUMBER(SEARCH("Python",K58)),1,0)) -> 1 | Q58: =IF(ISBLANK(K58),0,IF(ISNUMBER(SEARCH("PowerBI",K58)),1,0)) -> 1 | R58: =IF(ISBLANK(K58),0,IF(ISNUMBER(SEARCH("Tableau",K58)),1,0)) -> 0 | S58: =IF(ISBLANK(K58),0,IF(ISNUMBER(SEARCH("Excel",K58)),1,0)) -> 0 | T58: =IF(ISBLANK(K58),0,IF(ISNUMBER(SEARCH("Statistics",K58)),1,0)) -> 0 | U58: =IF(ISBLANK(K58),0,IF(ISNUMBER(SEARCH("AWS",K58)),1,0)) -> 0 | V58: =IF(ISBLANK(K58),0,IF(ISNUMBER(SEARCH("GCP",K58)),1,0)) -> 0 | W58: =IF(ISBLANK(K58),0,IF(ISNUMBER(SEARCH("NoSQL",K58)),1,0)) -> 0 | X58: =IF(ISBLANK(K58),0,IF(ISNUMBER(SEARCH("Data Modeling",K58)),1,0)) -> 0 | Y58: =IF(ISBLANK(K58),0,IF(ISNUMBER(SEARCH("Pandas",K58)),1,0)) -> 0 | Z58: =IF(ISBLANK(K58),0,IF(ISNUMBER(SEARCH("Numpy",K58)),1,0)) -> 0 | AA58: =IF(ISBLANK(K58),0,IF(ISNUMBER(SEARCH("Pyspark",K58)),1,0)) -> 0 | AB58: =IF(ISBLANK(K58),0,IF(ISNUMBER(SEARCH("Hadoop",K58)),1,0)) -> 0 | AC58: =IF(ISBLANK(K58),0,IF(ISNUMBER(SEARCH("ETL",K58)),1,0)) -> 1 | AD58: =IF(ISBLANK(K58),0,IF(ISNUMBER(SEARCH("Azure",K58)),1,0)) -> 0 | AE58: =IF(ISBLANK(K58),0,IF(ISNUMBER(SEARCH("Databricks",K58)),1,0)) -> 0 | AF58: =IF(ISBLANK(K58),0,IF(ISNUMBER(SEARCH("A/B Testing",K58)),1,0)) -> 0 | AG58: =IF(ISBLANK(K58),0,IF(ISNUMBER(SEARCH("Snowflake",K58)),1,0)) -> 0 | AH58: =IF(ISBLANK(K58),0,IF(ISNUMBER(SEARCH("Agile",K58)),1,0)) -> 0 | AI58: =IF(ISBLANK(K58),0,IF(ISNUMBER(SEARCH("Jira",K58)),1,0)) -> 0 | AJ58: =IF(ISBLANK(K58),0,IF(ISNUMBER(SEARCH("Git",K58)),1,0)) -> 0 | AK58: =IF(ISBLANK(K58),0,IF(ISNUMBER(SEARCH("Reporting",K58)),1,0)) -> 0 | AL58: =IF(ISBLANK(K58),0,IF(ISNUMBER(SEARCH("CI/CD",K58)),1,0)) -> 0 | AM58: =IF(ISBLANK(L58),0,IF(ISNUMBER(SEARCH("Python",L58)),1,0)) -> 0 | AN58: =IF(ISBLANK(L58),0,IF(ISNUMBER(SEARCH("SQL",L58)),1,0)) -> 0 | AO58: =IF(ISBLANK(L58),0,IF(ISNUMBER(SEARCH("Airflow",L58)),1,0)) -> 0 | AP58: =IF(ISBLANK(L58),0,IF(ISNUMBER(SEARCH("Kafka",L58)),1,0)) -> 0 | AQ58: =IF(ISBLANK(L58),0,IF(ISNUMBER(SEARCH("ML",L58)),1,0)) -> 0 | AR58: =IF(ISBLANK(L59),0,IF(ISNUMBER(SEARCH("ML",L59)),1,0)) -> 0 | AS58: =IF(ISBLANK(L60),0,IF(ISNUMBER(SEARCH("Docker",L60)),1,0)) -> 0 | AT58: =IF(ISBLANK(L60),0,IF(ISNUMBER(SEARCH("dbt",L60)),1,0)) -> 0 | AU58: =IF(ISBLANK(L60),0,IF(ISNUMBER(SEARCH("AWS",L60)),1,0)) -> 0 | AV58: =IF(ISBLANK(L60),0,IF(ISNUMBER(SEARCH("GCP",L60)),1,0)) -> 0 | AW58: =IF(ISBLANK(L60),0,IF(ISNUMBER(SEARCH("Azure",L60)),1,0)) -> 0 | AX58: =IF(ISBLANK(M60),0,IF(ISNUMBER(SEARCH("Tableau",L60)),1,0)) -> 0 | AY58: =IF(ISBLANK(N60),0,IF(ISNUMBER(SEARCH("PowerBI",L60)),1,0)) -> 0 | AZ58: Fulltime
A59: 58 | B59: 46178 | C59: LinkedIn | D59: BI Developer | E59: Deloitte | F59: Bengaluru | G59: 2 | H59: 6 | I59: ND | J59: ND | K59: PowerBI , Excel,SQL , Data modeling | L59: None | M59: Hybrid | N59: Large | O59: =IF(ISBLANK(K59),0,IF(ISNUMBER(SEARCH("sql",K59)),1,0)) -> 1 | P59: =IF(ISBLANK(K59),0,IF(ISNUMBER(SEARCH("Python",K59)),1,0)) -> 0 | Q59: =IF(ISBLANK(K59),0,IF(ISNUMBER(SEARCH("PowerBI",K59)),1,0)) -> 1 | R59: =IF(ISBLANK(K59),0,IF(ISNUMBER(SEARCH("Tableau",K59)),1,0)) -> 0 | S59: =IF(ISBLANK(K59),0,IF(ISNUMBER(SEARCH("Excel",K59)),1,0)) -> 1 | T59: =IF(ISBLANK(K59),0,IF(ISNUMBER(SEARCH("Statistics",K59)),1,0)) -> 0 | U59: =IF(ISBLANK(K59),0,IF(ISNUMBER(SEARCH("AWS",K59)),1,0)) -> 0 | V59: =IF(ISBLANK(K59),0,IF(ISNUMBER(SEARCH("GCP",K59)),1,0)) -> 0 | W59: =IF(ISBLANK(K59),0,IF(ISNUMBER(SEARCH("NoSQL",K59)),1,0)) -> 0 | X59: =IF(ISBLANK(K59),0,IF(ISNUMBER(SEARCH("Data Modeling",K59)),1,0)) -> 1 | Y59: =IF(ISBLANK(K59),0,IF(ISNUMBER(SEARCH("Pandas",K59)),1,0)) -> 0 | Z59: =IF(ISBLANK(K59),0,IF(ISNUMBER(SEARCH("Numpy",K59)),1,0)) -> 0 | AA59: =IF(ISBLANK(K59),0,IF(ISNUMBER(SEARCH("Pyspark",K59)),1,0)) -> 0 | AB59: =IF(ISBLANK(K59),0,IF(ISNUMBER(SEARCH("Hadoop",K59)),1,0)) -> 0 | AC59: =IF(ISBLANK(K59),0,IF(ISNUMBER(SEARCH("ETL",K59)),1,0)) -> 0 | AD59: =IF(ISBLANK(K59),0,IF(ISNUMBER(SEARCH("Azure",K59)),1,0)) -> 0 | AE59: =IF(ISBLANK(K59),0,IF(ISNUMBER(SEARCH("Databricks",K59)),1,0)) -> 0 | AF59: =IF(ISBLANK(K59),0,IF(ISNUMBER(SEARCH("A/B Testing",K59)),1,0)) -> 0 | AG59: =IF(ISBLANK(K59),0,IF(ISNUMBER(SEARCH("Snowflake",K59)),1,0)) -> 0 | AH59: =IF(ISBLANK(K59),0,IF(ISNUMBER(SEARCH("Agile",K59)),1,0)) -> 0 | AI59: =IF(ISBLANK(K59),0,IF(ISNUMBER(SEARCH("Jira",K59)),1,0)) -> 0 | AJ59: =IF(ISBLANK(K59),0,IF(ISNUMBER(SEARCH("Git",K59)),1,0)) -> 0 | AK59: =IF(ISBLANK(K59),0,IF(ISNUMBER(SEARCH("Reporting",K59)),1,0)) -> 0 | AL59: =IF(ISBLANK(K59),0,IF(ISNUMBER(SEARCH("CI/CD",K59)),1,0)) -> 0 | AM59: =IF(ISBLANK(L59),0,IF(ISNUMBER(SEARCH("Python",L59)),1,0)) -> 0 | AN59: =IF(ISBLANK(L59),0,IF(ISNUMBER(SEARCH("SQL",L59)),1,0)) -> 0 | AO59: =IF(ISBLANK(L59),0,IF(ISNUMBER(SEARCH("Airflow",L59)),1,0)) -> 0 | AP59: =IF(ISBLANK(L59),0,IF(ISNUMBER(SEARCH("Kafka",L59)),1,0)) -> 0 | AQ59: =IF(ISBLANK(L59),0,IF(ISNUMBER(SEARCH("ML",L59)),1,0)) -> 0 | AR59: =IF(ISBLANK(L60),0,IF(ISNUMBER(SEARCH("ML",L60)),1,0)) -> 0 | AS59: =IF(ISBLANK(L61),0,IF(ISNUMBER(SEARCH("Docker",L61)),1,0)) -> 0 | AT59: =IF(ISBLANK(L61),0,IF(ISNUMBER(SEARCH("dbt",L61)),1,0)) -> 0 | AU59: =IF(ISBLANK(L61),0,IF(ISNUMBER(SEARCH("AWS",L61)),1,0)) -> 0 | AV59: =IF(ISBLANK(L61),0,IF(ISNUMBER(SEARCH("GCP",L61)),1,0)) -> 0 | AW59: =IF(ISBLANK(L61),0,IF(ISNUMBER(SEARCH("Azure",L61)),1,0)) -> 0 | AX59: =IF(ISBLANK(M61),0,IF(ISNUMBER(SEARCH("Tableau",L61)),1,0)) -> 0 | AY59: =IF(ISBLANK(N61),0,IF(ISNUMBER(SEARCH("PowerBI",L61)),1,0)) -> 0 | AZ59: Fulltime
A60: 59 | B60: 46178 | C60: LinkedIn | D60: MIS Analyst | E60: NES Fircroft | F60: Bengaluru | G60: 1 | H60: 2 | I60: ND | J60: ND | K60: Excel, Financial data analysis | L60: None | M60: On-site | N60: Small | O60: =IF(ISBLANK(K60),0,IF(ISNUMBER(SEARCH("sql",K60)),1,0)) -> 0 | P60: =IF(ISBLANK(K60),0,IF(ISNUMBER(SEARCH("Python",K60)),1,0)) -> 0 | Q60: =IF(ISBLANK(K60),0,IF(ISNUMBER(SEARCH("PowerBI",K60)),1,0)) -> 0 | R60: =IF(ISBLANK(K60),0,IF(ISNUMBER(SEARCH("Tableau",K60)),1,0)) -> 0 | S60: =IF(ISBLANK(K60),0,IF(ISNUMBER(SEARCH("Excel",K60)),1,0)) -> 1 | T60: =IF(ISBLANK(K60),0,IF(ISNUMBER(SEARCH("Statistics",K60)),1,0)) -> 0 | U60: =IF(ISBLANK(K60),0,IF(ISNUMBER(SEARCH("AWS",K60)),1,0)) -> 0 | V60: =IF(ISBLANK(K60),0,IF(ISNUMBER(SEARCH("GCP",K60)),1,0)) -> 0 | W60: =IF(ISBLANK(K60),0,IF(ISNUMBER(SEARCH("NoSQL",K60)),1,0)) -> 0 | X60: =IF(ISBLANK(K60),0,IF(ISNUMBER(SEARCH("Data Modeling",K60)),1,0)) -> 0 | Y60: =IF(ISBLANK(K60),0,IF(ISNUMBER(SEARCH("Pandas",K60)),1,0)) -> 0 | Z60: =IF(ISBLANK(K60),0,IF(ISNUMBER(SEARCH("Numpy",K60)),1,0)) -> 0 | AA60: =IF(ISBLANK(K60),0,IF(ISNUMBER(SEARCH("Pyspark",K60)),1,0)) -> 0 | AB60: =IF(ISBLANK(K60),0,IF(ISNUMBER(SEARCH("Hadoop",K60)),1,0)) -> 0 | AC60: =IF(ISBLANK(K60),0,IF(ISNUMBER(SEARCH("ETL",K60)),1,0)) -> 0 | AD60: =IF(ISBLANK(K60),0,IF(ISNUMBER(SEARCH("Azure",K60)),1,0)) -> 0 | AE60: =IF(ISBLANK(K60),0,IF(ISNUMBER(SEARCH("Databricks",K60)),1,0)) -> 0 | AF60: =IF(ISBLANK(K60),0,IF(ISNUMBER(SEARCH("A/B Testing",K60)),1,0)) -> 0 | AG60: =IF(ISBLANK(K60),0,IF(ISNUMBER(SEARCH("Snowflake",K60)),1,0)) -> 0 | AH60: =IF(ISBLANK(K60),0,IF(ISNUMBER(SEARCH("Agile",K60)),1,0)) -> 0 | AI60: =IF(ISBLANK(K60),0,IF(ISNUMBER(SEARCH("Jira",K60)),1,0)) -> 0 | AJ60: =IF(ISBLANK(K60),0,IF(ISNUMBER(SEARCH("Git",K60)),1,0)) -> 0 | AK60: =IF(ISBLANK(K60),0,IF(ISNUMBER(SEARCH("Reporting",K60)),1,0)) -> 0 | AL60: =IF(ISBLANK(K60),0,IF(ISNUMBER(SEARCH("CI/CD",K60)),1,0)) -> 0 | AM60: =IF(ISBLANK(L60),0,IF(ISNUMBER(SEARCH("Python",L60)),1,0)) -> 0 | AN60: =IF(ISBLANK(L60),0,IF(ISNUMBER(SEARCH("SQL",L60)),1,0)) -> 0 | AO60: =IF(ISBLANK(L60),0,IF(ISNUMBER(SEARCH("Airflow",L60)),1,0)) -> 0 | AP60: =IF(ISBLANK(L60),0,IF(ISNUMBER(SEARCH("Kafka",L60)),1,0)) -> 0 | AQ60: =IF(ISBLANK(L60),0,IF(ISNUMBER(SEARCH("ML",L60)),1,0)) -> 0 | AR60: =IF(ISBLANK(L61),0,IF(ISNUMBER(SEARCH("ML",L61)),1,0)) -> 0 | AS60: =IF(ISBLANK(L62),0,IF(ISNUMBER(SEARCH("Docker",L62)),1,0)) -> 0 | AT60: =IF(ISBLANK(L62),0,IF(ISNUMBER(SEARCH("dbt",L62)),1,0)) -> 1 | AU60: =IF(ISBLANK(L62),0,IF(ISNUMBER(SEARCH("AWS",L62)),1,0)) -> 0 | AV60: =IF(ISBLANK(L62),0,IF(ISNUMBER(SEARCH("GCP",L62)),1,0)) -> 0 | AW60: =IF(ISBLANK(L62),0,IF(ISNUMBER(SEARCH("Azure",L62)),1,0)) -> 0 | AX60: =IF(ISBLANK(M62),0,IF(ISNUMBER(SEARCH("Tableau",L62)),1,0)) -> 0 | AY60: =IF(ISBLANK(N62),0,IF(ISNUMBER(SEARCH("PowerBI",L62)),1,0)) -> 0 | AZ60: Fulltime
A61: 60 | B61: 46178 | C61: LinkedIn | D61: BI Developer | E61: GlobalFoundries | F61: Bengaluru | G61: 2 | H61: 4 | I61: ND | J61: ND | K61: SQL, PowerBI | L61: DBMS , Cloud native database technologies | M61: On-site | N61: Large | O61: =IF(ISBLANK(K61),0,IF(ISNUMBER(SEARCH("sql",K61)),1,0)) -> 1 | P61: =IF(ISBLANK(K61),0,IF(ISNUMBER(SEARCH("Python",K61)),1,0)) -> 0 | Q61: =IF(ISBLANK(K61),0,IF(ISNUMBER(SEARCH("PowerBI",K61)),1,0)) -> 1 | R61: =IF(ISBLANK(K61),0,IF(ISNUMBER(SEARCH("Tableau",K61)),1,0)) -> 0 | S61: =IF(ISBLANK(K61),0,IF(ISNUMBER(SEARCH("Excel",K61)),1,0)) -> 0 | T61: =IF(ISBLANK(K61),0,IF(ISNUMBER(SEARCH("Statistics",K61)),1,0)) -> 0 | U61: =IF(ISBLANK(K61),0,IF(ISNUMBER(SEARCH("AWS",K61)),1,0)) -> 0 | V61: =IF(ISBLANK(K61),0,IF(ISNUMBER(SEARCH("GCP",K61)),1,0)) -> 0 | W61: =IF(ISBLANK(K61),0,IF(ISNUMBER(SEARCH("NoSQL",K61)),1,0)) -> 0 | X61: =IF(ISBLANK(K61),0,IF(ISNUMBER(SEARCH("Data Modeling",K61)),1,0)) -> 0 | Y61: =IF(ISBLANK(K61),0,IF(ISNUMBER(SEARCH("Pandas",K61)),1,0)) -> 0 | Z61: =IF(ISBLANK(K61),0,IF(ISNUMBER(SEARCH("Numpy",K61)),1,0)) -> 0 | AA61: =IF(ISBLANK(K61),0,IF(ISNUMBER(SEARCH("Pyspark",K61)),1,0)) -> 0 | AB61: =IF(ISBLANK(K61),0,IF(ISNUMBER(SEARCH("Hadoop",K61)),1,0)) -> 0 | AC61: =IF(ISBLANK(K61),0,IF(ISNUMBER(SEARCH("ETL",K61)),1,0)) -> 0 | AD61: =IF(ISBLANK(K61),0,IF(ISNUMBER(SEARCH("Azure",K61)),1,0)) -> 0 | AE61: =IF(ISBLANK(K61),0,IF(ISNUMBER(SEARCH("Databricks",K61)),1,0)) -> 0 | AF61: =IF(ISBLANK(K61),0,IF(ISNUMBER(SEARCH("A/B Testing",K61)),1,0)) -> 0 | AG61: =IF(ISBLANK(K61),0,IF(ISNUMBER(SEARCH("Snowflake",K61)),1,0)) -> 0 | AH61: =IF(ISBLANK(K61),0,IF(ISNUMBER(SEARCH("Agile",K61)),1,0)) -> 0 | AI61: =IF(ISBLANK(K61),0,IF(ISNUMBER(SEARCH("Jira",K61)),1,0)) -> 0 | AJ61: =IF(ISBLANK(K61),0,IF(ISNUMBER(SEARCH("Git",K61)),1,0)) -> 0 | AK61: =IF(ISBLANK(K61),0,IF(ISNUMBER(SEARCH("Reporting",K61)),1,0)) -> 0 | AL61: =IF(ISBLANK(K61),0,IF(ISNUMBER(SEARCH("CI/CD",K61)),1,0)) -> 0 | AM61: =IF(ISBLANK(L61),0,IF(ISNUMBER(SEARCH("Python",L61)),1,0)) -> 0 | AN61: =IF(ISBLANK(L61),0,IF(ISNUMBER(SEARCH("SQL",L61)),1,0)) -> 0 | AO61: =IF(ISBLANK(L61),0,IF(ISNUMBER(SEARCH("Airflow",L61)),1,0)) -> 0 | AP61: =IF(ISBLANK(L61),0,IF(ISNUMBER(SEARCH("Kafka",L61)),1,0)) -> 0 | AQ61: =IF(ISBLANK(L61),0,IF(ISNUMBER(SEARCH("ML",L61)),1,0)) -> 0 | AR61: =IF(ISBLANK(L62),0,IF(ISNUMBER(SEARCH("ML",L62)),1,0)) -> 0 | AS61: =IF(ISBLANK(L63),0,IF(ISNUMBER(SEARCH("Docker",L63)),1,0)) -> 0 | AT61: =IF(ISBLANK(L63),0,IF(ISNUMBER(SEARCH("dbt",L63)),1,0)) -> 0 | AU61: =IF(ISBLANK(L63),0,IF(ISNUMBER(SEARCH("AWS",L63)),1,0)) -> 0 | AV61: =IF(ISBLANK(L63),0,IF(ISNUMBER(SEARCH("GCP",L63)),1,0)) -> 0 | AW61: =IF(ISBLANK(L63),0,IF(ISNUMBER(SEARCH("Azure",L63)),1,0)) -> 0 | AX61: =IF(ISBLANK(M63),0,IF(ISNUMBER(SEARCH("Tableau",L63)),1,0)) -> 0 | AY61: =IF(ISBLANK(N63),0,IF(ISNUMBER(SEARCH("PowerBI",L63)),1,0)) -> 0 | AZ61: Fulltime
A62: 61 | B62: 46178 | C62: LinkedIn | D62: Business Analyst | E62: Blissclub | F62: Bengaluru | G62: 2 | H62: 4 | I62: ND | J62: ND | K62: SQL,PowerBi or equivalent | L62: Understanding of performance marketing analytics,dbt, Pandas | M62: On-site | N62: Startup | O62: =IF(ISBLANK(K62),0,IF(ISNUMBER(SEARCH("sql",K62)),1,0)) -> 1 | P62: =IF(ISBLANK(K62),0,IF(ISNUMBER(SEARCH("Python",K62)),1,0)) -> 0 | Q62: =IF(ISBLANK(K62),0,IF(ISNUMBER(SEARCH("PowerBI",K62)),1,0)) -> 1 | R62: =IF(ISBLANK(K62),0,IF(ISNUMBER(SEARCH("Tableau",K62)),1,0)) -> 0 | S62: =IF(ISBLANK(K62),0,IF(ISNUMBER(SEARCH("Excel",K62)),1,0)) -> 0 | T62: =IF(ISBLANK(K62),0,IF(ISNUMBER(SEARCH("Statistics",K62)),1,0)) -> 0 | U62: =IF(ISBLANK(K62),0,IF(ISNUMBER(SEARCH("AWS",K62)),1,0)) -> 0 | V62: =IF(ISBLANK(K62),0,IF(ISNUMBER(SEARCH("GCP",K62)),1,0)) -> 0 | W62: =IF(ISBLANK(K62),0,IF(ISNUMBER(SEARCH("NoSQL",K62)),1,0)) -> 0 | X62: =IF(ISBLANK(K62),0,IF(ISNUMBER(SEARCH("Data Modeling",K62)),1,0)) -> 0 | Y62: =IF(ISBLANK(K62),0,IF(ISNUMBER(SEARCH("Pandas",K62)),1,0)) -> 0 | Z62: =IF(ISBLANK(K62),0,IF(ISNUMBER(SEARCH("Numpy",K62)),1,0)) -> 0 | AA62: =IF(ISBLANK(K62),0,IF(ISNUMBER(SEARCH("Pyspark",K62)),1,0)) -> 0 | AB62: =IF(ISBLANK(K62),0,IF(ISNUMBER(SEARCH("Hadoop",K62)),1,0)) -> 0 | AC62: =IF(ISBLANK(K62),0,IF(ISNUMBER(SEARCH("ETL",K62)),1,0)) -> 0 | AD62: =IF(ISBLANK(K62),0,IF(ISNUMBER(SEARCH("Azure",K62)),1,0)) -> 0 | AE62: =IF(ISBLANK(K62),0,IF(ISNUMBER(SEARCH("Databricks",K62)),1,0)) -> 0 | AF62: =IF(ISBLANK(K62),0,IF(ISNUMBER(SEARCH("A/B Testing",K62)),1,0)) -> 0 | AG62: =IF(ISBLANK(K62),0,IF(ISNUMBER(SEARCH("Snowflake",K62)),1,0)) -> 0 | AH62: =IF(ISBLANK(K62),0,IF(ISNUMBER(SEARCH("Agile",K62)),1,0)) -> 0 | AI62: =IF(ISBLANK(K62),0,IF(ISNUMBER(SEARCH("Jira",K62)),1,0)) -> 0 | AJ62: =IF(ISBLANK(K62),0,IF(ISNUMBER(SEARCH("Git",K62)),1,0)) -> 0 | AK62: =IF(ISBLANK(K62),0,IF(ISNUMBER(SEARCH("Reporting",K62)),1,0)) -> 0 | AL62: =IF(ISBLANK(K62),0,IF(ISNUMBER(SEARCH("CI/CD",K62)),1,0)) -> 0 | AM62: =IF(ISBLANK(L62),0,IF(ISNUMBER(SEARCH("Python",L62)),1,0)) -> 0 | AN62: =IF(ISBLANK(L62),0,IF(ISNUMBER(SEARCH("SQL",L62)),1,0)) -> 0 | AO62: =IF(ISBLANK(L62),0,IF(ISNUMBER(SEARCH("Airflow",L62)),1,0)) -> 0 | AP62: =IF(ISBLANK(L62),0,IF(ISNUMBER(SEARCH("Kafka",L62)),1,0)) -> 0 | AQ62: =IF(ISBLANK(L62),0,IF(ISNUMBER(SEARCH("ML",L62)),1,0)) -> 0 | AR62: =IF(ISBLANK(L63),0,IF(ISNUMBER(SEARCH("ML",L63)),1,0)) -> 0 | AS62: =IF(ISBLANK(L64),0,IF(ISNUMBER(SEARCH("Docker",L64)),1,0)) -> 0 | AT62: =IF(ISBLANK(L64),0,IF(ISNUMBER(SEARCH("dbt",L64)),1,0)) -> 0 | AU62: =IF(ISBLANK(L64),0,IF(ISNUMBER(SEARCH("AWS",L64)),1,0)) -> 0 | AV62: =IF(ISBLANK(L64),0,IF(ISNUMBER(SEARCH("GCP",L64)),1,0)) -> 0 | AW62: =IF(ISBLANK(L64),0,IF(ISNUMBER(SEARCH("Azure",L64)),1,0)) -> 0 | AX62: =IF(ISBLANK(M64),0,IF(ISNUMBER(SEARCH("Tableau",L64)),1,0)) -> 0 | AY62: =IF(ISBLANK(N64),0,IF(ISNUMBER(SEARCH("PowerBI",L64)),1,0)) -> 0 | AZ62: Fulltime
A63: 62 | B63: 46178 | C63: LinkedIn | D63: BI Developer | E63: SBA Insights | F63: Bengaluru | G63: ND | H63: ND | I63: ND | J63: ND | K63: PowerBI, Data warehousing, ETL | L63: Familiarity with Power Automate and Copilot is a plus | M63: On-site | N63: Small | O63: =IF(ISBLANK(K63),0,IF(ISNUMBER(SEARCH("sql",K63)),1,0)) -> 0 | P63: =IF(ISBLANK(K63),0,IF(ISNUMBER(SEARCH("Python",K63)),1,0)) -> 0 | Q63: =IF(ISBLANK(K63),0,IF(ISNUMBER(SEARCH("PowerBI",K63)),1,0)) -> 1 | R63: =IF(ISBLANK(K63),0,IF(ISNUMBER(SEARCH("Tableau",K63)),1,0)) -> 0 | S63: =IF(ISBLANK(K63),0,IF(ISNUMBER(SEARCH("Excel",K63)),1,0)) -> 0 | T63: =IF(ISBLANK(K63),0,IF(ISNUMBER(SEARCH("Statistics",K63)),1,0)) -> 0 | U63: =IF(ISBLANK(K63),0,IF(ISNUMBER(SEARCH("AWS",K63)),1,0)) -> 0 | V63: =IF(ISBLANK(K63),0,IF(ISNUMBER(SEARCH("GCP",K63)),1,0)) -> 0 | W63: =IF(ISBLANK(K63),0,IF(ISNUMBER(SEARCH("NoSQL",K63)),1,0)) -> 0 | X63: =IF(ISBLANK(K63),0,IF(ISNUMBER(SEARCH("Data Modeling",K63)),1,0)) -> 0 | Y63: =IF(ISBLANK(K63),0,IF(ISNUMBER(SEARCH("Pandas",K63)),1,0)) -> 0 | Z63: =IF(ISBLANK(K63),0,IF(ISNUMBER(SEARCH("Numpy",K63)),1,0)) -> 0 | AA63: =IF(ISBLANK(K63),0,IF(ISNUMBER(SEARCH("Pyspark",K63)),1,0)) -> 0 | AB63: =IF(ISBLANK(K63),0,IF(ISNUMBER(SEARCH("Hadoop",K63)),1,0)) -> 0 | AC63: =IF(ISBLANK(K63),0,IF(ISNUMBER(SEARCH("ETL",K63)),1,0)) -> 1 | AD63: =IF(ISBLANK(K63),0,IF(ISNUMBER(SEARCH("Azure",K63)),1,0)) -> 0 | AE63: =IF(ISBLANK(K63),0,IF(ISNUMBER(SEARCH("Databricks",K63)),1,0)) -> 0 | AF63: =IF(ISBLANK(K63),0,IF(ISNUMBER(SEARCH("A/B Testing",K63)),1,0)) -> 0 | AG63: =IF(ISBLANK(K63),0,IF(ISNUMBER(SEARCH("Snowflake",K63)),1,0)) -> 0 | AH63: =IF(ISBLANK(K63),0,IF(ISNUMBER(SEARCH("Agile",K63)),1,0)) -> 0 | AI63: =IF(ISBLANK(K63),0,IF(ISNUMBER(SEARCH("Jira",K63)),1,0)) -> 0 | AJ63: =IF(ISBLANK(K63),0,IF(ISNUMBER(SEARCH("Git",K63)),1,0)) -> 0 | AK63: =IF(ISBLANK(K63),0,IF(ISNUMBER(SEARCH("Reporting",K63)),1,0)) -> 0 | AL63: =IF(ISBLANK(K63),0,IF(ISNUMBER(SEARCH("CI/CD",K63)),1,0)) -> 0 | AM63: =IF(ISBLANK(L63),0,IF(ISNUMBER(SEARCH("Python",L63)),1,0)) -> 0 | AN63: =IF(ISBLANK(L63),0,IF(ISNUMBER(SEARCH("SQL",L63)),1,0)) -> 0 | AO63: =IF(ISBLANK(L63),0,IF(ISNUMBER(SEARCH("Airflow",L63)),1,0)) -> 0 | AP63: =IF(ISBLANK(L63),0,IF(ISNUMBER(SEARCH("Kafka",L63)),1,0)) -> 0 | AQ63: =IF(ISBLANK(L63),0,IF(ISNUMBER(SEARCH("ML",L63)),1,0)) -> 0 | AR63: =IF(ISBLANK(L64),0,IF(ISNUMBER(SEARCH("ML",L64)),1,0)) -> 1 | AS63: =IF(ISBLANK(L65),0,IF(ISNUMBER(SEARCH("Docker",L65)),1,0)) -> 0 | AT63: =IF(ISBLANK(L65),0,IF(ISNUMBER(SEARCH("dbt",L65)),1,0)) -> 0 | AU63: =IF(ISBLANK(L65),0,IF(ISNUMBER(SEARCH("AWS",L65)),1,0)) -> 0 | AV63: =IF(ISBLANK(L65),0,IF(ISNUMBER(SEARCH("GCP",L65)),1,0)) -> 0 | AW63: =IF(ISBLANK(L65),0,IF(ISNUMBER(SEARCH("Azure",L65)),1,0)) -> 0 | AX63: =IF(ISBLANK(M65),0,IF(ISNUMBER(SEARCH("Tableau",L65)),1,0)) -> 0 | AY63: =IF(ISBLANK(N65),0,IF(ISNUMBER(SEARCH("PowerBI",L65)),1,0)) -> 0 | AZ63: Fulltime
A64: 63 | B64: 46178 | C64: LinkedIn | D64: BI Developer | E64: Thermo Fisher Scientific | F64: Bengaluru | G64: 1 | H64: 5 | I64: ND | J64: ND | K64: PowerBI, SQL, Agile Development | L64: Exposure to Databricks or Python , Knowledge of AI/ML use cases is preferred | M64: On-site | N64: Large | O64: =IF(ISBLANK(K64),0,IF(ISNUMBER(SEARCH("sql",K64)),1,0)) -> 1 | P64: =IF(ISBLANK(K64),0,IF(ISNUMBER(SEARCH("Python",K64)),1,0)) -> 0 | Q64: =IF(ISBLANK(K64),0,IF(ISNUMBER(SEARCH("PowerBI",K64)),1,0)) -> 1 | R64: =IF(ISBLANK(K64),0,IF(ISNUMBER(SEARCH("Tableau",K64)),1,0)) -> 0 | S64: =IF(ISBLANK(K64),0,IF(ISNUMBER(SEARCH("Excel",K64)),1,0)) -> 0 | T64: =IF(ISBLANK(K64),0,IF(ISNUMBER(SEARCH("Statistics",K64)),1,0)) -> 0 | U64: =IF(ISBLANK(K64),0,IF(ISNUMBER(SEARCH("AWS",K64)),1,0)) -> 0 | V64: =IF(ISBLANK(K64),0,IF(ISNUMBER(SEARCH("GCP",K64)),1,0)) -> 0 | W64: =IF(ISBLANK(K64),0,IF(ISNUMBER(SEARCH("NoSQL",K64)),1,0)) -> 0 | X64: =IF(ISBLANK(K64),0,IF(ISNUMBER(SEARCH("Data Modeling",K64)),1,0)) -> 0 | Y64: =IF(ISBLANK(K64),0,IF(ISNUMBER(SEARCH("Pandas",K64)),1,0)) -> 0 | Z64: =IF(ISBLANK(K64),0,IF(ISNUMBER(SEARCH("Numpy",K64)),1,0)) -> 0 | AA64: =IF(ISBLANK(K64),0,IF(ISNUMBER(SEARCH("Pyspark",K64)),1,0)) -> 0 | AB64: =IF(ISBLANK(K64),0,IF(ISNUMBER(SEARCH("Hadoop",K64)),1,0)) -> 0 | AC64: =IF(ISBLANK(K64),0,IF(ISNUMBER(SEARCH("ETL",K64)),1,0)) -> 0 | AD64: =IF(ISBLANK(K64),0,IF(ISNUMBER(SEARCH("Azure",K64)),1,0)) -> 0 | AE64: =IF(ISBLANK(K64),0,IF(ISNUMBER(SEARCH("Databricks",K64)),1,0)) -> 0 | AF64: =IF(ISBLANK(K64),0,IF(ISNUMBER(SEARCH("A/B Testing",K64)),1,0)) -> 0 | AG64: =IF(ISBLANK(K64),0,IF(ISNUMBER(SEARCH("Snowflake",K64)),1,0)) -> 0 | AH64: =IF(ISBLANK(K64),0,IF(ISNUMBER(SEARCH("Agile",K64)),1,0)) -> 1 | AI64: =IF(ISBLANK(K64),0,IF(ISNUMBER(SEARCH("Jira",K64)),1,0)) -> 0 | AJ64: =IF(ISBLANK(K64),0,IF(ISNUMBER(SEARCH("Git",K64)),1,0)) -> 0 | AK64: =IF(ISBLANK(K64),0,IF(ISNUMBER(SEARCH("Reporting",K64)),1,0)) -> 0 | AL64: =IF(ISBLANK(K64),0,IF(ISNUMBER(SEARCH("CI/CD",K64)),1,0)) -> 0 | AM64: =IF(ISBLANK(L64),0,IF(ISNUMBER(SEARCH("Python",L64)),1,0)) -> 1 | AN64: =IF(ISBLANK(L64),0,IF(ISNUMBER(SEARCH("SQL",L64)),1,0)) -> 0 | AO64: =IF(ISBLANK(L64),0,IF(ISNUMBER(SEARCH("Airflow",L64)),1,0)) -> 0 | AP64: =IF(ISBLANK(L64),0,IF(ISNUMBER(SEARCH("Kafka",L64)),1,0)) -> 0 | AQ64: =IF(ISBLANK(L64),0,IF(ISNUMBER(SEARCH("ML",L64)),1,0)) -> 1 | AR64: =IF(ISBLANK(L65),0,IF(ISNUMBER(SEARCH("ML",L65)),1,0)) -> 0 | AS64: =IF(ISBLANK(L66),0,IF(ISNUMBER(SEARCH("Docker",L66)),1,0)) -> 0 | AT64: =IF(ISBLANK(L66),0,IF(ISNUMBER(SEARCH("dbt",L66)),1,0)) -> 0 | AU64: =IF(ISBLANK(L66),0,IF(ISNUMBER(SEARCH("AWS",L66)),1,0)) -> 0 | AV64: =IF(ISBLANK(L66),0,IF(ISNUMBER(SEARCH("GCP",L66)),1,0)) -> 0 | AW64: =IF(ISBLANK(L66),0,IF(ISNUMBER(SEARCH("Azure",L66)),1,0)) -> 0 | AX64: =IF(ISBLANK(M66),0,IF(ISNUMBER(SEARCH("Tableau",L66)),1,0)) -> 0 | AY64: =IF(ISBLANK(N66),0,IF(ISNUMBER(SEARCH("PowerBI",L66)),1,0)) -> 0 | AZ64: Fulltime
A65: 64 | B65: 46178 | C65: LinkedIn | D65: Data Analyst | E65: Skan AI | F65: Bengaluru | G65: 6 | H65: ND | I65: ND | J65: ND | K65: Databricks/Snowflake , Power BI,SQL | L65: None | M65: On-site | N65: Small | O65: =IF(ISBLANK(K65),0,IF(ISNUMBER(SEARCH("sql",K65)),1,0)) -> 1 | P65: =IF(ISBLANK(K65),0,IF(ISNUMBER(SEARCH("Python",K65)),1,0)) -> 0 | Q65: =IF(ISBLANK(K65),0,IF(ISNUMBER(SEARCH("PowerBI",K65)),1,0)) -> 0 | R65: =IF(ISBLANK(K65),0,IF(ISNUMBER(SEARCH("Tableau",K65)),1,0)) -> 0 | S65: =IF(ISBLANK(K65),0,IF(ISNUMBER(SEARCH("Excel",K65)),1,0)) -> 0 | T65: =IF(ISBLANK(K65),0,IF(ISNUMBER(SEARCH("Statistics",K65)),1,0)) -> 0 | U65: =IF(ISBLANK(K65),0,IF(ISNUMBER(SEARCH("AWS",K65)),1,0)) -> 0 | V65: =IF(ISBLANK(K65),0,IF(ISNUMBER(SEARCH("GCP",K65)),1,0)) -> 0 | W65: =IF(ISBLANK(K65),0,IF(ISNUMBER(SEARCH("NoSQL",K65)),1,0)) -> 0 | X65: =IF(ISBLANK(K65),0,IF(ISNUMBER(SEARCH("Data Modeling",K65)),1,0)) -> 0 | Y65: =IF(ISBLANK(K65),0,IF(ISNUMBER(SEARCH("Pandas",K65)),1,0)) -> 0 | Z65: =IF(ISBLANK(K65),0,IF(ISNUMBER(SEARCH("Numpy",K65)),1,0)) -> 0 | AA65: =IF(ISBLANK(K65),0,IF(ISNUMBER(SEARCH("Pyspark",K65)),1,0)) -> 0 | AB65: =IF(ISBLANK(K65),0,IF(ISNUMBER(SEARCH("Hadoop",K65)),1,0)) -> 0 | AC65: =IF(ISBLANK(K65),0,IF(ISNUMBER(SEARCH("ETL",K65)),1,0)) -> 0 | AD65: =IF(ISBLANK(K65),0,IF(ISNUMBER(SEARCH("Azure",K65)),1,0)) -> 0 | AE65: =IF(ISBLANK(K65),0,IF(ISNUMBER(SEARCH("Databricks",K65)),1,0)) -> 1 | AF65: =IF(ISBLANK(K65),0,IF(ISNUMBER(SEARCH("A/B Testing",K65)),1,0)) -> 0 | AG65: =IF(ISBLANK(K65),0,IF(ISNUMBER(SEARCH("Snowflake",K65)),1,0)) -> 1 | AH65: =IF(ISBLANK(K65),0,IF(ISNUMBER(SEARCH("Agile",K65)),1,0)) -> 0 | AI65: =IF(ISBLANK(K65),0,IF(ISNUMBER(SEARCH("Jira",K65)),1,0)) -> 0 | AJ65: =IF(ISBLANK(K65),0,IF(ISNUMBER(SEARCH("Git",K65)),1,0)) -> 0 | AK65: =IF(ISBLANK(K65),0,IF(ISNUMBER(SEARCH("Reporting",K65)),1,0)) -> 0 | AL65: =IF(ISBLANK(K65),0,IF(ISNUMBER(SEARCH("CI/CD",K65)),1,0)) -> 0 | AM65: =IF(ISBLANK(L65),0,IF(ISNUMBER(SEARCH("Python",L65)),1,0)) -> 0 | AN65: =IF(ISBLANK(L65),0,IF(ISNUMBER(SEARCH("SQL",L65)),1,0)) -> 0 | AO65: =IF(ISBLANK(L65),0,IF(ISNUMBER(SEARCH("Airflow",L65)),1,0)) -> 0 | AP65: =IF(ISBLANK(L65),0,IF(ISNUMBER(SEARCH("Kafka",L65)),1,0)) -> 0 | AQ65: =IF(ISBLANK(L65),0,IF(ISNUMBER(SEARCH("ML",L65)),1,0)) -> 0 | AR65: =IF(ISBLANK(L66),0,IF(ISNUMBER(SEARCH("ML",L66)),1,0)) -> 0 | AS65: =IF(ISBLANK(L67),0,IF(ISNUMBER(SEARCH("Docker",L67)),1,0)) -> 0 | AT65: =IF(ISBLANK(L67),0,IF(ISNUMBER(SEARCH("dbt",L67)),1,0)) -> 0 | AU65: =IF(ISBLANK(L67),0,IF(ISNUMBER(SEARCH("AWS",L67)),1,0)) -> 0 | AV65: =IF(ISBLANK(L67),0,IF(ISNUMBER(SEARCH("GCP",L67)),1,0)) -> 0 | AW65: =IF(ISBLANK(L67),0,IF(ISNUMBER(SEARCH("Azure",L67)),1,0)) -> 1 | AX65: =IF(ISBLANK(M67),0,IF(ISNUMBER(SEARCH("Tableau",L67)),1,0)) -> 0 | AY65: =IF(ISBLANK(N67),0,IF(ISNUMBER(SEARCH("PowerBI",L67)),1,0)) -> 0 | AZ65: Fulltime
A66: 65 | B66: 46178 | C66: LinkedIn | D66: BI Developer | E66: Experian | F66: Hyderabad | G66: ND | H66: ND | I66: ND | J66: ND | K66: Oracle Services, SQL, Unix scripts | L66: None | M66: On-site | N66: Small | O66: =IF(ISBLANK(K66),0,IF(ISNUMBER(SEARCH("sql",K66)),1,0)) -> 1 | P66: =IF(ISBLANK(K66),0,IF(ISNUMBER(SEARCH("Python",K66)),1,0)) -> 0 | Q66: =IF(ISBLANK(K66),0,IF(ISNUMBER(SEARCH("PowerBI",K66)),1,0)) -> 0 | R66: =IF(ISBLANK(K66),0,IF(ISNUMBER(SEARCH("Tableau",K66)),1,0)) -> 0 | S66: =IF(ISBLANK(K66),0,IF(ISNUMBER(SEARCH("Excel",K66)),1,0)) -> 0 | T66: =IF(ISBLANK(K66),0,IF(ISNUMBER(SEARCH("Statistics",K66)),1,0)) -> 0 | U66: =IF(ISBLANK(K66),0,IF(ISNUMBER(SEARCH("AWS",K66)),1,0)) -> 0 | V66: =IF(ISBLANK(K66),0,IF(ISNUMBER(SEARCH("GCP",K66)),1,0)) -> 0 | W66: =IF(ISBLANK(K66),0,IF(ISNUMBER(SEARCH("NoSQL",K66)),1,0)) -> 0 | X66: =IF(ISBLANK(K66),0,IF(ISNUMBER(SEARCH("Data Modeling",K66)),1,0)) -> 0 | Y66: =IF(ISBLANK(K66),0,IF(ISNUMBER(SEARCH("Pandas",K66)),1,0)) -> 0 | Z66: =IF(ISBLANK(K66),0,IF(ISNUMBER(SEARCH("Numpy",K66)),1,0)) -> 0 | AA66: =IF(ISBLANK(K66),0,IF(ISNUMBER(SEARCH("Pyspark",K66)),1,0)) -> 0 | AB66: =IF(ISBLANK(K66),0,IF(ISNUMBER(SEARCH("Hadoop",K66)),1,0)) -> 0 | AC66: =IF(ISBLANK(K66),0,IF(ISNUMBER(SEARCH("ETL",K66)),1,0)) -> 0 | AD66: =IF(ISBLANK(K66),0,IF(ISNUMBER(SEARCH("Azure",K66)),1,0)) -> 0 | AE66: =IF(ISBLANK(K66),0,IF(ISNUMBER(SEARCH("Databricks",K66)),1,0)) -> 0 | AF66: =IF(ISBLANK(K66),0,IF(ISNUMBER(SEARCH("A/B Testing",K66)),1,0)) -> 0 | AG66: =IF(ISBLANK(K66),0,IF(ISNUMBER(SEARCH("Snowflake",K66)),1,0)) -> 0 | AH66: =IF(ISBLANK(K66),0,IF(ISNUMBER(SEARCH("Agile",K66)),1,0)) -> 0 | AI66: =IF(ISBLANK(K66),0,IF(ISNUMBER(SEARCH("Jira",K66)),1,0)) -> 0 | AJ66: =IF(ISBLANK(K66),0,IF(ISNUMBER(SEARCH("Git",K66)),1,0)) -> 0 | AK66: =IF(ISBLANK(K66),0,IF(ISNUMBER(SEARCH("Reporting",K66)),1,0)) -> 0 | AL66: =IF(ISBLANK(K66),0,IF(ISNUMBER(SEARCH("CI/CD",K66)),1,0)) -> 0 | AM66: =IF(ISBLANK(L66),0,IF(ISNUMBER(SEARCH("Python",L66)),1,0)) -> 0 | AN66: =IF(ISBLANK(L66),0,IF(ISNUMBER(SEARCH("SQL",L66)),1,0)) -> 0 | AO66: =IF(ISBLANK(L66),0,IF(ISNUMBER(SEARCH("Airflow",L66)),1,0)) -> 0 | AP66: =IF(ISBLANK(L66),0,IF(ISNUMBER(SEARCH("Kafka",L66)),1,0)) -> 0 | AQ66: =IF(ISBLANK(L66),0,IF(ISNUMBER(SEARCH("ML",L66)),1,0)) -> 0 | AR66: =IF(ISBLANK(L67),0,IF(ISNUMBER(SEARCH("ML",L67)),1,0)) -> 0 | AS66: =IF(ISBLANK(L68),0,IF(ISNUMBER(SEARCH("Docker",L68)),1,0)) -> 0 | AT66: =IF(ISBLANK(L68),0,IF(ISNUMBER(SEARCH("dbt",L68)),1,0)) -> 0 | AU66: =IF(ISBLANK(L68),0,IF(ISNUMBER(SEARCH("AWS",L68)),1,0)) -> 0 | AV66: =IF(ISBLANK(L68),0,IF(ISNUMBER(SEARCH("GCP",L68)),1,0)) -> 0 | AW66: =IF(ISBLANK(L68),0,IF(ISNUMBER(SEARCH("Azure",L68)),1,0)) -> 0 | AX66: =IF(ISBLANK(M68),0,IF(ISNUMBER(SEARCH("Tableau",L68)),1,0)) -> 0 | AY66: =IF(ISBLANK(N68),0,IF(ISNUMBER(SEARCH("PowerBI",L68)),1,0)) -> 0 | AZ66: Fulltime
A67: 66 | B67: 46178 | C67: LinkedIn | D67: BI Developer | E67: Precision for Medicine | F67: Bengaluru | G67: 3 | H67: 5 | I67: ND | J67: ND | K67: PowerBI,SQL,Data modeling | L67: Data Visualization, Azure data tools | M67: On-site | N67: Medium | O67: =IF(ISBLANK(K67),0,IF(ISNUMBER(SEARCH("sql",K67)),1,0)) -> 1 | P67: =IF(ISBLANK(K67),0,IF(ISNUMBER(SEARCH("Python",K67)),1,0)) -> 0 | Q67: =IF(ISBLANK(K67),0,IF(ISNUMBER(SEARCH("PowerBI",K67)),1,0)) -> 1 | R67: =IF(ISBLANK(K67),0,IF(ISNUMBER(SEARCH("Tableau",K67)),1,0)) -> 0 | S67: =IF(ISBLANK(K67),0,IF(ISNUMBER(SEARCH("Excel",K67)),1,0)) -> 0 | T67: =IF(ISBLANK(K67),0,IF(ISNUMBER(SEARCH("Statistics",K67)),1,0)) -> 0 | U67: =IF(ISBLANK(K67),0,IF(ISNUMBER(SEARCH("AWS",K67)),1,0)) -> 0 | V67: =IF(ISBLANK(K67),0,IF(ISNUMBER(SEARCH("GCP",K67)),1,0)) -> 0 | W67: =IF(ISBLANK(K67),0,IF(ISNUMBER(SEARCH("NoSQL",K67)),1,0)) -> 0 | X67: =IF(ISBLANK(K67),0,IF(ISNUMBER(SEARCH("Data Modeling",K67)),1,0)) -> 1 | Y67: =IF(ISBLANK(K67),0,IF(ISNUMBER(SEARCH("Pandas",K67)),1,0)) -> 0 | Z67: =IF(ISBLANK(K67),0,IF(ISNUMBER(SEARCH("Numpy",K67)),1,0)) -> 0 | AA67: =IF(ISBLANK(K67),0,IF(ISNUMBER(SEARCH("Pyspark",K67)),1,0)) -> 0 | AB67: =IF(ISBLANK(K67),0,IF(ISNUMBER(SEARCH("Hadoop",K67)),1,0)) -> 0 | AC67: =IF(ISBLANK(K67),0,IF(ISNUMBER(SEARCH("ETL",K67)),1,0)) -> 0 | AD67: =IF(ISBLANK(K67),0,IF(ISNUMBER(SEARCH("Azure",K67)),1,0)) -> 0 | AE67: =IF(ISBLANK(K67),0,IF(ISNUMBER(SEARCH("Databricks",K67)),1,0)) -> 0 | AF67: =IF(ISBLANK(K67),0,IF(ISNUMBER(SEARCH("A/B Testing",K67)),1,0)) -> 0 | AG67: =IF(ISBLANK(K67),0,IF(ISNUMBER(SEARCH("Snowflake",K67)),1,0)) -> 0 | AH67: =IF(ISBLANK(K67),0,IF(ISNUMBER(SEARCH("Agile",K67)),1,0)) -> 0 | AI67: =IF(ISBLANK(K67),0,IF(ISNUMBER(SEARCH("Jira",K67)),1,0)) -> 0 | AJ67: =IF(ISBLANK(K67),0,IF(ISNUMBER(SEARCH("Git",K67)),1,0)) -> 0 | AK67: =IF(ISBLANK(K67),0,IF(ISNUMBER(SEARCH("Reporting",K67)),1,0)) -> 0 | AL67: =IF(ISBLANK(K67),0,IF(ISNUMBER(SEARCH("CI/CD",K67)),1,0)) -> 0 | AM67: =IF(ISBLANK(L67),0,IF(ISNUMBER(SEARCH("Python",L67)),1,0)) -> 0 | AN67: =IF(ISBLANK(L67),0,IF(ISNUMBER(SEARCH("SQL",L67)),1,0)) -> 0 | AO67: =IF(ISBLANK(L67),0,IF(ISNUMBER(SEARCH("Airflow",L67)),1,0)) -> 0 | AP67: =IF(ISBLANK(L67),0,IF(ISNUMBER(SEARCH("Kafka",L67)),1,0)) -> 0 | AQ67: =IF(ISBLANK(L67),0,IF(ISNUMBER(SEARCH("ML",L67)),1,0)) -> 0 | AR67: =IF(ISBLANK(L68),0,IF(ISNUMBER(SEARCH("ML",L68)),1,0)) -> 0 | AS67: =IF(ISBLANK(L69),0,IF(ISNUMBER(SEARCH("Docker",L69)),1,0)) -> 0 | AT67: =IF(ISBLANK(L69),0,IF(ISNUMBER(SEARCH("dbt",L69)),1,0)) -> 0 | AU67: =IF(ISBLANK(L69),0,IF(ISNUMBER(SEARCH("AWS",L69)),1,0)) -> 0 | AV67: =IF(ISBLANK(L69),0,IF(ISNUMBER(SEARCH("GCP",L69)),1,0)) -> 0 | AW67: =IF(ISBLANK(L69),0,IF(ISNUMBER(SEARCH("Azure",L69)),1,0)) -> 0 | AX67: =IF(ISBLANK(M69),0,IF(ISNUMBER(SEARCH("Tableau",L69)),1,0)) -> 0 | AY67: =IF(ISBLANK(N69),0,IF(ISNUMBER(SEARCH("PowerBI",L69)),1,0)) -> 0 | AZ67: Fulltime
A68: 67 | B68: 46178 | C68: LinkedIn | D68: BI Developer | E68: ProcDNA | F68: Gurgaon | G68: 1 | H68: 5 | I68: ND | J68: ND | K68: PowerBI,SQL, Data visualization | L68: None | M68: On-site | N68: Medium | O68: =IF(ISBLANK(K68),0,IF(ISNUMBER(SEARCH("sql",K68)),1,0)) -> 1 | P68: =IF(ISBLANK(K68),0,IF(ISNUMBER(SEARCH("Python",K68)),1,0)) -> 0 | Q68: =IF(ISBLANK(K68),0,IF(ISNUMBER(SEARCH("PowerBI",K68)),1,0)) -> 1 | R68: =IF(ISBLANK(K68),0,IF(ISNUMBER(SEARCH("Tableau",K68)),1,0)) -> 0 | S68: =IF(ISBLANK(K68),0,IF(ISNUMBER(SEARCH("Excel",K68)),1,0)) -> 0 | T68: =IF(ISBLANK(K68),0,IF(ISNUMBER(SEARCH("Statistics",K68)),1,0)) -> 0 | U68: =IF(ISBLANK(K68),0,IF(ISNUMBER(SEARCH("AWS",K68)),1,0)) -> 0 | V68: =IF(ISBLANK(K68),0,IF(ISNUMBER(SEARCH("GCP",K68)),1,0)) -> 0 | W68: =IF(ISBLANK(K68),0,IF(ISNUMBER(SEARCH("NoSQL",K68)),1,0)) -> 0 | X68: =IF(ISBLANK(K68),0,IF(ISNUMBER(SEARCH("Data Modeling",K68)),1,0)) -> 0 | Y68: =IF(ISBLANK(K68),0,IF(ISNUMBER(SEARCH("Pandas",K68)),1,0)) -> 0 | Z68: =IF(ISBLANK(K68),0,IF(ISNUMBER(SEARCH("Numpy",K68)),1,0)) -> 0 | AA68: =IF(ISBLANK(K68),0,IF(ISNUMBER(SEARCH("Pyspark",K68)),1,0)) -> 0 | AB68: =IF(ISBLANK(K68),0,IF(ISNUMBER(SEARCH("Hadoop",K68)),1,0)) -> 0 | AC68: =IF(ISBLANK(K68),0,IF(ISNUMBER(SEARCH("ETL",K68)),1,0)) -> 0 | AD68: =IF(ISBLANK(K68),0,IF(ISNUMBER(SEARCH("Azure",K68)),1,0)) -> 0 | AE68: =IF(ISBLANK(K68),0,IF(ISNUMBER(SEARCH("Databricks",K68)),1,0)) -> 0 | AF68: =IF(ISBLANK(K68),0,IF(ISNUMBER(SEARCH("A/B Testing",K68)),1,0)) -> 0 | AG68: =IF(ISBLANK(K68),0,IF(ISNUMBER(SEARCH("Snowflake",K68)),1,0)) -> 0 | AH68: =IF(ISBLANK(K68),0,IF(ISNUMBER(SEARCH("Agile",K68)),1,0)) -> 0 | AI68: =IF(ISBLANK(K68),0,IF(ISNUMBER(SEARCH("Jira",K68)),1,0)) -> 0 | AJ68: =IF(ISBLANK(K68),0,IF(ISNUMBER(SEARCH("Git",K68)),1,0)) -> 0 | AK68: =IF(ISBLANK(K68),0,IF(ISNUMBER(SEARCH("Reporting",K68)),1,0)) -> 0 | AL68: =IF(ISBLANK(K68),0,IF(ISNUMBER(SEARCH("CI/CD",K68)),1,0)) -> 0 | AM68: =IF(ISBLANK(L68),0,IF(ISNUMBER(SEARCH("Python",L68)),1,0)) -> 0 | AN68: =IF(ISBLANK(L68),0,IF(ISNUMBER(SEARCH("SQL",L68)),1,0)) -> 0 | AO68: =IF(ISBLANK(L68),0,IF(ISNUMBER(SEARCH("Airflow",L68)),1,0)) -> 0 | AP68: =IF(ISBLANK(L68),0,IF(ISNUMBER(SEARCH("Kafka",L68)),1,0)) -> 0 | AQ68: =IF(ISBLANK(L68),0,IF(ISNUMBER(SEARCH("ML",L68)),1,0)) -> 0 | AR68: =IF(ISBLANK(L69),0,IF(ISNUMBER(SEARCH("ML",L69)),1,0)) -> 0 | AS68: =IF(ISBLANK(L70),0,IF(ISNUMBER(SEARCH("Docker",L70)),1,0)) -> 0 | AT68: =IF(ISBLANK(L70),0,IF(ISNUMBER(SEARCH("dbt",L70)),1,0)) -> 0 | AU68: =IF(ISBLANK(L70),0,IF(ISNUMBER(SEARCH("AWS",L70)),1,0)) -> 1 | AV68: =IF(ISBLANK(L70),0,IF(ISNUMBER(SEARCH("GCP",L70)),1,0)) -> 0 | AW68: =IF(ISBLANK(L70),0,IF(ISNUMBER(SEARCH("Azure",L70)),1,0)) -> 0 | AX68: =IF(ISBLANK(M70),0,IF(ISNUMBER(SEARCH("Tableau",L70)),1,0)) -> 0 | AY68: =IF(ISBLANK(N70),0,IF(ISNUMBER(SEARCH("PowerBI",L70)),1,0)) -> 0 | AZ68: Fulltime
A69: 68 | B69: 46178 | C69: LinkedIn | D69: BI Developer | E69: Quest Global | F69: Bengaluru | G69: 3 | H69: 5 | I69: ND | J69: ND | K69: Tableau, SQL,ETL | L69: None | M69: On-site | N69: Small | O69: =IF(ISBLANK(K69),0,IF(ISNUMBER(SEARCH("sql",K69)),1,0)) -> 1 | P69: =IF(ISBLANK(K69),0,IF(ISNUMBER(SEARCH("Python",K69)),1,0)) -> 0 | Q69: =IF(ISBLANK(K69),0,IF(ISNUMBER(SEARCH("PowerBI",K69)),1,0)) -> 0 | R69: =IF(ISBLANK(K69),0,IF(ISNUMBER(SEARCH("Tableau",K69)),1,0)) -> 1 | S69: =IF(ISBLANK(K69),0,IF(ISNUMBER(SEARCH("Excel",K69)),1,0)) -> 0 | T69: =IF(ISBLANK(K69),0,IF(ISNUMBER(SEARCH("Statistics",K69)),1,0)) -> 0 | U69: =IF(ISBLANK(K69),0,IF(ISNUMBER(SEARCH("AWS",K69)),1,0)) -> 0 | V69: =IF(ISBLANK(K69),0,IF(ISNUMBER(SEARCH("GCP",K69)),1,0)) -> 0 | W69: =IF(ISBLANK(K69),0,IF(ISNUMBER(SEARCH("NoSQL",K69)),1,0)) -> 0 | X69: =IF(ISBLANK(K69),0,IF(ISNUMBER(SEARCH("Data Modeling",K69)),1,0)) -> 0 | Y69: =IF(ISBLANK(K69),0,IF(ISNUMBER(SEARCH("Pandas",K69)),1,0)) -> 0 | Z69: =IF(ISBLANK(K69),0,IF(ISNUMBER(SEARCH("Numpy",K69)),1,0)) -> 0 | AA69: =IF(ISBLANK(K69),0,IF(ISNUMBER(SEARCH("Pyspark",K69)),1,0)) -> 0 | AB69: =IF(ISBLANK(K69),0,IF(ISNUMBER(SEARCH("Hadoop",K69)),1,0)) -> 0 | AC69: =IF(ISBLANK(K69),0,IF(ISNUMBER(SEARCH("ETL",K69)),1,0)) -> 1 | AD69: =IF(ISBLANK(K69),0,IF(ISNUMBER(SEARCH("Azure",K69)),1,0)) -> 0 | AE69: =IF(ISBLANK(K69),0,IF(ISNUMBER(SEARCH("Databricks",K69)),1,0)) -> 0 | AF69: =IF(ISBLANK(K69),0,IF(ISNUMBER(SEARCH("A/B Testing",K69)),1,0)) -> 0 | AG69: =IF(ISBLANK(K69),0,IF(ISNUMBER(SEARCH("Snowflake",K69)),1,0)) -> 0 | AH69: =IF(ISBLANK(K69),0,IF(ISNUMBER(SEARCH("Agile",K69)),1,0)) -> 0 | AI69: =IF(ISBLANK(K69),0,IF(ISNUMBER(SEARCH("Jira",K69)),1,0)) -> 0 | AJ69: =IF(ISBLANK(K69),0,IF(ISNUMBER(SEARCH("Git",K69)),1,0)) -> 0 | AK69: =IF(ISBLANK(K69),0,IF(ISNUMBER(SEARCH("Reporting",K69)),1,0)) -> 0 | AL69: =IF(ISBLANK(K69),0,IF(ISNUMBER(SEARCH("CI/CD",K69)),1,0)) -> 0 | AM69: =IF(ISBLANK(L69),0,IF(ISNUMBER(SEARCH("Python",L69)),1,0)) -> 0 | AN69: =IF(ISBLANK(L69),0,IF(ISNUMBER(SEARCH("SQL",L69)),1,0)) -> 0 | AO69: =IF(ISBLANK(L69),0,IF(ISNUMBER(SEARCH("Airflow",L69)),1,0)) -> 0 | AP69: =IF(ISBLANK(L69),0,IF(ISNUMBER(SEARCH("Kafka",L69)),1,0)) -> 0 | AQ69: =IF(ISBLANK(L69),0,IF(ISNUMBER(SEARCH("ML",L69)),1,0)) -> 0 | AR69: =IF(ISBLANK(L70),0,IF(ISNUMBER(SEARCH("ML",L70)),1,0)) -> 1 | AS69: =IF(ISBLANK(L71),0,IF(ISNUMBER(SEARCH("Docker",L71)),1,0)) -> 0 | AT69: =IF(ISBLANK(L71),0,IF(ISNUMBER(SEARCH("dbt",L71)),1,0)) -> 0 | AU69: =IF(ISBLANK(L71),0,IF(ISNUMBER(SEARCH("AWS",L71)),1,0)) -> 0 | AV69: =IF(ISBLANK(L71),0,IF(ISNUMBER(SEARCH("GCP",L71)),1,0)) -> 0 | AW69: =IF(ISBLANK(L71),0,IF(ISNUMBER(SEARCH("Azure",L71)),1,0)) -> 1 | AX69: =IF(ISBLANK(M71),0,IF(ISNUMBER(SEARCH("Tableau",L71)),1,0)) -> 0 | AY69: =IF(ISBLANK(N71),0,IF(ISNUMBER(SEARCH("PowerBI",L71)),1,0)) -> 0 | AZ69: Fulltime
A70: 69 | B70: 46178 | C70: LinkedIn | D70: BI Developer | E70: Koch | F70: Bengaluru | G70: 3 | H70: ND | I70: ND | J70: ND | K70: PowerBI,ETL,SQL | L70: Python,AWS,MLOps,LLMOps,Databricks | M70: On-site | N70: Medium | O70: =IF(ISBLANK(K70),0,IF(ISNUMBER(SEARCH("sql",K70)),1,0)) -> 1 | P70: =IF(ISBLANK(K70),0,IF(ISNUMBER(SEARCH("Python",K70)),1,0)) -> 0 | Q70: =IF(ISBLANK(K70),0,IF(ISNUMBER(SEARCH("PowerBI",K70)),1,0)) -> 1 | R70: =IF(ISBLANK(K70),0,IF(ISNUMBER(SEARCH("Tableau",K70)),1,0)) -> 0 | S70: =IF(ISBLANK(K70),0,IF(ISNUMBER(SEARCH("Excel",K70)),1,0)) -> 0 | T70: =IF(ISBLANK(K70),0,IF(ISNUMBER(SEARCH("Statistics",K70)),1,0)) -> 0 | U70: =IF(ISBLANK(K70),0,IF(ISNUMBER(SEARCH("AWS",K70)),1,0)) -> 0 | V70: =IF(ISBLANK(K70),0,IF(ISNUMBER(SEARCH("GCP",K70)),1,0)) -> 0 | W70: =IF(ISBLANK(K70),0,IF(ISNUMBER(SEARCH("NoSQL",K70)),1,0)) -> 0 | X70: =IF(ISBLANK(K70),0,IF(ISNUMBER(SEARCH("Data Modeling",K70)),1,0)) -> 0 | Y70: =IF(ISBLANK(K70),0,IF(ISNUMBER(SEARCH("Pandas",K70)),1,0)) -> 0 | Z70: =IF(ISBLANK(K70),0,IF(ISNUMBER(SEARCH("Numpy",K70)),1,0)) -> 0 | AA70: =IF(ISBLANK(K70),0,IF(ISNUMBER(SEARCH("Pyspark",K70)),1,0)) -> 0 | AB70: =IF(ISBLANK(K70),0,IF(ISNUMBER(SEARCH("Hadoop",K70)),1,0)) -> 0 | AC70: =IF(ISBLANK(K70),0,IF(ISNUMBER(SEARCH("ETL",K70)),1,0)) -> 1 | AD70: =IF(ISBLANK(K70),0,IF(ISNUMBER(SEARCH("Azure",K70)),1,0)) -> 0 | AE70: =IF(ISBLANK(K70),0,IF(ISNUMBER(SEARCH("Databricks",K70)),1,0)) -> 0 | AF70: =IF(ISBLANK(K70),0,IF(ISNUMBER(SEARCH("A/B Testing",K70)),1,0)) -> 0 | AG70: =IF(ISBLANK(K70),0,IF(ISNUMBER(SEARCH("Snowflake",K70)),1,0)) -> 0 | AH70: =IF(ISBLANK(K70),0,IF(ISNUMBER(SEARCH("Agile",K70)),1,0)) -> 0 | AI70: =IF(ISBLANK(K70),0,IF(ISNUMBER(SEARCH("Jira",K70)),1,0)) -> 0 | AJ70: =IF(ISBLANK(K70),0,IF(ISNUMBER(SEARCH("Git",K70)),1,0)) -> 0 | AK70: =IF(ISBLANK(K70),0,IF(ISNUMBER(SEARCH("Reporting",K70)),1,0)) -> 0 | AL70: =IF(ISBLANK(K70),0,IF(ISNUMBER(SEARCH("CI/CD",K70)),1,0)) -> 0 | AM70: =IF(ISBLANK(L70),0,IF(ISNUMBER(SEARCH("Python",L70)),1,0)) -> 1 | AN70: =IF(ISBLANK(L70),0,IF(ISNUMBER(SEARCH("SQL",L70)),1,0)) -> 0 | AO70: =IF(ISBLANK(L70),0,IF(ISNUMBER(SEARCH("Airflow",L70)),1,0)) -> 0 | AP70: =IF(ISBLANK(L70),0,IF(ISNUMBER(SEARCH("Kafka",L70)),1,0)) -> 0 | AQ70: =IF(ISBLANK(L70),0,IF(ISNUMBER(SEARCH("ML",L70)),1,0)) -> 1 | AR70: =IF(ISBLANK(L71),0,IF(ISNUMBER(SEARCH("ML",L71)),1,0)) -> 0 | AS70: =IF(ISBLANK(L72),0,IF(ISNUMBER(SEARCH("Docker",L72)),1,0)) -> 0 | AT70: =IF(ISBLANK(L72),0,IF(ISNUMBER(SEARCH("dbt",L72)),1,0)) -> 0 | AU70: =IF(ISBLANK(L72),0,IF(ISNUMBER(SEARCH("AWS",L72)),1,0)) -> 0 | AV70: =IF(ISBLANK(L72),0,IF(ISNUMBER(SEARCH("GCP",L72)),1,0)) -> 0 | AW70: =IF(ISBLANK(L72),0,IF(ISNUMBER(SEARCH("Azure",L72)),1,0)) -> 0 | AX70: =IF(ISBLANK(M72),0,IF(ISNUMBER(SEARCH("Tableau",L72)),1,0)) -> 0 | AY70: =IF(ISBLANK(N72),0,IF(ISNUMBER(SEARCH("PowerBI",L72)),1,0)) -> 0 | AZ70: Fulltime
